Workbook

Sheet Inputs
A1: Cap table - HTGC V1.0 Feb 2010
A2: Hercules Technology Growth Capital
A3: Inputs For Capitalization Table
G4: (User Inputs Blue Text & Numbers)
H6: Company Name: | I6: Company Name
H7: Cap Table Date: | I7: 39813
D8: Capitalization Of Company Since Inception
D9: Name of Round Closed | E9: Date Round Closed | F9: Post-Money | G9: Preference Multiple | H9: Cap | I9: Seniority Rank | J9: Conv. Ratio | K9: Price Per Share | L9: Total Raised | M9: Shares Issued | N9: Warrants Issued | O9: Strike Price
D10: Series A | E10: 39113 | F10: 0 | G10: 1 | H10: 2 | I10: 10 | J10: 1 | K10: 1 | L10: 5000000 | M10: =IFERROR(L10/K10,"") -> 5000000 | N10: 10000 | O10: 1
D11: Series B | E11: =E10+365 -> 39478 | F11: 0 | G11: 1 | H11: 2 | I11: 10 | J11: 1 | K11: 2 | L11: 10000000 | M11: =IFERROR(L11/K11,"") -> 5000000 | N11: 10000 | O11: 1
D12: Series C | E12: =E11+365 -> 39843 | F12: 0 | G12: 1 | H12: 2 | I12: 2 | J12: 1 | K12: 2.5 | L12: 15000000 | M12: =IFERROR(L12/K12,"") -> 6000000 | N12: 10000 | O12: 1
D13: Series D | E13: =E12 -> 39843 | F13: 0 | G13: 1 | H13: 2 | I13: 1 | J13: 1 | K13: 2 | L13: 20000000 | M13: =IFERROR(L13/K13,"") -> 10000000 | N13: 10000 | O13: 1
D14: - | E14: =E13 -> 39843 | F14: 0 | G14: 1 | H14: 2 | I14: 10 | J14: 1 | K14: 0 | L14: 0 | M14: =IFERROR(L14/K14,"") | N14: 0 | O14: 0
D15: - | E15: =E14 -> 39843 | F15: 0 | G15: 1 | H15: 2 | I15: 10 | J15: 1 | K15: 0 | L15: 0 | M15: =IFERROR(L15/K15,"") | N15: 0 | O15: 0
D16: - | E16: =E15 -> 39843 | F16: 0 | G16: 1 | H16: 2 | I16: 10 | J16: 1 | K16: 0 | L16: 0 | M16: =IFERROR(L16/K16,"") | N16: 0 | O16: 0
D17: - | E17: =E16 -> 39843 | F17: 0 | G17: 1 | H17: 2 | I17: 10 | J17: 1 | K17: 0 | L17: 0 | M17: =IFERROR(L17/K17,"") | N17: 0 | O17: 0
D18: - | E18: =E17 -> 39843 | F18: 0 | G18: 1 | H18: 2 | I18: 10 | J18: 1 | K18: 0 | L18: 0 | M18: =IFERROR(L18/K18,"") | N18: 0 | O18: 0
D19: - | E19: =E18 -> 39843 | F19: 0 | G19: 1 | H19: 2 | I19: 10 | J19: 1 | K19: 0 | L19: 0 | M19: =IFERROR(L19/K19,"") | N19: 0 | O19: 0
D20: Warrants | L20: =N10*O10+N11*O11+N12*O12+N13*O13+N14*O14+N15*O15+N16*O16+N17*O17+N18*O18+N19*O19 -> 40000 | M20: =N21 -> 40000 | O20: =N20*P20 -> 0
D21: Subtotal Of All Preferred | L21: =SUM(L10:L20) -> 50040000 | M21: =SUM(M10:M20) -> 26040000 | N21: =SUM(N10:N20) -> 40000
D22: Common Shares Issued | K22: 1e-08 | L22: =M22*K22 -> 0.052 | M22: 5200000
D23: Options (Vested + Authorized) | K23: 1e-07 | L23: =0 -> 0 | M23: 0
D24: Subtotal Of All Common + Options | L24: =SUM(L22:L23) -> 0.052 | M24: =SUM(M22:M23) -> 5200000
D26: TOTALS | L26: =L24+L21 -> 50040000 | M26: =M24+M21 -> 31240000 | N26: =N21+N24 -> 40000
D29: Current Investors - # of Shares Per Round
D30: Investor/Series | E30: Coverage Partner | F30: {=IF(TRANSPOSE(D10:D19)="","",TRANSPOSE(D10:D19))} -> Series A | G30: Series B | H30: Series C | I30: Series D | J30: - | K30: - | L30: - | M30: - | N30: - | O30: - | P30: Common | Q30: Options | R30: TOTAL
D31: HTGC | F31: 1000000 | G31: 1000000 | H31: 0 | I31: 0 | J31: 0 | K31: 0 | L31: 0 | M31: 0 | N31: 0 | O31: 0 | P31: 0 | Q31: 0 | R31: =SUM(F31:Q31) -> 2000000
D32: Inv B | F32: 1000000 | G32: 1000000 | H32: 0 | I32: 0 | J32: 0 | K32: 0 | L32: 0 | M32: 0 | N32: 0 | O32: 0 | P32: 0 | Q32: 0 | R32: =SUM(F32:Q32) -> 2000000
D33: Inv C | F33: 1000000 | G33: 1000000 | H33: 1000000 | I33: 0 | J33: 0 | K33: 0 | L33: 0 | M33: 0 | N33: 0 | O33: 0 | P33: 0 | Q33: 0 | R33: =SUM(F33:Q33) -> 3000000
D34: Inv D | F34: 1000000 | G34: 1000000 | H34: 1000000 | I34: 0 | J34: 0 | K34: 0 | L34: 0 | M34: 0 | N34: 0 | O34: 0 | P34: 0 | Q34: 0 | R34: =SUM(F34:Q34) -> 3000000
D35: Inv E | F35: 1000000 | G35: 1000000 | H35: 1000000 | I35: 0 | J35: 0 | K35: 0 | L35: 0 | M35: 0 | N35: 0 | O35: 0 | P35: 0 | Q35: 0 | R35: =SUM(F35:Q35) -> 3000000
D36: Inv F | F36: 0 | G36: 0 | H36: 1000000 | I36: =10000000/3 -> 3333333.3 | J36: 0 | K36: 0 | L36: 0 | M36: 0 | N36: 0 | O36: 0 | P36: 0 | Q36: 0 | R36: =SUM(F36:Q36) -> 4333333.3
D37: Inv G | F37: 0 | G37: 0 | H37: 1000000 | I37: =10000000/3 -> 3333333.3 | J37: 0 | K37: 0 | L37: 0 | M37: 0 | N37: 0 | O37: 0 | P37: 0 | Q37: 0 | R37: =SUM(F37:Q37) -> 4333333.3
D38: Inv H | F38: 0 | G38: 0 | H38: 1000000 | I38: =10000000/3 -> 3333333.3 | J38: 0 | K38: 0 | L38: 0 | M38: 0 | N38: 0 | O38: 0 | P38: 0 | Q38: 0 | R38: =SUM(F38:Q38) -> 4333333.3
D39: Other Investors | F39: 0 | G39: 0 | H39: 0 | I39: 0 | J39: 0 | K39: 0 | L39: 0 | M39: 0 | N39: 0 | O39: 0 | P39: 0 | Q39: 0 | R39: =SUM(F39:Q39) -> 0
D40: Management | P40: 5200000 | Q40: =M23 -> 0 | R40: =SUM(F40:Q40) -> 5200000
D41: Warrants | F41: {=TRANSPOSE(N10:N20)} -> 10000 | G41: 10000 | H41: 10000 | I41: 10000 | J41: 0 | K41: 0 | L41: 0 | M41: 0 | N41: 0 | O41: 0 | R41: =SUM(F41:O41) -> 40000
D42: TOTALS | F42: =IF(SUM(F31:F40)=0,"",SUM(F31:F40)) -> 5000000 | G42: =IF(SUM(G31:G40)=0,"",SUM(G31:G40)) -> 5000000 | H42: =IF(SUM(H31:H40)=0,"",SUM(H31:H40)) -> 6000000 | I42: =IF(SUM(I31:I40)=0,"",SUM(I31:I40)) -> 10000000 | J42: =IF(SUM(J31:J40)=0,"",SUM(J31:J40)) | K42: =IF(SUM(K31:K40)=0,"",SUM(K31:K40)) | L42: =IF(SUM(L31:L40)=0,"",SUM(L31:L40)) | M42: =IF(SUM(M31:M40)=0,"",SUM(M31:M40)) | ... Q42: =IF(SUM(Q31:Q40)=0,"",SUM(Q31:Q40)) | R42: =SUM(R31:R41) -> 31240000
D44: Footnotes (must be manually asterisked in row D10:D19 and D31:D38)
D45: *
D46: **
D47: ***
D48: ****

Sheet Pro Forma Cap Table
B1: =Inputs!I6 -> Company Name
B2: Pro Forma Capitalization Table
B3: =Inputs!I7 -> 39813
F5: {=IF(TRANSPOSE(Inputs!E$10:E$19)=0,"",TRANSPOSE(Inputs!E$10:E$19))} -> 39113 | G5: 39478 | H5: 39843 | I5: 39843 | J5: 39843 | K5: 39843 | L5: 39843 | M5: 39843 | N5: 39843 | O5: 39843
C6: Common | D6: Stock | E6: Total | F6: {=IF(TRANSPOSE(Inputs!D$10:D$19)=0,"",TRANSPOSE(Inputs!D$10:D$19))} -> Series A | G6: Series B | H6: Series C | I6: Series D | J6: - | K6: - | L6: - | M6: - | N6: - | O6: - | P6: Total | Q6: Total # | R6: Total Ful. Dil | S6: Ful. Dil. as Conv. | T6: Total
B7: Investor (Partner) | C7: =Inputs!K22 -> 1e-08 | D7: =Inputs!K23 -> 1e-07 | E7: Common | F7: {=IF(TRANSPOSE(Inputs!K$10:K$19)=0,0,TRANSPOSE(Inputs!K$10:K$19))} -> 1 | G7: 2 | H7: 2.5 | I7: 2 | J7: 0 | K7: 0 | L7: 0 | M7: 0 | N7: 0 | O7: 0 | P7: Preferred | Q7: Of All | R7: Ownership | S7: Ownership | T7: Dollars ($)
C8: Shares | D8: Options | E8: & Options | F8: =IF(F7=0,"","Preferred") -> Preferred | G8: =IF(G7=0,"","Preferred") -> Preferred | H8: =IF(H7=0,"","Preferred") -> Preferred | I8: =IF(I7=0,"","Preferred") -> Preferred | J8: =IF(J7=0,"","Preferred") | K8: =IF(K7=0,"","Preferred") | L8: =IF(L7=0,"","Preferred") | M8: =IF(M7=0,"","Preferred") | ... O8: =IF(O7=0,"","Preferred") | P8: Shares | Q8: Shares Held | R8: Percent (%) | S8: Percent (%) | T8: Invested
C9: <------------------------------------------------------------------------------------------------------------------- # of Shares ------------------------------------------------------------------------------------------------------------------->
B10: =IF(Inputs!E31=0,Inputs!D31,CONCATENATE(Inputs!D31," (",Inputs!E31,")")) -> HTGC | C10: =IF(C$7="",0,Inputs!P31) -> 0 | D10: =IF(D$7="",0,Inputs!Q31) -> 0 | E10: =SUM(C10:D10) -> 0 | F10: =IF(F$7="",0,Inputs!F31) -> 1000000 | G10: =IF(G$7="",0,Inputs!G31) -> 1000000 | H10: =IF(H$7="",0,Inputs!H31) -> 0 | I10: =IF(I$7="",0,Inputs!I31) -> 0 | J10: =IF(J$7="",0,Inputs!J31) -> 0 | K10: =IF(K$7="",0,Inputs!K31) -> 0 | L10: =IF(L$7="",0,Inputs!L31) -> 0 | M10: =IF(M$7="",0,Inputs!M31) -> 0 | ... O10: =IF(O$7="",0,Inputs!O31) -> 0 | P10: =SUM(F10:O10) -> 2000000 | Q10: =P10+E10 -> 2000000 | R10: =Q10/Q$26 -> 0.064020487 | S10: =(F10*$F$51+G10*$G$51+H10*$H$51+I10*$I$51+J10*$J$51+K10*$K$51+L10*$L$51+M10*$M$51+N10*$N$51+O10*$O$51+E10)/($F$53+$E$26) -> 0.064020487 | T10: =$F$7*F10+$G$7*G10+$H$7*H10+$I$7*I10+$J$7*J10+$K$7*K10+$L$7*L10+$M$7*M10+$N$7*N10+$O$7*O10 -> 3000000
B11: =IF(Inputs!E32=0,Inputs!D32,CONCATENATE(Inputs!D32," (",Inputs!E32,")")) -> Inv B | C11: =IF(C$7="",0,Inputs!P32) -> 0 | D11: =IF(D$7="",0,Inputs!Q32) -> 0 | E11: =SUM(C11:D11) -> 0 | F11: =IF(F$7="",0,Inputs!F32) -> 1000000 | G11: =IF(G$7="",0,Inputs!G32) -> 1000000 | H11: =IF(H$7="",0,Inputs!H32) -> 0 | I11: =IF(I$7="",0,Inputs!I32) -> 0 | J11: =IF(J$7="",0,Inputs!J32) -> 0 | K11: =IF(K$7="",0,Inputs!K32) -> 0 | L11: =IF(L$7="",0,Inputs!L32) -> 0 | M11: =IF(M$7="",0,Inputs!M32) -> 0 | ... O11: =IF(O$7="",0,Inputs!O32) -> 0 | P11: =SUM(F11:O11) -> 2000000 | Q11: =P11+E11 -> 2000000 | R11: =Q11/Q$26 -> 0.064020487 | S11: =(F11*$F$51+G11*$G$51+H11*$H$51+I11*$I$51+J11*$J$51+K11*$K$51+L11*$L$51+M11*$M$51+N11*$N$51+O11*$O$51+E11)/($F$53+$E$26) -> 0.064020487 | T11: =$F$7*F11+$G$7*G11+$H$7*H11+$I$7*I11+$J$7*J11+$K$7*K11+$L$7*L11+$M$7*M11+$N$7*N11+$O$7*O11 -> 3000000
B12: =IF(Inputs!E33=0,Inputs!D33,CONCATENATE(Inputs!D33," (",Inputs!E33,")")) -> Inv C | C12: =IF(C$7="",0,Inputs!P33) -> 0 | D12: =IF(D$7="",0,Inputs!Q33) -> 0 | E12: =SUM(C12:D12) -> 0 | F12: =IF(F$7="",0,Inputs!F33) -> 1000000 | G12: =IF(G$7="",0,Inputs!G33) -> 1000000 | H12: =IF(H$7="",0,Inputs!H33) -> 1000000 | I12: =IF(I$7="",0,Inputs!I33) -> 0 | J12: =IF(J$7="",0,Inputs!J33) -> 0 | K12: =IF(K$7="",0,Inputs!K33) -> 0 | L12: =IF(L$7="",0,Inputs!L33) -> 0 | M12: =IF(M$7="",0,Inputs!M33) -> 0 | ... O12: =IF(O$7="",0,Inputs!O33) -> 0 | P12: =SUM(F12:O12) -> 3000000 | Q12: =P12+E12 -> 3000000 | R12: =Q12/Q$26 -> 0.09603073 | S12: =(F12*$F$51+G12*$G$51+H12*$H$51+I12*$I$51+J12*$J$51+K12*$K$51+L12*$L$51+M12*$M$51+N12*$N$51+O12*$O$51+E12)/($F$53+$E$26) -> 0.09603073 | T12: =$F$7*F12+$G$7*G12+$H$7*H12+$I$7*I12+$J$7*J12+$K$7*K12+$L$7*L12+$M$7*M12+$N$7*N12+$O$7*O12 -> 5500000
B13: =IF(Inputs!E34=0,Inputs!D34,CONCATENATE(Inputs!D34," (",Inputs!E34,")")) -> Inv D | C13: =IF(C$7="",0,Inputs!P34) -> 0 | D13: =IF(D$7="",0,Inputs!Q34) -> 0 | E13: =SUM(C13:D13) -> 0 | F13: =IF(F$7="",0,Inputs!F34) -> 1000000 | G13: =IF(G$7="",0,Inputs!G34) -> 1000000 | H13: =IF(H$7="",0,Inputs!H34) -> 1000000 | I13: =IF(I$7="",0,Inputs!I34) -> 0 | J13: =IF(J$7="",0,Inputs!J34) -> 0 | K13: =IF(K$7="",0,Inputs!K34) -> 0 | L13: =IF(L$7="",0,Inputs!L34) -> 0 | M13: =IF(M$7="",0,Inputs!M34) -> 0 | ... O13: =IF(O$7="",0,Inputs!O34) -> 0 | P13: =SUM(F13:O13) -> 3000000 | Q13: =P13+E13 -> 3000000 | R13: =Q13/Q$26 -> 0.09603073 | S13: =(F13*$F$51+G13*$G$51+H13*$H$51+I13*$I$51+J13*$J$51+K13*$K$51+L13*$L$51+M13*$M$51+N13*$N$51+O13*$O$51+E13)/($F$53+$E$26) -> 0.09603073 | T13: =$F$7*F13+$G$7*G13+$H$7*H13+$I$7*I13+$J$7*J13+$K$7*K13+$L$7*L13+$M$7*M13+$N$7*N13+$O$7*O13 -> 5500000
B14: =IF(Inputs!E35=0,Inputs!D35,CONCATENATE(Inputs!D35," (",Inputs!E35,")")) -> Inv E | C14: =IF(C$7="",0,Inputs!P35) -> 0 | D14: =IF(D$7="",0,Inputs!Q35) -> 0 | E14: =SUM(C14:D14) -> 0 | F14: =IF(F$7="",0,Inputs!F35) -> 1000000 | G14: =IF(G$7="",0,Inputs!G35) -> 1000000 | H14: =IF(H$7="",0,Inputs!H35) -> 1000000 | I14: =IF(I$7="",0,Inputs!I35) -> 0 | J14: =IF(J$7="",0,Inputs!J35) -> 0 | K14: =IF(K$7="",0,Inputs!K35) -> 0 | L14: =IF(L$7="",0,Inputs!L35) -> 0 | M14: =IF(M$7="",0,Inputs!M35) -> 0 | ... O14: =IF(O$7="",0,Inputs!O35) -> 0 | P14: =SUM(F14:O14) -> 3000000 | Q14: =P14+E14 -> 3000000 | R14: =Q14/Q$26 -> 0.09603073 | S14: =(F14*$F$51+G14*$G$51+H14*$H$51+I14*$I$51+J14*$J$51+K14*$K$51+L14*$L$51+M14*$M$51+N14*$N$51+O14*$O$51+E14)/($F$53+$E$26) -> 0.09603073 | T14: =$F$7*F14+$G$7*G14+$H$7*H14+$I$7*I14+$J$7*J14+$K$7*K14+$L$7*L14+$M$7*M14+$N$7*N14+$O$7*O14 -> 5500000
B15: =IF(Inputs!E36=0,Inputs!D36,CONCATENATE(Inputs!D36," (",Inputs!E36,")")) -> Inv F | C15: =IF(C$7="",0,Inputs!P36) -> 0 | D15: =IF(D$7="",0,Inputs!Q36) -> 0 | E15: =SUM(C15:D15) -> 0 | F15: =IF(F$7="",0,Inputs!F36) -> 0 | G15: =IF(G$7="",0,Inputs!G36) -> 0 | H15: =IF(H$7="",0,Inputs!H36) -> 1000000 | I15: =IF(I$7="",0,Inputs!I36) -> 3333333.3 | J15: =IF(J$7="",0,Inputs!J36) -> 0 | K15: =IF(K$7="",0,Inputs!K36) -> 0 | L15: =IF(L$7="",0,Inputs!L36) -> 0 | M15: =IF(M$7="",0,Inputs!M36) -> 0 | ... O15: =IF(O$7="",0,Inputs!O36) -> 0 | P15: =SUM(F15:O15) -> 4333333.3 | Q15: =P15+E15 -> 4333333.3 | R15: =Q15/Q$26 -> 0.13871105 | S15: =(F15*$F$51+G15*$G$51+H15*$H$51+I15*$I$51+J15*$J$51+K15*$K$51+L15*$L$51+M15*$M$51+N15*$N$51+O15*$O$51+E15)/($F$53+$E$26) -> 0.13871105 | T15: =$F$7*F15+$G$7*G15+$H$7*H15+$I$7*I15+$J$7*J15+$K$7*K15+$L$7*L15+$M$7*M15+$N$7*N15+$O$7*O15 -> 9166666.7
B16: =IF(Inputs!E37=0,Inputs!D37,CONCATENATE(Inputs!D37," (",Inputs!E37,")")) -> Inv G | C16: =IF(C$7="",0,Inputs!P37) -> 0 | D16: =IF(D$7="",0,Inputs!Q37) -> 0 | E16: =SUM(C16:D16) -> 0 | F16: =IF(F$7="",0,Inputs!F37) -> 0 | G16: =IF(G$7="",0,Inputs!G37) -> 0 | H16: =IF(H$7="",0,Inputs!H37) -> 1000000 | I16: =IF(I$7="",0,Inputs!I37) -> 3333333.3 | J16: =IF(J$7="",0,Inputs!J37) -> 0 | K16: =IF(K$7="",0,Inputs!K37) -> 0 | L16: =IF(L$7="",0,Inputs!L37) -> 0 | M16: =IF(M$7="",0,Inputs!M37) -> 0 | ... O16: =IF(O$7="",0,Inputs!O37) -> 0 | P16: =SUM(F16:O16) -> 4333333.3 | Q16: =P16+E16 -> 4333333.3 | R16: =Q16/Q$26 -> 0.13871105 | S16: =(F16*$F$51+G16*$G$51+H16*$H$51+I16*$I$51+J16*$J$51+K16*$K$51+L16*$L$51+M16*$M$51+N16*$N$51+O16*$O$51+E16)/($F$53+$E$26) -> 0.13871105 | T16: =$F$7*F16+$G$7*G16+$H$7*H16+$I$7*I16+$J$7*J16+$K$7*K16+$L$7*L16+$M$7*M16+$N$7*N16+$O$7*O16 -> 9166666.7
B17: =IF(Inputs!E38=0,Inputs!D38,CONCATENATE(Inputs!D38," (",Inputs!E38,")")) -> Inv H | C17: =IF(C$7="",0,Inputs!P38) -> 0 | D17: =IF(D$7="",0,Inputs!Q38) -> 0 | E17: =SUM(C17:D17) -> 0 | F17: =IF(F$7="",0,Inputs!F38) -> 0 | G17: =IF(G$7="",0,Inputs!G38) -> 0 | H17: =IF(H$7="",0,Inputs!H38) -> 1000000 | I17: =IF(I$7="",0,Inputs!I38) -> 3333333.3 | J17: =IF(J$7="",0,Inputs!J38) -> 0 | K17: =IF(K$7="",0,Inputs!K38) -> 0 | L17: =IF(L$7="",0,Inputs!L38) -> 0 | M17: =IF(M$7="",0,Inputs!M38) -> 0 | ... O17: =IF(O$7="",0,Inputs!O38) -> 0 | P17: =SUM(F17:O17) -> 4333333.3 | Q17: =P17+E17 -> 4333333.3 | R17: =Q17/Q$26 -> 0.13871105 | S17: =(F17*$F$51+G17*$G$51+H17*$H$51+I17*$I$51+J17*$J$51+K17*$K$51+L17*$L$51+M17*$M$51+N17*$N$51+O17*$O$51+E17)/($F$53+$E$26) -> 0.13871105 | T17: =$F$7*F17+$G$7*G17+$H$7*H17+$I$7*I17+$J$7*J17+$K$7*K17+$L$7*L17+$M$7*M17+$N$7*N17+$O$7*O17 -> 9166666.7
B18: =Inputs!D39 -> Other Investors | C18: =IF(C$7="",0,Inputs!P39) -> 0 | D18: =IF(D$7="",0,Inputs!Q39) -> 0 | E18: =SUM(C18:D18) -> 0 | F18: =IF(F$7="",0,Inputs!F39) -> 0 | G18: =IF(G$7="",0,Inputs!G39) -> 0 | H18: =IF(H$7="",0,Inputs!H39) -> 0 | I18: =IF(I$7="",0,Inputs!I39) -> 0 | J18: =IF(J$7="",0,Inputs!J39) -> 0 | K18: =IF(K$7="",0,Inputs!K39) -> 0 | L18: =IF(L$7="",0,Inputs!L39) -> 0 | M18: =IF(M$7="",0,Inputs!M39) -> 0 | ... O18: =IF(O$7="",0,Inputs!O39) -> 0 | P18: =SUM(F18:O18) -> 0 | Q18: =P18+E18 -> 0 | R18: =Q18/Q$26 -> 0 | S18: =(F18*$F$51+G18*$G$51+H18*$H$51+I18*$I$51+J18*$J$51+K18*$K$51+L18*$L$51+M18*$M$51+N18*$N$51+O18*$O$51+E18)/($F$53+$E$26) -> 0 | T18: =$F$7*F18+$G$7*G18+$H$7*H18+$I$7*I18+$J$7*J18+$K$7*K18+$L$7*L18+$M$7*M18+$N$7*N18+$O$7*O18 -> 0
B19: Warrants By Series | C19: =Inputs!N22 -> 0 | D19: =Inputs!N23 -> 0 | E19: =SUM(C19:D19) -> 0 | F19: {=IF(TRANSPOSE(Inputs!N$10:N$19)=0,0,TRANSPOSE(Inputs!N$10:N$19))} -> 10000 | G19: 10000 | H19: 10000 | I19: 10000 | J19: 0 | K19: 0 | L19: 0 | M19: 0 | N19: 0 | O19: 0 | P19: =SUM(F19:O19) -> 40000 | Q19: =P19+E19 -> 40000 | R19: =Q19/Q$26 -> 0.0012804097 | S19: =(F19*$F$51+G19*$G$51+H19*$H$51+I19*$I$51+J19*$J$51+K19*$K$51+L19*$L$51+M19*$M$51+N19*$N$51+O19*$O$51+E19)/($F$53+$E$26) -> 0.0012804097 | T19: =T38 -> 40000
B20: Subtotal Investors | C20: =SUM(C10:C18) -> 0 | D20: =SUM(D10:D18) -> 0 | E20: =SUM(E10:E18) -> 0 | F20: =SUM(F10:F19) -> 5010000 | G20: =SUM(G10:G19) -> 5010000 | H20: =SUM(H10:H19) -> 6010000 | I20: =SUM(I10:I19) -> 10010000 | J20: =SUM(J10:J19) -> 0 | K20: =SUM(K10:K19) -> 0 | L20: =SUM(L10:L19) -> 0 | M20: =SUM(M10:M19) -> 0 | ... T20: =SUM(T10:T19) -> 50040000
B22: =Inputs!D40 -> Management | C22: =IF(C$7=0,0,Inputs!P40) -> 5200000 | D22: =IF(D$7=0,0,Inputs!Q40) -> 0 | E22: =SUM(C22:D22) -> 5200000 | P22: =SUM(F22:O22) -> 0 | Q22: =P22+E22 -> 5200000 | R22: =Q22/Q$26 -> 0.16645327 | S22: =(F22*$F$51+G22*$G$51+H22*$H$51+I22*$I$51+J22*$J$51+K22*$K$51+L22*$L$51+M22*$M$51+N22*$N$51+O22*$O$51+E22)/($F$53+$E$26) -> 0.16645327 | T22: =$F$7*F22+$G$7*G22+$H$7*H22+$I$7*I22+$J$7*J22+$K$7*K22+$L$7*L22+$M$7*M22+$N$7*N22+$O$7*O22 -> 0
B24: Subtotal Managers | C24: =SUM(C22:C23) -> 5200000 | D24: =SUM(D22:D23) -> 0 | E24: =SUM(E22:E23) -> 5200000 | F24: =SUM(F22:F23) -> 0 | G24: =SUM(G22:G23) -> 0 | H24: =SUM(H22:H23) -> 0 | I24: =SUM(I22:I23) -> 0 | J24: =SUM(J22:J23) -> 0 | ... T24: =SUM(T22:T23) -> 0
B26: Total Shares | C26: =C20+C24 -> 5200000 | D26: =D20+D24 -> 0 | E26: =E20+E24 -> 5200000 | F26: =F20+F24 -> 5010000 | G26: =G20+G24 -> 5010000 | H26: =H20+H24 -> 6010000 | I26: =I20+I24 -> 10010000 | J26: =J20+J24 -> 0 | ... S26: =S20+S24 -> 1
C28: <--------------------------------------------------------------------------------------------------------------- Amount Invested --------------------------------------------------------------------------------------------------------------->
B29: =IF(Inputs!E31=0,Inputs!D31,CONCATENATE(Inputs!D31," (",Inputs!E31,")")) -> HTGC | C29: =IF(C$7="","",Inputs!P31*C$7) -> 0 | D29: =IF(D$7="","",Inputs!Q31*D$7) -> 0 | E29: =SUM(C29:D29) -> 0 | F29: =IF(F$7="","",Inputs!F31*F$7) -> 1000000 | G29: =IF(G$7="","",Inputs!G31*G$7) -> 2000000 | H29: =IF(H$7="","",Inputs!H31*H$7) -> 0 | I29: =IF(I$7="","",Inputs!I31*I$7) -> 0 | J29: =IF(J$7="","",Inputs!J31*J$7) -> 0 | K29: =IF(K$7="","",Inputs!K31*K$7) -> 0 | L29: =IF(L$7="","",Inputs!L31*L$7) -> 0 | M29: =IF(M$7="","",Inputs!M31*M$7) -> 0 | ... O29: =IF(O$7="","",Inputs!O31*O$7) -> 0 | P29: =SUM(F29:O29) -> 3000000 | Q29: ='Pro Forma Cap Table'!Q10 -> 2000000 | R29: =Q29/$Q$26 -> 0.064020487 | S29: ='Pro Forma Cap Table'!S10 -> 0.064020487 | T29: =SUM(F29:O29) -> 3000000
B30: =IF(Inputs!E32=0,Inputs!D32,CONCATENATE(Inputs!D32," (",Inputs!E32,")")) -> Inv B | C30: =IF(C$7="","",Inputs!P32*C$7) -> 0 | D30: =IF(D$7="","",Inputs!Q32*D$7) -> 0 | E30: =SUM(C30:D30) -> 0 | F30: =IF(F$7="","",Inputs!F32*F$7) -> 1000000 | G30: =IF(G$7="","",Inputs!G32*G$7) -> 2000000 | H30: =IF(H$7="","",Inputs!H32*H$7) -> 0 | I30: =IF(I$7="","",Inputs!I32*I$7) -> 0 | J30: =IF(J$7="","",Inputs!J32*J$7) -> 0 | K30: =IF(K$7="","",Inputs!K32*K$7) -> 0 | L30: =IF(L$7="","",Inputs!L32*L$7) -> 0 | M30: =IF(M$7="","",Inputs!M32*M$7) -> 0 | ... O30: =IF(O$7="","",Inputs!O32*O$7) -> 0 | P30: =SUM(F30:O30) -> 3000000 | Q30: ='Pro Forma Cap Table'!Q11 -> 2000000 | R30: =Q30/$Q$26 -> 0.064020487 | S30: ='Pro Forma Cap Table'!S11 -> 0.064020487 | T30: =SUM(F30:O30) -> 3000000
B31: =IF(Inputs!E33=0,Inputs!D33,CONCATENATE(Inputs!D33," (",Inputs!E33,")")) -> Inv C | C31: =IF(C$7="","",Inputs!P33*C$7) -> 0 | D31: =IF(D$7="","",Inputs!Q33*D$7) -> 0 | E31: =SUM(C31:D31) -> 0 | F31: =IF(F$7="","",Inputs!F33*F$7) -> 1000000 | G31: =IF(G$7="","",Inputs!G33*G$7) -> 2000000 | H31: =IF(H$7="","",Inputs!H33*H$7) -> 2500000 | I31: =IF(I$7="","",Inputs!I33*I$7) -> 0 | J31: =IF(J$7="","",Inputs!J33*J$7) -> 0 | K31: =IF(K$7="","",Inputs!K33*K$7) -> 0 | L31: =IF(L$7="","",Inputs!L33*L$7) -> 0 | M31: =IF(M$7="","",Inputs!M33*M$7) -> 0 | ... O31: =IF(O$7="","",Inputs!O33*O$7) -> 0 | P31: =SUM(F31:O31) -> 5500000 | Q31: ='Pro Forma Cap Table'!Q12 -> 3000000 | R31: =Q31/$Q$26 -> 0.09603073 | S31: ='Pro Forma Cap Table'!S12 -> 0.09603073 | T31: =SUM(F31:O31) -> 5500000
B32: =IF(Inputs!E34=0,Inputs!D34,CONCATENATE(Inputs!D34," (",Inputs!E34,")")) -> Inv D | C32: =IF(C$7="","",Inputs!P34*C$7) -> 0 | D32: =IF(D$7="","",Inputs!Q34*D$7) -> 0 | E32: =SUM(C32:D32) -> 0 | F32: =IF(F$7="","",Inputs!F34*F$7) -> 1000000 | G32: =IF(G$7="","",Inputs!G34*G$7) -> 2000000 | H32: =IF(H$7="","",Inputs!H34*H$7) -> 2500000 | I32: =IF(I$7="","",Inputs!I34*I$7) -> 0 | J32: =IF(J$7="","",Inputs!J34*J$7) -> 0 | K32: =IF(K$7="","",Inputs!K34*K$7) -> 0 | L32: =IF(L$7="","",Inputs!L34*L$7) -> 0 | M32: =IF(M$7="","",Inputs!M34*M$7) -> 0 | ... O32: =IF(O$7="","",Inputs!O34*O$7) -> 0 | P32: =SUM(F32:O32) -> 5500000 | Q32: ='Pro Forma Cap Table'!Q13 -> 3000000 | R32: =Q32/$Q$26 -> 0.09603073 | S32: ='Pro Forma Cap Table'!S13 -> 0.09603073 | T32: =SUM(F32:O32) -> 5500000
B33: =IF(Inputs!E35=0,Inputs!D35,CONCATENATE(Inputs!D35," (",Inputs!E35,")")) -> Inv E | C33: =IF(C$7="","",Inputs!P35*C$7) -> 0 | D33: =IF(D$7="","",Inputs!Q35*D$7) -> 0 | E33: =SUM(C33:D33) -> 0 | F33: =IF(F$7="","",Inputs!F35*F$7) -> 1000000 | G33: =IF(G$7="","",Inputs!G35*G$7) -> 2000000 | H33: =IF(H$7="","",Inputs!H35*H$7) -> 2500000 | I33: =IF(I$7="","",Inputs!I35*I$7) -> 0 | J33: =IF(J$7="","",Inputs!J35*J$7) -> 0 | K33: =IF(K$7="","",Inputs!K35*K$7) -> 0 | L33: =IF(L$7="","",Inputs!L35*L$7) -> 0 | M33: =IF(M$7="","",Inputs!M35*M$7) -> 0 | ... O33: =IF(O$7="","",Inputs!O35*O$7) -> 0 | P33: =SUM(F33:O33) -> 5500000 | Q33: ='Pro Forma Cap Table'!Q14 -> 3000000 | R33: =Q33/$Q$26 -> 0.09603073 | S33: ='Pro Forma Cap Table'!S14 -> 0.09603073 | T33: =SUM(F33:O33) -> 5500000
B34: =IF(Inputs!E36=0,Inputs!D36,CONCATENATE(Inputs!D36," (",Inputs!E36,")")) -> Inv F | C34: =IF(C$7="","",Inputs!P36*C$7) -> 0 | D34: =IF(D$7="","",Inputs!Q36*D$7) -> 0 | E34: =SUM(C34:D34) -> 0 | F34: =IF(F$7="","",Inputs!F36*F$7) -> 0 | G34: =IF(G$7="","",Inputs!G36*G$7) -> 0 | H34: =IF(H$7="","",Inputs!H36*H$7) -> 2500000 | I34: =IF(I$7="","",Inputs!I36*I$7) -> 6666666.7 | J34: =IF(J$7="","",Inputs!J36*J$7) -> 0 | K34: =IF(K$7="","",Inputs!K36*K$7) -> 0 | L34: =IF(L$7="","",Inputs!L36*L$7) -> 0 | M34: =IF(M$7="","",Inputs!M36*M$7) -> 0 | ... O34: =IF(O$7="","",Inputs!O36*O$7) -> 0 | P34: =SUM(F34:O34) -> 9166666.7 | Q34: ='Pro Forma Cap Table'!Q15 -> 4333333.3 | R34: =Q34/$Q$26 -> 0.13871105 | S34: ='Pro Forma Cap Table'!S15 -> 0.13871105 | T34: =SUM(F34:O34) -> 9166666.7
B35: =IF(Inputs!E37=0,Inputs!D37,CONCATENATE(Inputs!D37," (",Inputs!E37,")")) -> Inv G | C35: =IF(C$7="","",Inputs!P37*C$7) -> 0 | D35: =IF(D$7="","",Inputs!Q37*D$7) -> 0 | E35: =SUM(C35:D35) -> 0 | F35: =IF(F$7="","",Inputs!F37*F$7) -> 0 | G35: =IF(G$7="","",Inputs!G37*G$7) -> 0 | H35: =IF(H$7="","",Inputs!H37*H$7) -> 2500000 | I35: =IF(I$7="","",Inputs!I37*I$7) -> 6666666.7 | J35: =IF(J$7="","",Inputs!J37*J$7) -> 0 | K35: =IF(K$7="","",Inputs!K37*K$7) -> 0 | L35: =IF(L$7="","",Inputs!L37*L$7) -> 0 | M35: =IF(M$7="","",Inputs!M37*M$7) -> 0 | ... O35: =IF(O$7="","",Inputs!O37*O$7) -> 0 | P35: =SUM(F35:O35) -> 9166666.7 | Q35: ='Pro Forma Cap Table'!Q16 -> 4333333.3 | R35: =Q35/$Q$26 -> 0.13871105 | S35: ='Pro Forma Cap Table'!S16 -> 0.13871105 | T35: =SUM(F35:O35) -> 9166666.7
B36: =IF(Inputs!E38=0,Inputs!D38,CONCATENATE(Inputs!D38," (",Inputs!E38,")")) -> Inv H | C36: =IF(C$7="","",Inputs!P38*C$7) -> 0 | D36: =IF(D$7="","",Inputs!Q38*D$7) -> 0 | E36: =SUM(C36:D36) -> 0 | F36: =IF(F$7="","",Inputs!F38*F$7) -> 0 | G36: =IF(G$7="","",Inputs!G38*G$7) -> 0 | H36: =IF(H$7="","",Inputs!H38*H$7) -> 2500000 | I36: =IF(I$7="","",Inputs!I38*I$7) -> 6666666.7 | J36: =IF(J$7="","",Inputs!J38*J$7) -> 0 | K36: =IF(K$7="","",Inputs!K38*K$7) -> 0 | L36: =IF(L$7="","",Inputs!L38*L$7) -> 0 | M36: =IF(M$7="","",Inputs!M38*M$7) -> 0 | ... O36: =IF(O$7="","",Inputs!O38*O$7) -> 0 | P36: =SUM(F36:O36) -> 9166666.7 | Q36: ='Pro Forma Cap Table'!Q17 -> 4333333.3 | R36: =Q36/$Q$26 -> 0.13871105 | S36: ='Pro Forma Cap Table'!S17 -> 0.13871105 | T36: =SUM(F36:O36) -> 9166666.7
B37: =Inputs!D39 -> Other Investors | C37: =IF(C$7="","",Inputs!P39*C$7) -> 0 | D37: =IF(D$7="","",Inputs!Q39*D$7) -> 0 | E37: =SUM(C37:D37) -> 0 | F37: =IF(F$7="","",Inputs!F39*F$7) -> 0 | G37: =IF(G$7="","",Inputs!G39*G$7) -> 0 | H37: =IF(H$7="","",Inputs!H39*H$7) -> 0 | I37: =IF(I$7="","",Inputs!I39*I$7) -> 0 | J37: =IF(J$7="","",Inputs!J39*J$7) -> 0 | K37: =IF(K$7="","",Inputs!K39*K$7) -> 0 | L37: =IF(L$7="","",Inputs!L39*L$7) -> 0 | M37: =IF(M$7="","",Inputs!M39*M$7) -> 0 | ... O37: =IF(O$7="","",Inputs!O39*O$7) -> 0 | P37: =SUM(F37:O37) -> 0 | Q37: ='Pro Forma Cap Table'!Q18 -> 0 | R37: =Q37/$Q$26 -> 0 | S37: ='Pro Forma Cap Table'!S18 -> 0 | T37: =SUM(F37:O37) -> 0
B38: Warrants By Series | C38: =C19*Inputs!$K$20 -> 0 | D38: =D19*Inputs!$K$20 -> 0 | F38: =F19*Inputs!O10 -> 10000 | G38: =G19*Inputs!$O11 -> 10000 | H38: =H19*Inputs!$O12 -> 10000 | I38: =I19*Inputs!$O13 -> 10000 | J38: =J19*Inputs!$O14 -> 0 | K38: =K19*Inputs!$O15 -> 0 | L38: =L19*Inputs!$O16 -> 0 | M38: =M19*Inputs!$O17 -> 0 | N38: =N19*Inputs!$O18 -> 0 | O38: =O19*Inputs!$O19 -> 0 | P38: =SUM(F38:O38) -> 40000 | Q38: ='Pro Forma Cap Table'!Q19 -> 40000 | R38: =Q38/$Q$26 -> 0.0012804097 | S38: ='Pro Forma Cap Table'!S19 -> 0.0012804097 | T38: =SUM(F38:O38) -> 40000
B39: Subtotal Investors | C39: =SUM(C29:C37) -> 0 | D39: =SUM(D29:D37) -> 0 | E39: =SUM(E29:E37) -> 0 | F39: =SUM(F29:F38) -> 5010000 | G39: =SUM(G29:G38) -> 10010000 | H39: =SUM(H29:H38) -> 15010000 | I39: =SUM(I29:I38) -> 20010000 | J39: =SUM(J29:J38) -> 0 | K39: =SUM(K29:K38) -> 0 | L39: =SUM(L29:L38) -> 0 | M39: =SUM(M29:M38) -> 0 | ... T39: =SUM(T29:T38) -> 50040000
B41: =Inputs!D40 -> Management | C41: =IF(C$7=0,0,Inputs!M22*C7) -> 0.052 | D41: =IF(D$7=0,0,Inputs!M23*D7) -> 0 | E41: =SUM(C41:D41) -> 0.052 | F41: =IF(F$7=0,0,Inputs!F40*F$7) -> 0 | G41: =IF(G$7=0,0,Inputs!G40*G$7) -> 0 | H41: =IF(H$7=0,0,Inputs!H40*H$7) -> 0 | I41: =IF(I$7=0,0,Inputs!I40*I$7) -> 0 | J41: =IF(J$7=0,0,Inputs!J40*J$7) -> 0 | K41: =IF(K$7=0,0,Inputs!K40*K$7) -> 0 | L41: =IF(L$7=0,0,Inputs!L40*L$7) -> 0 | M41: =IF(M$7=0,0,Inputs!M40*M$7) -> 0 | ... O41: =IF(O$7=0,0,Inputs!O40*O$7) -> 0 | P41: =SUM(F41:O41) -> 0 | Q41: =Q22 -> 5200000 | R41: =Q41/Q$26 -> 0.16645327 | S41: ='Pro Forma Cap Table'!S22 -> 0.16645327 | T41: =T22 -> 0
B43: Subtotal Managers | C43: =SUM(C41:C42) -> 0.052 | D43: =SUM(D41:D42) -> 0 | E43: =SUM(E41:E42) -> 0.052 | F43: =SUM(F41:F42) -> 0 | G43: =SUM(G41:G42) -> 0 | H43: =SUM(H41:H42) -> 0 | I43: =SUM(I41:I42) -> 0 | J43: =SUM(J41:J42) -> 0 | ... T43: =SUM(T41:T42) -> 0
B45: Total Dollars | C45: =C91*C7 -> 0.052 | D45: =D91*D7 -> 0 | E45: =SUM(C45:D45) -> 0.052 | F45: =IF(F7=0,"N/A",F$91*F$7) -> 5000000 | G45: =IF(G7=0,"N/A",G$91*G$7) -> 10000000 | H45: =IF(H7=0,"N/A",H$91*H$7) -> 15000000 | I45: =IF(I7=0,"N/A",I$91*I$7) -> 20000000 | J45: =IF(J7=0,"N/A",J$91*J$7) -> N/A | K45: =IF(K7=0,"N/A",K$91*K$7) -> N/A | L45: =IF(L7=0,"N/A",L$91*L$7) -> N/A | M45: =IF(M7=0,"N/A",M$91*M$7) -> N/A | ... O45: =IF(O7=0,"N/A",O$91*O$7) -> N/A | P45: =SUM(F45:O45) -> 50000000 | R45: =R39+R43 -> 1 | S45: =S39+S43 -> 1 | T45: =T39+T43 -> 50040000
D46: Post-Money | F46: {=IF(TRANSPOSE(Inputs!F$10:F$19)=0,"N/A",TRANSPOSE(Inputs!F$10:F$19))} -> N/A | G46: N/A | H46: N/A | I46: N/A | J46: N/A | K46: N/A | L46: N/A | M46: N/A | N46: N/A | O46: N/A | Q46: Total Liquidation Preference | T46: =F92*F47+G92*G47+H92*H47+I92*I47+J92*J47+K92*K47+L92*L47+M92*M47+N92*N47+O92*O47 -> 50000000
D47: Liq. Pref. Multiple | F47: {=IF(TRANSPOSE(Inputs!G$10:G$19)=0,0,TRANSPOSE(Inputs!G$10:G$19))} -> 1 | G47: 1 | H47: 1 | I47: 1 | J47: 1 | K47: 1 | L47: 1 | M47: 1 | N47: 1 | O47: 1 | Q47: =IF(G7=0,F6,IF(H7=0,G6,IF(I7=0,H6,IF(J7=0,I6,IF(K7=0,J6,IF(L7=0,K6,IF(M7=0,L6,IF(N7=0,M6,IF(O7=0,N6,O6))))))))) -> Series D | R47: ful. dil. post-money valuation of | T47: =R48*Q26 -> 62480000
D48: Cap | F48: {=IF(TRANSPOSE(Inputs!H$10:H$19)=0,0,TRANSPOSE(Inputs!H$10:H$19))} -> 2 | G48: 2 | H48: 2 | I48: 2 | J48: 2 | K48: 2 | L48: 2 | M48: 2 | N48: 2 | O48: 2 | Q48: Based on | R48: =IF(G7=0,F7,IF(H7=0,G7,IF(I7=0,H7,IF(J7=0,I7,IF(K7=0,J7,IF(L7=0,K7,IF(M7=0,L7,IF(N7=0,M7,IF(O7=0,N7,O7))))))))) -> 2 | S48: per share price.
D49: Participating Preferred | F49: =IF(F47=0,"",IF(F48<=F47,"No","Yes")) -> Yes | G49: =IF(G47=0,"",IF(G48<=G47,"No","Yes")) -> Yes | H49: =IF(H47=0,"",IF(H48<=H47,"No","Yes")) -> Yes | I49: =IF(I47=0,"",IF(I48<=I47,"No","Yes")) -> Yes | J49: =IF(J47=0,"",IF(J48<=J47,"No","Yes")) -> Yes | K49: =IF(K47=0,"",IF(K48<=K47,"No","Yes")) -> Yes | L49: =IF(L47=0,"",IF(L48<=L47,"No","Yes")) -> Yes | M49: =IF(M47=0,"",IF(M48<=M47,"No","Yes")) -> Yes | ... O49: =IF(O47=0,"",IF(O48<=O47,"No","Yes")) -> Yes | Q49: Footnotes
D50: Seniority (1 = highest) | F50: {=IF(TRANSPOSE(Inputs!I$10:I$19)=0,"",TRANSPOSE(Inputs!I$10:I$19))} -> 10 | G50: 10 | H50: 2 | I50: 1 | J50: 10 | K50: 10 | L50: 10 | M50: 10 | N50: 10 | O50: 10 | Q50: =IF(Inputs!E45="Text Here","HIDE ROW", CONCATENATE(Inputs!D45, Inputs!E45)) -> *
D51: Conversion Ratio | F51: {=IF(TRANSPOSE(Inputs!J$10:J$19)=0,0,TRANSPOSE(Inputs!J$10:J$19))} -> 1 | G51: 1 | H51: 1 | I51: 1 | J51: 1 | K51: 1 | L51: 1 | M51: 1 | N51: 1 | O51: 1 | Q51: =IF(Inputs!E46="Text Here","HIDE ROW", CONCATENATE(Inputs!D46, Inputs!E46)) -> **
Q52: =IF(Inputs!E47="Text Here","HIDE ROW", CONCATENATE(Inputs!D47," ",Inputs!E47)) -> ***
F53: =SUM(F90:O90) -> 26040000 | Q53: =IF(Inputs!E48="Text Here","HIDE ROW", CONCATENATE(Inputs!D48," ",Inputs!E48)) -> ****
D90: Round CSE | F90: =IFERROR(F51*F26,"") -> 5010000 | G90: =IFERROR(G51*G26,"") -> 5010000 | H90: =IFERROR(H51*H26,"") -> 6010000 | I90: =IFERROR(I51*I26,"") -> 10010000 | J90: =IFERROR(J51*J26,"") -> 0 | K90: =IFERROR(K51*K26,"") -> 0 | L90: =IFERROR(L51*L26,"") -> 0 | M90: =IFERROR(M51*M26,"") -> 0 | ... O90: =IFERROR(O51*O26,"") -> 0
B91: Total Shares | C91: =C20+C24 -> 5200000 | D91: =D20+D24 -> 0 | E91: =E20+E24 -> 5200000 | F91: ='Pro Forma Cap Table'!F26-'Pro Forma Cap Table'!F19 -> 5000000 | G91: ='Pro Forma Cap Table'!G26-'Pro Forma Cap Table'!G19 -> 5000000 | H91: ='Pro Forma Cap Table'!H26-'Pro Forma Cap Table'!H19 -> 6000000 | I91: ='Pro Forma Cap Table'!I26-'Pro Forma Cap Table'!I19 -> 10000000 | J91: ='Pro Forma Cap Table'!J26-'Pro Forma Cap Table'!J19 -> 0 | K91: ='Pro Forma Cap Table'!K26-'Pro Forma Cap Table'!K19 -> 0 | L91: ='Pro Forma Cap Table'!L26-'Pro Forma Cap Table'!L19 -> 0 | M91: ='Pro Forma Cap Table'!M26-'Pro Forma Cap Table'!M19 -> 0 | ... O91: ='Pro Forma Cap Table'!O26-'Pro Forma Cap Table'!O19 -> 0 | P91: =P26 -> 26040000 | Q91: =Q39+Q43 -> 31240000 | R91: =R39+R43 -> 1 | S91: =S39+S43 -> 1
B92: Total Dollars | C92: =C26*C7 -> 0.052 | D92: =D26*D7 -> 0 | E92: =SUM(C92:D92) -> 0.052 | F92: =(F26-F19)*F7 -> 5000000 | G92: =(G26-G19)*G7 -> 10000000 | H92: =(H26-H19)*H7 -> 15000000 | I92: =(I26-I19)*I7 -> 20000000 | J92: =(J26-J19)*J7 -> 0 | K92: =(K26-K19)*K7 -> 0 | L92: =(L26-L19)*L7 -> 0 | M92: =(M26-M19)*M7 -> 0 | ... O92: =(O26-O19)*O7 -> 0 | P92: =SUM(F92:O92) -> 50000000 | T92: =P92+E92 -> 50000000

Sheet $-Pro Forma Cap Table
B1: =Inputs!I6 -> Company Name
B2: Pro Forma Capitalization Table
F5: {=IF(TRANSPOSE(Inputs!E$10:E$19)=0,"",TRANSPOSE(Inputs!E$10:E$19))} -> 39113 | G5: 39478 | H5: 39843 | I5: 39843 | J5: 39843 | K5: 39843 | L5: 39843 | M5: 39843 | N5: 39843 | O5: 39843
D31: Post-Money | F31: {=IF(TRANSPOSE(Inputs!F$10:F$19)=0,"N/A",TRANSPOSE(Inputs!F$10:F$19))} -> N/A | G31: N/A | H31: N/A | I31: N/A | J31: N/A | K31: N/A | L31: N/A | M31: N/A | N31: N/A | O31: N/A | R31: =IF('Pro Forma Cap Table'!#REF!=0,'Pro Forma Cap Table'!#REF!,IF('Pro Forma Cap Table'!#REF!=0,'Pro Forma Cap Table'!#REF!,IF('Pro Forma Cap Table'!#REF!=0,'Pro Forma Cap Table'!#REF!,IF('Pro Forma Cap Table'!#REF!=0,'Pro Forma Cap Table'!#REF!,IF('Pro Forma Cap Table'!#REF!=0,'Pro Forma Cap Table'!#REF!,IF('Pro Forma Cap Table'!#REF!=0,'Pro Forma Cap Table'!#REF!,IF('Pro Forma Cap Table'!#REF!=0,'Pro Forma Cap Table'!#REF!,IF('Pro Forma Cap Table'!#REF!=0,'Pro Forma Cap Table'!#REF!,IF('Pro Forma Cap Table'!#REF!=0,'Pro Forma Cap Table'!#REF!,'Pro Forma Cap Table'!#REF!))))))))) -> #REF! | S31: Post-Money Valuation of | U31: =S32*'Pro Forma Cap Table'!Q91 -> #REF!
D32: Preference Multiple | F32: {=IF(TRANSPOSE(Inputs!G$10:G$19)=0,"",TRANSPOSE(Inputs!G$10:G$19))} -> 1 | G32: 1 | H32: 1 | I32: 1 | J32: 1 | K32: 1 | L32: 1 | M32: 1 | N32: 1 | O32: 1 | R32: Based on | S32: =IF('Pro Forma Cap Table'!#REF!=0,'Pro Forma Cap Table'!#REF!,IF('Pro Forma Cap Table'!#REF!=0,'Pro Forma Cap Table'!#REF!,IF('Pro Forma Cap Table'!#REF!=0,'Pro Forma Cap Table'!#REF!,IF('Pro Forma Cap Table'!#REF!=0,'Pro Forma Cap Table'!#REF!,IF('Pro Forma Cap Table'!#REF!=0,'Pro Forma Cap Table'!#REF!,IF('Pro Forma Cap Table'!#REF!=0,'Pro Forma Cap Table'!#REF!,IF('Pro Forma Cap Table'!#REF!=0,'Pro Forma Cap Table'!#REF!,IF('Pro Forma Cap Table'!#REF!=0,'Pro Forma Cap Table'!#REF!,IF('Pro Forma Cap Table'!#REF!=0,'Pro Forma Cap Table'!#REF!,'Pro Forma Cap Table'!#REF!))))))))) -> #REF! | T32: per share price.
D33: Cap | F33: {=IF(TRANSPOSE(Inputs!H$10:H$19)=0,"",TRANSPOSE(Inputs!H$10:H$19))} -> 2 | G33: 2 | H33: 2 | I33: 2 | J33: 2 | K33: 2 | L33: 2 | M33: 2 | N33: 2 | O33: 2
D34: Participating Preferred | F34: =IF(F32="","",IF(F33<=F32,"No","Yes")) -> Yes | G34: =IF(G32="","",IF(G33<=G32,"No","Yes")) -> Yes | H34: =IF(H32="","",IF(H33<=H32,"No","Yes")) -> Yes | I34: =IF(I32="","",IF(I33<=I32,"No","Yes")) -> Yes | J34: =IF(J32="","",IF(J33<=J32,"No","Yes")) -> Yes | K34: =IF(K32="","",IF(K33<=K32,"No","Yes")) -> Yes | L34: =IF(L32="","",IF(L33<=L32,"No","Yes")) -> Yes | M34: =IF(M32="","",IF(M33<=M32,"No","Yes")) -> Yes | ... O34: =IF(O32="","",IF(O33<=O32,"No","Yes")) -> Yes | R34: Footnotes
D35: Seniority Rank | F35: {=IF(TRANSPOSE(Inputs!I$10:I$19)=0,"",TRANSPOSE(Inputs!I$10:I$19))} -> 10 | G35: 10 | H35: 2 | I35: 1 | J35: 10 | K35: 10 | L35: 10 | M35: 10 | N35: 10 | O35: 10 | R35: =IF(Inputs!E45="Text Here","HIDE ROW", CONCATENATE(Inputs!D45, Inputs!E45)) -> *
D36: Conversion Ratio | F36: {=IF(TRANSPOSE(Inputs!J$10:J$19)=0,0,TRANSPOSE(Inputs!J$10:J$19))} -> 1 | G36: 1 | H36: 1 | I36: 1 | J36: 1 | K36: 1 | L36: 1 | M36: 1 | N36: 1 | O36: 1 | R36: =IF(Inputs!E46="Text Here","HIDE ROW", CONCATENATE(Inputs!D46, Inputs!E46)) -> **
D37: Round CSE | F37: =IFERROR(F36*'Pro Forma Cap Table'!F91,"") -> 5000000 | G37: =IFERROR(G36*'Pro Forma Cap Table'!G91,"") -> 5000000 | H37: =IFERROR(H36*'Pro Forma Cap Table'!H91,"") -> 6000000 | I37: =IFERROR(I36*'Pro Forma Cap Table'!I91,"") -> 10000000 | J37: =IFERROR(J36*'Pro Forma Cap Table'!J91,"") -> 0 | K37: =IFERROR(K36*'Pro Forma Cap Table'!K91,"") -> 0 | L37: =IFERROR(L36*'Pro Forma Cap Table'!L91,"") -> 0 | M37: =IFERROR(M36*'Pro Forma Cap Table'!M91,"") -> 0 | ... O37: =IFERROR(O36*'Pro Forma Cap Table'!O91,"") -> 0 | P37: =SUM(F37:O37) -> 26000000 | R37: =IF(Inputs!E47="Text Here","HIDE ROW", CONCATENATE(Inputs!D47," ",Inputs!E47)) -> ***
D38: in % | F38: =F37/(F37+'Pro Forma Cap Table'!$Q$43) -> 0.49019608 | G38: =G37/(G37+'Pro Forma Cap Table'!$Q$43) -> 0.49019608 | H38: =H37/(H37+'Pro Forma Cap Table'!$Q$43) -> 0.53571429 | I38: =I37/(I37+'Pro Forma Cap Table'!$Q$43) -> 0.65789474 | J38: =J37/(J37+'Pro Forma Cap Table'!$Q$43) -> 0 | K38: =K37/(K37+'Pro Forma Cap Table'!$Q$43) -> 0 | L38: =L37/(L37+'Pro Forma Cap Table'!$Q$43) -> 0 | M38: =M37/(M37+'Pro Forma Cap Table'!$Q$43) -> 0 | ... O38: =O37/(O37+'Pro Forma Cap Table'!$Q$43) -> 0 | R38: =IF(Inputs!E48="Text Here","HIDE ROW", CONCATENATE(Inputs!D48," ",Inputs!E48)) -> ****

Sheet Waterfall
B1: =Inputs!I6 -> Company Name
B2: Pro Forma Capitalization Table
B3: =Inputs!I7 -> 39813
F5: {=IF(TRANSPOSE(Inputs!E$10:E$19)=0,"",TRANSPOSE(Inputs!E$10:E$19))} -> 39113 | G5: 39478 | H5: 39843 | I5: 39843 | J5: 39843 | K5: 39843 | L5: 39843 | M5: 39843 | N5: 39843 | O5: 39843
C6: Common | D6: Stock | E6: Total | F6: {=IF(TRANSPOSE(Inputs!D$10:D$19)=0,"",TRANSPOSE(Inputs!D$10:D$19))} -> Series A | G6: Series B | H6: Series C | I6: Series D | J6: - | K6: - | L6: - | M6: - | N6: - | O6: - | P6: Total | Q6: Total # | R6: Total Ful. Dil | S6: Ful. Dil. as Conv. | T6: Total
B7: Investor (Partner) | C7: =Inputs!K22 -> 1e-08 | D7: =Inputs!K23 -> 1e-07 | E7: Common | F7: {=IF(TRANSPOSE(Inputs!K$10:K$19)=0,0,TRANSPOSE(Inputs!K$10:K$19))} -> 1 | G7: 2 | H7: 2.5 | I7: 2 | J7: 0 | K7: 0 | L7: 0 | M7: 0 | N7: 0 | O7: 0 | P7: Preferred | Q7: Of All | R7: Ownership | S7: Ownership | T7: Dollars ($)
C8: Shares | D8: Options | E8: & Options | F8: =IF(F7=0,"","Preferred") -> Preferred | G8: =IF(G7=0,"","Preferred") -> Preferred | H8: =IF(H7=0,"","Preferred") -> Preferred | I8: =IF(I7=0,"","Preferred") -> Preferred | J8: =IF(J7=0,"","Preferred") | K8: =IF(K7=0,"","Preferred") | L8: =IF(L7=0,"","Preferred") | M8: =IF(M7=0,"","Preferred") | ... O8: =IF(O7=0,"","Preferred") | P8: Shares | Q8: Shares Held | R8: Percent (%) | S8: Percent (%) | T8: Invested
C9: <------------------------------------------------------------------------------------------------------------------- # of Shares ------------------------------------------------------------------------------------------------------------------->
B10: =IF(Inputs!E31=0,Inputs!D31,CONCATENATE(Inputs!D31," (",Inputs!E31,")")) -> HTGC | C10: =IF(C$7="",0,Inputs!P31) -> 0 | D10: =IF(D$7="",0,Inputs!Q31) -> 0 | E10: =SUM(C10:D10) -> 0 | F10: =IF(F$7="",0,Inputs!F31) -> 1000000 | G10: =IF(G$7="",0,Inputs!G31) -> 1000000 | H10: =IF(H$7="",0,Inputs!H31) -> 0 | I10: =IF(I$7="",0,Inputs!I31) -> 0 | J10: =IF(J$7="",0,Inputs!J31) -> 0 | K10: =IF(K$7="",0,Inputs!K31) -> 0 | L10: =IF(L$7="",0,Inputs!L31) -> 0 | M10: =IF(M$7="",0,Inputs!M31) -> 0 | ... O10: =IF(O$7="",0,Inputs!O31) -> 0 | P10: =SUM(F10:O10) -> 2000000 | Q10: =P10+E10 -> 2000000 | R10: =Q10/Q$26 -> 0.064020487 | S10: =(F10*$F$51+G10*$G$51+H10*$H$51+I10*$I$51+J10*$J$51+K10*$K$51+L10*$L$51+M10*$M$51+N10*$N$51+O10*$O$51+E10)/($F$53+$E$26) -> 0.036182723 | T10: =$F$7*F10+$G$7*G10+$H$7*H10+$I$7*I10+$J$7*J10+$K$7*K10+$L$7*L10+$M$7*M10+$N$7*N10+$O$7*O10 -> 3000000
B11: =IF(Inputs!E32=0,Inputs!D32,CONCATENATE(Inputs!D32," (",Inputs!E32,")")) -> Inv B | C11: =IF(C$7="",0,Inputs!P32) -> 0 | D11: =IF(D$7="",0,Inputs!Q32) -> 0 | E11: =SUM(C11:D11) -> 0 | F11: =IF(F$7="",0,Inputs!F32) -> 1000000 | G11: =IF(G$7="",0,Inputs!G32) -> 1000000 | H11: =IF(H$7="",0,Inputs!H32) -> 0 | I11: =IF(I$7="",0,Inputs!I32) -> 0 | J11: =IF(J$7="",0,Inputs!J32) -> 0 | K11: =IF(K$7="",0,Inputs!K32) -> 0 | L11: =IF(L$7="",0,Inputs!L32) -> 0 | M11: =IF(M$7="",0,Inputs!M32) -> 0 | ... O11: =IF(O$7="",0,Inputs!O32) -> 0 | P11: =SUM(F11:O11) -> 2000000 | Q11: =P11+E11 -> 2000000 | R11: =Q11/Q$26 -> 0.064020487 | S11: =(F11*$F$51+G11*$G$51+H11*$H$51+I11*$I$51+J11*$J$51+K11*$K$51+L11*$L$51+M11*$M$51+N11*$N$51+O11*$O$51+E11)/($F$53+$E$26) -> 0.036182723 | T11: =$F$7*F11+$G$7*G11+$H$7*H11+$I$7*I11+$J$7*J11+$K$7*K11+$L$7*L11+$M$7*M11+$N$7*N11+$O$7*O11 -> 3000000
B12: =IF(Inputs!E33=0,Inputs!D33,CONCATENATE(Inputs!D33," (",Inputs!E33,")")) -> Inv C | C12: =IF(C$7="",0,Inputs!P33) -> 0 | D12: =IF(D$7="",0,Inputs!Q33) -> 0 | E12: =SUM(C12:D12) -> 0 | F12: =IF(F$7="",0,Inputs!F33) -> 1000000 | G12: =IF(G$7="",0,Inputs!G33) -> 1000000 | H12: =IF(H$7="",0,Inputs!H33) -> 1000000 | I12: =IF(I$7="",0,Inputs!I33) -> 0 | J12: =IF(J$7="",0,Inputs!J33) -> 0 | K12: =IF(K$7="",0,Inputs!K33) -> 0 | L12: =IF(L$7="",0,Inputs!L33) -> 0 | M12: =IF(M$7="",0,Inputs!M33) -> 0 | ... O12: =IF(O$7="",0,Inputs!O33) -> 0 | P12: =SUM(F12:O12) -> 3000000 | Q12: =P12+E12 -> 3000000 | R12: =Q12/Q$26 -> 0.09603073 | S12: =(F12*$F$51+G12*$G$51+H12*$H$51+I12*$I$51+J12*$J$51+K12*$K$51+L12*$L$51+M12*$M$51+N12*$N$51+O12*$O$51+E12)/($F$53+$E$26) -> 0.054274084 | T12: =$F$7*F12+$G$7*G12+$H$7*H12+$I$7*I12+$J$7*J12+$K$7*K12+$L$7*L12+$M$7*M12+$N$7*N12+$O$7*O12 -> 5500000
B13: =IF(Inputs!E34=0,Inputs!D34,CONCATENATE(Inputs!D34," (",Inputs!E34,")")) -> Inv D | C13: =IF(C$7="",0,Inputs!P34) -> 0 | D13: =IF(D$7="",0,Inputs!Q34) -> 0 | E13: =SUM(C13:D13) -> 0 | F13: =IF(F$7="",0,Inputs!F34) -> 1000000 | G13: =IF(G$7="",0,Inputs!G34) -> 1000000 | H13: =IF(H$7="",0,Inputs!H34) -> 1000000 | I13: =IF(I$7="",0,Inputs!I34) -> 0 | J13: =IF(J$7="",0,Inputs!J34) -> 0 | K13: =IF(K$7="",0,Inputs!K34) -> 0 | L13: =IF(L$7="",0,Inputs!L34) -> 0 | M13: =IF(M$7="",0,Inputs!M34) -> 0 | ... O13: =IF(O$7="",0,Inputs!O34) -> 0 | P13: =SUM(F13:O13) -> 3000000 | Q13: =P13+E13 -> 3000000 | R13: =Q13/Q$26 -> 0.09603073 | S13: =(F13*$F$51+G13*$G$51+H13*$H$51+I13*$I$51+J13*$J$51+K13*$K$51+L13*$L$51+M13*$M$51+N13*$N$51+O13*$O$51+E13)/($F$53+$E$26) -> 0.054274084 | T13: =$F$7*F13+$G$7*G13+$H$7*H13+$I$7*I13+$J$7*J13+$K$7*K13+$L$7*L13+$M$7*M13+$N$7*N13+$O$7*O13 -> 5500000
B14: =IF(Inputs!E35=0,Inputs!D35,CONCATENATE(Inputs!D35," (",Inputs!E35,")")) -> Inv E | C14: =IF(C$7="",0,Inputs!P35) -> 0 | D14: =IF(D$7="",0,Inputs!Q35) -> 0 | E14: =SUM(C14:D14) -> 0 | F14: =IF(F$7="",0,Inputs!F35) -> 1000000 | G14: =IF(G$7="",0,Inputs!G35) -> 1000000 | H14: =IF(H$7="",0,Inputs!H35) -> 1000000 | I14: =IF(I$7="",0,Inputs!I35) -> 0 | J14: =IF(J$7="",0,Inputs!J35) -> 0 | K14: =IF(K$7="",0,Inputs!K35) -> 0 | L14: =IF(L$7="",0,Inputs!L35) -> 0 | M14: =IF(M$7="",0,Inputs!M35) -> 0 | ... O14: =IF(O$7="",0,Inputs!O35) -> 0 | P14: =SUM(F14:O14) -> 3000000 | Q14: =P14+E14 -> 3000000 | R14: =Q14/Q$26 -> 0.09603073 | S14: =(F14*$F$51+G14*$G$51+H14*$H$51+I14*$I$51+J14*$J$51+K14*$K$51+L14*$L$51+M14*$M$51+N14*$N$51+O14*$O$51+E14)/($F$53+$E$26) -> 0.054274084 | T14: =$F$7*F14+$G$7*G14+$H$7*H14+$I$7*I14+$J$7*J14+$K$7*K14+$L$7*L14+$M$7*M14+$N$7*N14+$O$7*O14 -> 5500000
B15: =IF(Inputs!E36=0,Inputs!D36,CONCATENATE(Inputs!D36," (",Inputs!E36,")")) -> Inv F | C15: =IF(C$7="",0,Inputs!P36) -> 0 | D15: =IF(D$7="",0,Inputs!Q36) -> 0 | E15: =SUM(C15:D15) -> 0 | F15: =IF(F$7="",0,Inputs!F36) -> 0 | G15: =IF(G$7="",0,Inputs!G36) -> 0 | H15: =IF(H$7="",0,Inputs!H36) -> 1000000 | I15: =IF(I$7="",0,Inputs!I36) -> 3333333.3 | J15: =IF(J$7="",0,Inputs!J36) -> 0 | K15: =IF(K$7="",0,Inputs!K36) -> 0 | L15: =IF(L$7="",0,Inputs!L36) -> 0 | M15: =IF(M$7="",0,Inputs!M36) -> 0 | ... O15: =IF(O$7="",0,Inputs!O36) -> 0 | P15: =SUM(F15:O15) -> 4333333.3 | Q15: =P15+E15 -> 4333333.3 | R15: =Q15/Q$26 -> 0.13871105 | S15: =(F15*$F$51+G15*$G$51+H15*$H$51+I15*$I$51+J15*$J$51+K15*$K$51+L15*$L$51+M15*$M$51+N15*$N$51+O15*$O$51+E15)/($F$53+$E$26) -> 0.078395899 | T15: =$F$7*F15+$G$7*G15+$H$7*H15+$I$7*I15+$J$7*J15+$K$7*K15+$L$7*L15+$M$7*M15+$N$7*N15+$O$7*O15 -> 9166666.7
B16: =IF(Inputs!E37=0,Inputs!D37,CONCATENATE(Inputs!D37," (",Inputs!E37,")")) -> Inv G | C16: =IF(C$7="",0,Inputs!P37) -> 0 | D16: =IF(D$7="",0,Inputs!Q37) -> 0 | E16: =SUM(C16:D16) -> 0 | F16: =IF(F$7="",0,Inputs!F37) -> 0 | G16: =IF(G$7="",0,Inputs!G37) -> 0 | H16: =IF(H$7="",0,Inputs!H37) -> 1000000 | I16: =IF(I$7="",0,Inputs!I37) -> 3333333.3 | J16: =IF(J$7="",0,Inputs!J37) -> 0 | K16: =IF(K$7="",0,Inputs!K37) -> 0 | L16: =IF(L$7="",0,Inputs!L37) -> 0 | M16: =IF(M$7="",0,Inputs!M37) -> 0 | ... O16: =IF(O$7="",0,Inputs!O37) -> 0 | P16: =SUM(F16:O16) -> 4333333.3 | Q16: =P16+E16 -> 4333333.3 | R16: =Q16/Q$26 -> 0.13871105 | S16: =(F16*$F$51+G16*$G$51+H16*$H$51+I16*$I$51+J16*$J$51+K16*$K$51+L16*$L$51+M16*$M$51+N16*$N$51+O16*$O$51+E16)/($F$53+$E$26) -> 0.078395899 | T16: =$F$7*F16+$G$7*G16+$H$7*H16+$I$7*I16+$J$7*J16+$K$7*K16+$L$7*L16+$M$7*M16+$N$7*N16+$O$7*O16 -> 9166666.7
B17: =IF(Inputs!E38=0,Inputs!D38,CONCATENATE(Inputs!D38," (",Inputs!E38,")")) -> Inv H | C17: =IF(C$7="",0,Inputs!P38) -> 0 | D17: =IF(D$7="",0,Inputs!Q38) -> 0 | E17: =SUM(C17:D17) -> 0 | F17: =IF(F$7="",0,Inputs!F38) -> 0 | G17: =IF(G$7="",0,Inputs!G38) -> 0 | H17: =IF(H$7="",0,Inputs!H38) -> 1000000 | I17: =IF(I$7="",0,Inputs!I38) -> 3333333.3 | J17: =IF(J$7="",0,Inputs!J38) -> 0 | K17: =IF(K$7="",0,Inputs!K38) -> 0 | L17: =IF(L$7="",0,Inputs!L38) -> 0 | M17: =IF(M$7="",0,Inputs!M38) -> 0 | ... O17: =IF(O$7="",0,Inputs!O38) -> 0 | P17: =SUM(F17:O17) -> 4333333.3 | Q17: =P17+E17 -> 4333333.3 | R17: =Q17/Q$26 -> 0.13871105 | S17: =(F17*$F$51+G17*$G$51+H17*$H$51+I17*$I$51+J17*$J$51+K17*$K$51+L17*$L$51+M17*$M$51+N17*$N$51+O17*$O$51+E17)/($F$53+$E$26) -> 0.078395899 | T17: =$F$7*F17+$G$7*G17+$H$7*H17+$I$7*I17+$J$7*J17+$K$7*K17+$L$7*L17+$M$7*M17+$N$7*N17+$O$7*O17 -> 9166666.7
B18: =Inputs!D39 -> Other Investors | C18: =IF(C$7="",0,Inputs!P39) -> 0 | D18: =IF(D$7="",0,Inputs!Q39) -> 0 | E18: =SUM(C18:D18) -> 0 | F18: =IF(F$7="",0,Inputs!F39) -> 0 | G18: =IF(G$7="",0,Inputs!G39) -> 0 | H18: =IF(H$7="",0,Inputs!H39) -> 0 | I18: =IF(I$7="",0,Inputs!I39) -> 0 | J18: =IF(J$7="",0,Inputs!J39) -> 0 | K18: =IF(K$7="",0,Inputs!K39) -> 0 | L18: =IF(L$7="",0,Inputs!L39) -> 0 | M18: =IF(M$7="",0,Inputs!M39) -> 0 | ... O18: =IF(O$7="",0,Inputs!O39) -> 0 | P18: =SUM(F18:O18) -> 0 | Q18: =P18+E18 -> 0 | R18: =Q18/Q$26 -> 0 | S18: =(F18*$F$51+G18*$G$51+H18*$H$51+I18*$I$51+J18*$J$51+K18*$K$51+L18*$L$51+M18*$M$51+N18*$N$51+O18*$O$51+E18)/($F$53+$E$26) -> 0 | T18: =$F$7*F18+$G$7*G18+$H$7*H18+$I$7*I18+$J$7*J18+$K$7*K18+$L$7*L18+$M$7*M18+$N$7*N18+$O$7*O18 -> 0
B19: Warrants By Series | C19: =Inputs!N22 -> 0 | D19: =Inputs!N23 -> 0 | E19: =SUM(C19:D19) -> 0 | F19: {=IF(TRANSPOSE(Inputs!N$10:N$19)=0,0,TRANSPOSE(Inputs!N$10:N$19))} -> 10000 | G19: 10000 | H19: 10000 | I19: 10000 | J19: 0 | K19: 0 | L19: 0 | M19: 0 | N19: 0 | O19: 0 | P19: =SUM(F19:O19) -> 40000 | Q19: =P19+E19 -> 40000 | R19: =Q19/Q$26 -> 0.0012804097 | S19: =(F19*$F$51+G19*$G$51+H19*$H$51+I19*$I$51+J19*$J$51+K19*$K$51+L19*$L$51+M19*$M$51+N19*$N$51+O19*$O$51+E19)/($F$53+$E$26) -> 0.00072365445 | T19: =T38 -> 40000
B20: Subtotal Investors | C20: =SUM(C10:C18) -> 0 | D20: =SUM(D10:D18) -> 0 | E20: =SUM(E10:E18) -> 0 | F20: =SUM(F10:F19) -> 5010000 | G20: =SUM(G10:G19) -> 5010000 | H20: =SUM(H10:H19) -> 6010000 | I20: =SUM(I10:I19) -> 10010000 | J20: =SUM(J10:J19) -> 0 | K20: =SUM(K10:K19) -> 0 | L20: =SUM(L10:L19) -> 0 | M20: =SUM(M10:M19) -> 0 | ... T20: =SUM(T10:T19) -> 50040000
B22: =Inputs!D40 -> Management | C22: =IF(C$7=0,0,Inputs!P40) -> 5200000 | D22: =IF(D$7=0,0,Inputs!Q40) -> 0 | E22: =SUM(C22:D22) -> 5200000 | F22: =IF(F$7=0,0,Inputs!F40) -> 0 | G22: =IF(G$7=0,0,Inputs!G40) -> 0 | H22: =IF(H$7=0,0,Inputs!H40) -> 0 | I22: =IF(I$7=0,0,Inputs!I40) -> 0 | J22: =IF(J$7=0,0,Inputs!J40) -> 0 | K22: =IF(K$7=0,0,Inputs!K40) -> 0 | L22: =IF(L$7=0,0,Inputs!L40) -> 0 | M22: =IF(M$7=0,0,Inputs!M40) -> 0 | ... O22: =IF(O$7=0,0,Inputs!O40) -> 0 | P22: =SUM(F22:O22) -> 0 | Q22: =P22+E22 -> 5200000 | R22: =Q22/Q$26 -> 0.16645327 | S22: =(F22*$F$51+G22*$G$51+H22*$H$51+I22*$I$51+J22*$J$51+K22*$K$51+L22*$L$51+M22*$M$51+N22*$N$51+O22*$O$51+E22)/($F$53+$E$26) -> 0.094075079 | T22: =$F$7*F22+$G$7*G22+$H$7*H22+$I$7*I22+$J$7*J22+$K$7*K22+$L$7*L22+$M$7*M22+$N$7*N22+$O$7*O22 -> 0
B24: Subtotal Managers | C24: =SUM(C22:C23) -> 5200000 | D24: =SUM(D22:D23) -> 0 | E24: =SUM(E22:E23) -> 5200000 | F24: =SUM(F22:F23) -> 0 | G24: =SUM(G22:G23) -> 0 | H24: =SUM(H22:H23) -> 0 | I24: =SUM(I22:I23) -> 0 | J24: =SUM(J22:J23) -> 0 | ... T24: =SUM(T22:T23) -> 0
B26: Total Shares | C26: =C20+C24 -> 5200000 | D26: =D20+D24 -> 0 | E26: =E20+E24 -> 5200000 | F26: =F20+F24 -> 5010000 | G26: =G20+G24 -> 5010000 | H26: =H20+H24 -> 6010000 | I26: =I20+I24 -> 10010000 | J26: =J20+J24 -> 0 | ... S26: =S20+S24 -> 0.56517413
C28: <--------------------------------------------------------------------------------------------------------------- Amount Invested --------------------------------------------------------------------------------------------------------------->
B29: =IF(Inputs!E31=0,Inputs!D31,CONCATENATE(Inputs!D31," (",Inputs!E31,")")) -> HTGC | C29: =IF(C$7="","",Inputs!P31*C$7) -> 0 | D29: =IF(D$7="","",Inputs!Q31*D$7) -> 0 | E29: =SUM(C29:D29) -> 0 | F29: =IF(F$7="","",Inputs!F31*F$7) -> 1000000 | G29: =IF(G$7="","",Inputs!G31*G$7) -> 2000000 | H29: =IF(H$7="","",Inputs!H31*H$7) -> 0 | I29: =IF(I$7="","",Inputs!I31*I$7) -> 0 | J29: =IF(J$7="","",Inputs!J31*J$7) -> 0 | K29: =IF(K$7="","",Inputs!K31*K$7) -> 0 | L29: =IF(L$7="","",Inputs!L31*L$7) -> 0 | M29: =IF(M$7="","",Inputs!M31*M$7) -> 0 | ... O29: =IF(O$7="","",Inputs!O31*O$7) -> 0 | P29: =SUM(F29:O29) -> 3000000 | Q29: ='Pro Forma Cap Table'!Q10 -> 2000000 | R29: =Q29/$Q$26 -> 0.064020487 | S29: ='Pro Forma Cap Table'!S10 -> 0.064020487 | T29: =SUM(F29:O29) -> 3000000
B30: =IF(Inputs!E32=0,Inputs!D32,CONCATENATE(Inputs!D32," (",Inputs!E32,")")) -> Inv B | C30: =IF(C$7="","",Inputs!P32*C$7) -> 0 | D30: =IF(D$7="","",Inputs!Q32*D$7) -> 0 | E30: =SUM(C30:D30) -> 0 | F30: =IF(F$7="","",Inputs!F32*F$7) -> 1000000 | G30: =IF(G$7="","",Inputs!G32*G$7) -> 2000000 | H30: =IF(H$7="","",Inputs!H32*H$7) -> 0 | I30: =IF(I$7="","",Inputs!I32*I$7) -> 0 | J30: =IF(J$7="","",Inputs!J32*J$7) -> 0 | K30: =IF(K$7="","",Inputs!K32*K$7) -> 0 | L30: =IF(L$7="","",Inputs!L32*L$7) -> 0 | M30: =IF(M$7="","",Inputs!M32*M$7) -> 0 | ... O30: =IF(O$7="","",Inputs!O32*O$7) -> 0 | P30: =SUM(F30:O30) -> 3000000 | Q30: ='Pro Forma Cap Table'!Q11 -> 2000000 | R30: =Q30/$Q$26 -> 0.064020487 | S30: ='Pro Forma Cap Table'!S11 -> 0.064020487 | T30: =SUM(F30:O30) -> 3000000
B31: =IF(Inputs!E33=0,Inputs!D33,CONCATENATE(Inputs!D33," (",Inputs!E33,")")) -> Inv C | C31: =IF(C$7="","",Inputs!P33*C$7) -> 0 | D31: =IF(D$7="","",Inputs!Q33*D$7) -> 0 | E31: =SUM(C31:D31) -> 0 | F31: =IF(F$7="","",Inputs!F33*F$7) -> 1000000 | G31: =IF(G$7="","",Inputs!G33*G$7) -> 2000000 | H31: =IF(H$7="","",Inputs!H33*H$7) -> 2500000 | I31: =IF(I$7="","",Inputs!I33*I$7) -> 0 | J31: =IF(J$7="","",Inputs!J33*J$7) -> 0 | K31: =IF(K$7="","",Inputs!K33*K$7) -> 0 | L31: =IF(L$7="","",Inputs!L33*L$7) -> 0 | M31: =IF(M$7="","",Inputs!M33*M$7) -> 0 | ... O31: =IF(O$7="","",Inputs!O33*O$7) -> 0 | P31: =SUM(F31:O31) -> 5500000 | Q31: ='Pro Forma Cap Table'!Q12 -> 3000000 | R31: =Q31/$Q$26 -> 0.09603073 | S31: ='Pro Forma Cap Table'!S12 -> 0.09603073 | T31: =SUM(F31:O31) -> 5500000
B32: =IF(Inputs!E34=0,Inputs!D34,CONCATENATE(Inputs!D34," (",Inputs!E34,")")) -> Inv D | C32: =IF(C$7="","",Inputs!P34*C$7) -> 0 | D32: =IF(D$7="","",Inputs!Q34*D$7) -> 0 | E32: =SUM(C32:D32) -> 0 | F32: =IF(F$7="","",Inputs!F34*F$7) -> 1000000 | G32: =IF(G$7="","",Inputs!G34*G$7) -> 2000000 | H32: =IF(H$7="","",Inputs!H34*H$7) -> 2500000 | I32: =IF(I$7="","",Inputs!I34*I$7) -> 0 | J32: =IF(J$7="","",Inputs!J34*J$7) -> 0 | K32: =IF(K$7="","",Inputs!K34*K$7) -> 0 | L32: =IF(L$7="","",Inputs!L34*L$7) -> 0 | M32: =IF(M$7="","",Inputs!M34*M$7) -> 0 | ... O32: =IF(O$7="","",Inputs!O34*O$7) -> 0 | P32: =SUM(F32:O32) -> 5500000 | Q32: ='Pro Forma Cap Table'!Q13 -> 3000000 | R32: =Q32/$Q$26 -> 0.09603073 | S32: ='Pro Forma Cap Table'!S13 -> 0.09603073 | T32: =SUM(F32:O32) -> 5500000
B33: =IF(Inputs!E35=0,Inputs!D35,CONCATENATE(Inputs!D35," (",Inputs!E35,")")) -> Inv E | C33: =IF(C$7="","",Inputs!P35*C$7) -> 0 | D33: =IF(D$7="","",Inputs!Q35*D$7) -> 0 | E33: =SUM(C33:D33) -> 0 | F33: =IF(F$7="","",Inputs!F35*F$7) -> 1000000 | G33: =IF(G$7="","",Inputs!G35*G$7) -> 2000000 | H33: =IF(H$7="","",Inputs!H35*H$7) -> 2500000 | I33: =IF(I$7="","",Inputs!I35*I$7) -> 0 | J33: =IF(J$7="","",Inputs!J35*J$7) -> 0 | K33: =IF(K$7="","",Inputs!K35*K$7) -> 0 | L33: =IF(L$7="","",Inputs!L35*L$7) -> 0 | M33: =IF(M$7="","",Inputs!M35*M$7) -> 0 | ... O33: =IF(O$7="","",Inputs!O35*O$7) -> 0 | P33: =SUM(F33:O33) -> 5500000 | Q33: ='Pro Forma Cap Table'!Q14 -> 3000000 | R33: =Q33/$Q$26 -> 0.09603073 | S33: ='Pro Forma Cap Table'!S14 -> 0.09603073 | T33: =SUM(F33:O33) -> 5500000
B34: =IF(Inputs!E36=0,Inputs!D36,CONCATENATE(Inputs!D36," (",Inputs!E36,")")) -> Inv F | C34: =IF(C$7="","",Inputs!P36*C$7) -> 0 | D34: =IF(D$7="","",Inputs!Q36*D$7) -> 0 | E34: =SUM(C34:D34) -> 0 | F34: =IF(F$7="","",Inputs!F36*F$7) -> 0 | G34: =IF(G$7="","",Inputs!G36*G$7) -> 0 | H34: =IF(H$7="","",Inputs!H36*H$7) -> 2500000 | I34: =IF(I$7="","",Inputs!I36*I$7) -> 6666666.7 | J34: =IF(J$7="","",Inputs!J36*J$7) -> 0 | K34: =IF(K$7="","",Inputs!K36*K$7) -> 0 | L34: =IF(L$7="","",Inputs!L36*L$7) -> 0 | M34: =IF(M$7="","",Inputs!M36*M$7) -> 0 | ... O34: =IF(O$7="","",Inputs!O36*O$7) -> 0 | P34: =SUM(F34:O34) -> 9166666.7 | Q34: ='Pro Forma Cap Table'!Q15 -> 4333333.3 | R34: =Q34/$Q$26 -> 0.13871105 | S34: ='Pro Forma Cap Table'!S15 -> 0.13871105 | T34: =SUM(F34:O34) -> 9166666.7
B35: =IF(Inputs!E37=0,Inputs!D37,CONCATENATE(Inputs!D37," (",Inputs!E37,")")) -> Inv G | C35: =IF(C$7="","",Inputs!P37*C$7) -> 0 | D35: =IF(D$7="","",Inputs!Q37*D$7) -> 0 | E35: =SUM(C35:D35) -> 0 | F35: =IF(F$7="","",Inputs!F37*F$7) -> 0 | G35: =IF(G$7="","",Inputs!G37*G$7) -> 0 | H35: =IF(H$7="","",Inputs!H37*H$7) -> 2500000 | I35: =IF(I$7="","",Inputs!I37*I$7) -> 6666666.7 | J35: =IF(J$7="","",Inputs!J37*J$7) -> 0 | K35: =IF(K$7="","",Inputs!K37*K$7) -> 0 | L35: =IF(L$7="","",Inputs!L37*L$7) -> 0 | M35: =IF(M$7="","",Inputs!M37*M$7) -> 0 | ... O35: =IF(O$7="","",Inputs!O37*O$7) -> 0 | P35: =SUM(F35:O35) -> 9166666.7 | Q35: ='Pro Forma Cap Table'!Q16 -> 4333333.3 | R35: =Q35/$Q$26 -> 0.13871105 | S35: ='Pro Forma Cap Table'!S16 -> 0.13871105 | T35: =SUM(F35:O35) -> 9166666.7
B36: =IF(Inputs!E38=0,Inputs!D38,CONCATENATE(Inputs!D38," (",Inputs!E38,")")) -> Inv H | C36: =IF(C$7="","",Inputs!P38*C$7) -> 0 | D36: =IF(D$7="","",Inputs!Q38*D$7) -> 0 | E36: =SUM(C36:D36) -> 0 | F36: =IF(F$7="","",Inputs!F38*F$7) -> 0 | G36: =IF(G$7="","",Inputs!G38*G$7) -> 0 | H36: =IF(H$7="","",Inputs!H38*H$7) -> 2500000 | I36: =IF(I$7="","",Inputs!I38*I$7) -> 6666666.7 | J36: =IF(J$7="","",Inputs!J38*J$7) -> 0 | K36: =IF(K$7="","",Inputs!K38*K$7) -> 0 | L36: =IF(L$7="","",Inputs!L38*L$7) -> 0 | M36: =IF(M$7="","",Inputs!M38*M$7) -> 0 | ... O36: =IF(O$7="","",Inputs!O38*O$7) -> 0 | P36: =SUM(F36:O36) -> 9166666.7 | Q36: ='Pro Forma Cap Table'!Q17 -> 4333333.3 | R36: =Q36/$Q$26 -> 0.13871105 | S36: ='Pro Forma Cap Table'!S17 -> 0.13871105 | T36: =SUM(F36:O36) -> 9166666.7
B37: =Inputs!D39 -> Other Investors | C37: =IF(C$7="","",Inputs!P39*C$7) -> 0 | D37: =IF(D$7="","",Inputs!Q39*D$7) -> 0 | E37: =SUM(C37:D37) -> 0 | F37: =IF(F$7="","",Inputs!F39*F$7) -> 0 | G37: =IF(G$7="","",Inputs!G39*G$7) -> 0 | H37: =IF(H$7="","",Inputs!H39*H$7) -> 0 | I37: =IF(I$7="","",Inputs!I39*I$7) -> 0 | J37: =IF(J$7="","",Inputs!J39*J$7) -> 0 | K37: =IF(K$7="","",Inputs!K39*K$7) -> 0 | L37: =IF(L$7="","",Inputs!L39*L$7) -> 0 | M37: =IF(M$7="","",Inputs!M39*M$7) -> 0 | ... O37: =IF(O$7="","",Inputs!O39*O$7) -> 0 | P37: =SUM(F37:O37) -> 0 | Q37: ='Pro Forma Cap Table'!Q18 -> 0 | R37: =Q37/$Q$26 -> 0 | S37: ='Pro Forma Cap Table'!S18 -> 0 | T37: =SUM(F37:O37) -> 0
B38: Warrants By Series | C38: =C19*Inputs!$K$20 -> 0 | D38: =D19*Inputs!$K$20 -> 0 | F38: =F19*Inputs!O10 -> 10000 | G38: =G19*Inputs!$O11 -> 10000 | H38: =H19*Inputs!$O12 -> 10000 | I38: =I19*Inputs!$O13 -> 10000 | J38: =J19*Inputs!$O14 -> 0 | K38: =K19*Inputs!$O15 -> 0 | L38: =L19*Inputs!$O16 -> 0 | M38: =M19*Inputs!$O17 -> 0 | N38: =N19*Inputs!$O18 -> 0 | O38: =O19*Inputs!$O19 -> 0 | P38: =SUM(F38:O38) -> 40000 | Q38: ='Pro Forma Cap Table'!Q19 -> 40000 | R38: =Q38/$Q$26 -> 0.0012804097 | S38: ='Pro Forma Cap Table'!S19 -> 0.0012804097 | T38: =SUM(F38:O38) -> 40000
B39: Subtotal Investors | C39: =SUM(C29:C37) -> 0 | D39: =SUM(D29:D37) -> 0 | E39: =SUM(E29:E37) -> 0 | F39: =SUM(F29:F38) -> 5010000 | G39: =SUM(G29:G38) -> 10010000 | H39: =SUM(H29:H38) -> 15010000 | I39: =SUM(I29:I38) -> 20010000 | J39: =SUM(J29:J38) -> 0 | K39: =SUM(K29:K38) -> 0 | L39: =SUM(L29:L38) -> 0 | M39: =SUM(M29:M38) -> 0 | ... T39: =SUM(T29:T38) -> 50040000
B41: =Inputs!D40 -> Management | C41: =IF(C$7=0,0,Inputs!M22*C7) -> 0.052 | D41: =IF(D$7=0,0,Inputs!M23*D7) -> 0 | E41: =SUM(C41:D41) -> 0.052 | F41: =IF(F$7=0,0,Inputs!F40*F$7) -> 0 | G41: =IF(G$7=0,0,Inputs!G40*G$7) -> 0 | H41: =IF(H$7=0,0,Inputs!H40*H$7) -> 0 | I41: =IF(I$7=0,0,Inputs!I40*I$7) -> 0 | J41: =IF(J$7=0,0,Inputs!J40*J$7) -> 0 | K41: =IF(K$7=0,0,Inputs!K40*K$7) -> 0 | L41: =IF(L$7=0,0,Inputs!L40*L$7) -> 0 | M41: =IF(M$7=0,0,Inputs!M40*M$7) -> 0 | ... O41: =IF(O$7=0,0,Inputs!O40*O$7) -> 0 | P41: =SUM(F41:O41) -> 0 | Q41: =Q22 -> 5200000 | R41: =Q41/Q$26 -> 0.16645327 | S41: ='Pro Forma Cap Table'!S22 -> 0.16645327 | T41: =T22 -> 0
B43: Subtotal Managers | C43: =SUM(C41:C42) -> 0.052 | D43: =SUM(D41:D42) -> 0 | E43: =SUM(E41:E42) -> 0.052 | F43: =SUM(F41:F42) -> 0 | G43: =SUM(G41:G42) -> 0 | H43: =SUM(H41:H42) -> 0 | I43: =SUM(I41:I42) -> 0 | J43: =SUM(J41:J42) -> 0 | ... T43: =SUM(T41:T42) -> 0
B45: Total Dollars | C45: =C2120*C7 -> 0.052 | D45: =D2120*D7 -> 0 | E45: =SUM(C45:D45) -> 0.052 | F45: =IF(F7=0,"N/A",F$2120*F$7) -> 5010000 | G45: =IF(G7=0,"N/A",G$2120*G$7) -> 10020000 | H45: =IF(H7=0,"N/A",H$2120*H$7) -> 15025000 | I45: =IF(I7=0,"N/A",I$2120*I$7) -> 20020000 | J45: =IF(J7=0,"N/A",J$2120*J$7) -> N/A | K45: =IF(K7=0,"N/A",K$2120*K$7) -> N/A | L45: =IF(L7=0,"N/A",L$2120*L$7) -> N/A | M45: =IF(M7=0,"N/A",M$2120*M$7) -> N/A | ... O45: =IF(O7=0,"N/A",O$2120*O$7) -> N/A | P45: =SUM(F45:O45) -> 50075000 | R45: =R39+R43 -> 1 | S45: =S39+S43 -> 1 | T45: =T39+T43 -> 50040000
D46: Post-Money | F46: {=IF(TRANSPOSE(Inputs!F$10:F$19)=0,"N/A",TRANSPOSE(Inputs!F$10:F$19))} -> N/A | G46: N/A | H46: N/A | I46: N/A | J46: N/A | K46: N/A | L46: N/A | M46: N/A | N46: N/A | O46: N/A | Q46: Total Liquidation Preference | T46: =F2121*F47+G2121*G47+H2121*H47+I2121*I47+J2121*J47+K2121*K47+L2121*L47+M2121*M47+N2121*N47+O2121*O47 -> 50075000
D47: Liq. Pref. Multiple | F47: {=IF(TRANSPOSE(Inputs!G$10:G$19)=0,0,TRANSPOSE(Inputs!G$10:G$19))} -> 1 | G47: 1 | H47: 1 | I47: 1 | J47: 1 | K47: 1 | L47: 1 | M47: 1 | N47: 1 | O47: 1 | Q47: =IF(G7=0,F6,IF(H7=0,G6,IF(I7=0,H6,IF(J7=0,I6,IF(K7=0,J6,IF(L7=0,K6,IF(M7=0,L6,IF(N7=0,M6,IF(O7=0,N6,O6))))))))) -> Series D | R47: ful. dil. post-money valuation of | T47: =R48*Q26 -> 62480000
D48: Cap | F48: {=IF(TRANSPOSE(Inputs!H$10:H$19)=0,0,TRANSPOSE(Inputs!H$10:H$19))} -> 2 | G48: 2 | H48: 2 | I48: 2 | J48: 2 | K48: 2 | L48: 2 | M48: 2 | N48: 2 | O48: 2 | Q48: Based on | R48: =IF(G7=0,F7,IF(H7=0,G7,IF(I7=0,H7,IF(J7=0,I7,IF(K7=0,J7,IF(L7=0,K7,IF(M7=0,L7,IF(N7=0,M7,IF(O7=0,N7,O7))))))))) -> 2 | S48: per share price.
D49: Participating Preferred | F49: =IF(F47=0,"",IF(F48<=F47,"No","Yes")) -> Yes | G49: =IF(G47=0,"",IF(G48<=G47,"No","Yes")) -> Yes | H49: =IF(H47=0,"",IF(H48<=H47,"No","Yes")) -> Yes | I49: =IF(I47=0,"",IF(I48<=I47,"No","Yes")) -> Yes | J49: =IF(J47=0,"",IF(J48<=J47,"No","Yes")) -> Yes | K49: =IF(K47=0,"",IF(K48<=K47,"No","Yes")) -> Yes | L49: =IF(L47=0,"",IF(L48<=L47,"No","Yes")) -> Yes | M49: =IF(M47=0,"",IF(M48<=M47,"No","Yes")) -> Yes | ... O49: =IF(O47=0,"",IF(O48<=O47,"No","Yes")) -> Yes | Q49: Footnotes
D50: Seniority (1 = highest) | F50: {=IF(TRANSPOSE(Inputs!I$10:I$19)=0,"",TRANSPOSE(Inputs!I$10:I$19))} -> 10 | G50: 10 | H50: 2 | I50: 1 | J50: 10 | K50: 10 | L50: 10 | M50: 10 | N50: 10 | O50: 10 | Q50: =IF(Inputs!E45="Text Here","HIDE ROW", CONCATENATE(Inputs!D45, Inputs!E45)) -> *
D51: Conversion Ratio | F51: {=IF(TRANSPOSE(Inputs!J$10:J$19)=0,0,TRANSPOSE(Inputs!J$10:J$19))} -> 1 | G51: 1 | H51: 1 | I51: 1 | J51: 1 | K51: 1 | L51: 1 | M51: 1 | N51: 1 | O51: 1 | Q51: =IF(Inputs!E46="Text Here","HIDE ROW", CONCATENATE(Inputs!D46, Inputs!E46)) -> **
Q52: =IF(Inputs!E47="Text Here","HIDE ROW", CONCATENATE(Inputs!D47," ",Inputs!E47)) -> ***
F53: =SUM(F2121:O2121) -> 50075000 | Q53: =IF(Inputs!E48="Text Here","HIDE ROW", CONCATENATE(Inputs!D48," ",Inputs!E48)) -> ****
B55: Expected Exit Time | C55: 40999
B56: Incremental (in days) | C56: 180
E61: Strike price | F61: =Inputs!$O10 -> 1 | G61: =Inputs!$O11 -> 1 | H61: =Inputs!$O12 -> 1 | I61: =Inputs!$O13 -> 1 | J61: =Inputs!$O14 -> 0 | K61: =Inputs!$O15 -> 0 | L61: =Inputs!$O16 -> 0 | M61: =Inputs!$O17 -> 0 | N61: =Inputs!$O18 -> 0 | O61: =Inputs!$O19 -> 0
E62: Pref Liq pref | F62: =F47*SUM(F10:F18)*F7 -> 5000000 | G62: =G47*SUM(G10:G18)*G7 -> 10000000 | H62: =H47*SUM(H10:H18)*H7 -> 15000000 | I62: =I47*SUM(I10:I18)*I7 -> 20000000 | J62: =J47*SUM(J10:J18)*J7 -> 0 | K62: =K47*SUM(K10:K18)*K7 -> 0 | L62: =L47*SUM(L10:L18)*L7 -> 0 | M62: =M47*SUM(M10:M18)*M7 -> 0 | ... O62: =O47*SUM(O10:O18)*O7 -> 0
E63: War Liq pref | F63: =MAX(0,(F47*F61*F19-F7*F19)) -> 0 | G63: =MAX(0,(G47*G61*G19-G7*G19)) -> 0 | H63: =MAX(0,(H47*H61*H19-H7*H19)) -> 0 | I63: =MAX(0,(I47*I61*I19-I7*I19)) -> 0 | J63: =MAX(0,(J47*J61*J19-J7*J19)) -> 0 | K63: =MAX(0,(K47*K61*K19-K7*K19)) -> 0 | L63: =MAX(0,(L47*L61*L19-L7*L19)) -> 0 | M63: =MAX(0,(M47*M61*M19-M7*M19)) -> 0 | ... O63: =MAX(0,(O47*O61*O19-O7*O19)) -> 0
F66: =B129 -> Series A | G66: =B130 -> Series B | H66: =B131 -> Series C | I66: =B132 -> Series D | J66: =B133 -> - | K66: =B134 -> - | L66: =B135 -> - | M66: =B136 -> - | N66: =B137 -> - | O66: =B138 -> -
B81: Equity Value | C81: =C822 -> 0 | N81: Equity Value | O81: =D822 -> 0 | Z81: Equity Value | AA81: =E822 -> 0 | AL81: Equity Value | AM81: =F822 -> 0 | AX81: Equity Value | AY81: =G822 -> 0 | BJ81: Equity Value | BK81: =H822 -> 0 | BV81: Equity Value | BW81: =I822 -> 0 | CH81: Equity Value | CI81: =J822 -> 0 | CT81: Equity Value | CU81: =K822 -> 0 | DF81: Equity Value | DG81: =L822 -> 0
B85: Liquidation Preference Payout | N85: Liquidation Preference Payout | Z85: Liquidation Preference Payout | AL85: Liquidation Preference Payout | AX85: Liquidation Preference Payout | BJ85: Liquidation Preference Payout | BV85: Liquidation Preference Payout | CH85: Liquidation Preference Payout | CT85: Liquidation Preference Payout | DF85: Liquidation Preference Payout
B86: Seniority 1 | C86: =IF(SUMIF($F$50:$O$50,"=1",$F$62:$O$62)<=C81,SUMIF($F$50:$O$50,"=1",$F$62:$O$62),C81) -> 0 | D86: 1 | N86: Seniority 1 | O86: =IF(SUMIF($F$50:$O$50,"=1",$F$62:$O$62)<=O81,SUMIF($F$50:$O$50,"=1",$F$62:$O$62),O81) -> 0 | P86: 1 | Z86: Seniority 1 | AA86: =IF(SUMIF($F$50:$O$50,"=1",$F$62:$O$62)<=AA81,SUMIF($F$50:$O$50,"=1",$F$62:$O$62),AA81) -> 0 | AB86: 1 | AL86: Seniority 1 | AM86: =IF(SUMIF($F$50:$O$50,"=1",$F$62:$O$62)<=AM81,SUMIF($F$50:$O$50,"=1",$F$62:$O$62),AM81) -> 0 | AN86: 1 | AX86: Seniority 1 | AY86: =IF(SUMIF($F$50:$O$50,"=1",$F$62:$O$62)<=AY81,SUMIF($F$50:$O$50,"=1",$F$62:$O$62),AY81) -> 0 | AZ86: 1 | BJ86: Seniority 1 | BK86: =IF(SUMIF($F$50:$O$50,"=1",$F$62:$O$62)<=BK81,SUMIF($F$50:$O$50,"=1",$F$62:$O$62),BK81) -> 0 | BL86: 1 | BV86: Seniority 1 | BW86: =IF(SUMIF($F$50:$O$50,"=1",$F$62:$O$62)<=BW81,SUMIF($F$50:$O$50,"=1",$F$62:$O$62),BW81) -> 0 | BX86: 1 | CH86: Seniority 1 | CI86: =IF(SUMIF($F$50:$O$50,"=1",$F$62:$O$62)<=CI81,SUMIF($F$50:$O$50,"=1",$F$62:$O$62),CI81) -> 0 | CJ86: 1 | CT86: Seniority 1 | CU86: =IF(SUMIF($F$50:$O$50,"=1",$F$62:$O$62)<=CU81,SUMIF($F$50:$O$50,"=1",$F$62:$O$62),CU81) -> 0 | CV86: 1 | DF86: Seniority 1 | DG86: =IF(SUMIF($F$50:$O$50,"=1",$F$62:$O$62)<=DG81,SUMIF($F$50:$O$50,"=1",$F$62:$O$62),DG81) -> 0 | DH86: 1
C87: =C81-C86 -> 0 | O87: =O81-O86 -> 0 | AA87: =AA81-AA86 -> 0 | AM87: =AM81-AM86 -> 0 | AY87: =AY81-AY86 -> 0 | BK87: =BK81-BK86 -> 0 | BW87: =BW81-BW86 -> 0 | CI87: =CI81-CI86 -> 0 | CU87: =CU81-CU86 -> 0 | DG87: =DG81-DG86 -> 0
B88: Seniority 1 - warrants | C88: =IF(SUMIF($F$50:$O$50,"=1",$F$63:$O$63)<=C87,SUMIF($F$50:$O$50,"=1",$F$63:$O$63),C87) -> 0 | E88: 1 | N88: Seniority 1 - warrants | O88: =IF(SUMIF($F$50:$O$50,"=1",$F$63:$O$63)<=O87,SUMIF($F$50:$O$50,"=1",$F$63:$O$63),O87) -> 0 | Q88: 1 | Z88: Seniority 1 - warrants | AA88: =IF(SUMIF($F$50:$O$50,"=1",$F$63:$O$63)<=AA87,SUMIF($F$50:$O$50,"=1",$F$63:$O$63),AA87) -> 0 | AC88: 1 | AL88: Seniority 1 - warrants | AM88: =IF(SUMIF($F$50:$O$50,"=1",$F$63:$O$63)<=AM87,SUMIF($F$50:$O$50,"=1",$F$63:$O$63),AM87) -> 0 | AO88: 1 | AX88: Seniority 1 - warrants | AY88: =IF(SUMIF($F$50:$O$50,"=1",$F$63:$O$63)<=AY87,SUMIF($F$50:$O$50,"=1",$F$63:$O$63),AY87) -> 0 | BA88: 1 | BJ88: Seniority 1 - warrants | BK88: =IF(SUMIF($F$50:$O$50,"=1",$F$63:$O$63)<=BK87,SUMIF($F$50:$O$50,"=1",$F$63:$O$63),BK87) -> 0 | BM88: 1 | BV88: Seniority 1 - warrants | BW88: =IF(SUMIF($F$50:$O$50,"=1",$F$63:$O$63)<=BW87,SUMIF($F$50:$O$50,"=1",$F$63:$O$63),BW87) -> 0 | BY88: 1 | CH88: Seniority 1 - warrants | CI88: =IF(SUMIF($F$50:$O$50,"=1",$F$63:$O$63)<=CI87,SUMIF($F$50:$O$50,"=1",$F$63:$O$63),CI87) -> 0 | CK88: 1 | CT88: Seniority 1 - warrants | CU88: =IF(SUMIF($F$50:$O$50,"=1",$F$63:$O$63)<=CU87,SUMIF($F$50:$O$50,"=1",$F$63:$O$63),CU87) -> 0 | CW88: 1 | DF88: Seniority 1 - warrants | DG88: =IF(SUMIF($F$50:$O$50,"=1",$F$63:$O$63)<=DG87,SUMIF($F$50:$O$50,"=1",$F$63:$O$63),DG87) -> 0 | DI88: 1
C89: =C87-C88 -> 0 | O89: =O87-O88 -> 0 | AA89: =AA87-AA88 -> 0 | AM89: =AM87-AM88 -> 0 | AY89: =AY87-AY88 -> 0 | BK89: =BK87-BK88 -> 0 | BW89: =BW87-BW88 -> 0 | CI89: =CI87-CI88 -> 0 | CU89: =CU87-CU88 -> 0 | DG89: =DG87-DG88 -> 0
B90: Seniority 2 | C90: =IF(SUMIF($F$50:$O$50,"=2",$F$62:$O$62)<=C89,SUMIF($F$50:$O$50,"=2",$F$62:$O$62),C89) -> 0 | D90: 2 | N90: Seniority 2 | O90: =IF(SUMIF($F$50:$O$50,"=2",$F$62:$O$62)<=O89,SUMIF($F$50:$O$50,"=2",$F$62:$O$62),O89) -> 0 | P90: 2 | Z90: Seniority 2 | AA90: =IF(SUMIF($F$50:$O$50,"=2",$F$62:$O$62)<=AA89,SUMIF($F$50:$O$50,"=2",$F$62:$O$62),AA89) -> 0 | AB90: 2 | AL90: Seniority 2 | AM90: =IF(SUMIF($F$50:$O$50,"=2",$F$62:$O$62)<=AM89,SUMIF($F$50:$O$50,"=2",$F$62:$O$62),AM89) -> 0 | AN90: 2 | AX90: Seniority 2 | AY90: =IF(SUMIF($F$50:$O$50,"=2",$F$62:$O$62)<=AY89,SUMIF($F$50:$O$50,"=2",$F$62:$O$62),AY89) -> 0 | AZ90: 2 | BJ90: Seniority 2 | BK90: =IF(SUMIF($F$50:$O$50,"=2",$F$62:$O$62)<=BK89,SUMIF($F$50:$O$50,"=2",$F$62:$O$62),BK89) -> 0 | BL90: 2 | BV90: Seniority 2 | BW90: =IF(SUMIF($F$50:$O$50,"=2",$F$62:$O$62)<=BW89,SUMIF($F$50:$O$50,"=2",$F$62:$O$62),BW89) -> 0 | BX90: 2 | CH90: Seniority 2 | CI90: =IF(SUMIF($F$50:$O$50,"=2",$F$62:$O$62)<=CI89,SUMIF($F$50:$O$50,"=2",$F$62:$O$62),CI89) -> 0 | CJ90: 2 | CT90: Seniority 2 | CU90: =IF(SUMIF($F$50:$O$50,"=2",$F$62:$O$62)<=CU89,SUMIF($F$50:$O$50,"=2",$F$62:$O$62),CU89) -> 0 | CV90: 2 | DF90: Seniority 2 | DG90: =IF(SUMIF($F$50:$O$50,"=2",$F$62:$O$62)<=DG89,SUMIF($F$50:$O$50,"=2",$F$62:$O$62),DG89) -> 0 | DH90: 2
C91: =C89-C90 -> 0 | O91: =O89-O90 -> 0 | AA91: =AA89-AA90 -> 0 | AM91: =AM89-AM90 -> 0 | AY91: =AY89-AY90 -> 0 | BK91: =BK89-BK90 -> 0 | BW91: =BW89-BW90 -> 0 | CI91: =CI89-CI90 -> 0 | CU91: =CU89-CU90 -> 0 | DG91: =DG89-DG90 -> 0
B92: Seniority 2 - warrants | C92: =IF(SUMIF($F$50:$O$50,"=2",$F$63:$O$63)<=C91,SUMIF($F$50:$O$50,"=2",$F$63:$O$63),C91) -> 0 | E92: 2 | N92: Seniority 2 - warrants | O92: =IF(SUMIF($F$50:$O$50,"=2",$F$63:$O$63)<=O91,SUMIF($F$50:$O$50,"=2",$F$63:$O$63),O91) -> 0 | Q92: 2 | Z92: Seniority 2 - warrants | AA92: =IF(SUMIF($F$50:$O$50,"=2",$F$63:$O$63)<=AA91,SUMIF($F$50:$O$50,"=2",$F$63:$O$63),AA91) -> 0 | AC92: 2 | AL92: Seniority 2 - warrants | AM92: =IF(SUMIF($F$50:$O$50,"=2",$F$63:$O$63)<=AM91,SUMIF($F$50:$O$50,"=2",$F$63:$O$63),AM91) -> 0 | AO92: 2 | AX92: Seniority 2 - warrants | AY92: =IF(SUMIF($F$50:$O$50,"=2",$F$63:$O$63)<=AY91,SUMIF($F$50:$O$50,"=2",$F$63:$O$63),AY91) -> 0 | BA92: 2 | BJ92: Seniority 2 - warrants | BK92: =IF(SUMIF($F$50:$O$50,"=2",$F$63:$O$63)<=BK91,SUMIF($F$50:$O$50,"=2",$F$63:$O$63),BK91) -> 0 | BM92: 2 | BV92: Seniority 2 - warrants | BW92: =IF(SUMIF($F$50:$O$50,"=2",$F$63:$O$63)<=BW91,SUMIF($F$50:$O$50,"=2",$F$63:$O$63),BW91) -> 0 | BY92: 2 | CH92: Seniority 2 - warrants | CI92: =IF(SUMIF($F$50:$O$50,"=2",$F$63:$O$63)<=CI91,SUMIF($F$50:$O$50,"=2",$F$63:$O$63),CI91) -> 0 | CK92: 2 | CT92: Seniority 2 - warrants | CU92: =IF(SUMIF($F$50:$O$50,"=2",$F$63:$O$63)<=CU91,SUMIF($F$50:$O$50,"=2",$F$63:$O$63),CU91) -> 0 | CW92: 2 | DF92: Seniority 2 - warrants | DG92: =IF(SUMIF($F$50:$O$50,"=2",$F$63:$O$63)<=DG91,SUMIF($F$50:$O$50,"=2",$F$63:$O$63),DG91) -> 0 | DI92: 2
C93: =C91-C92 -> 0 | O93: =O91-O92 -> 0 | AA93: =AA91-AA92 -> 0 | AM93: =AM91-AM92 -> 0 | AY93: =AY91-AY92 -> 0 | BK93: =BK91-BK92 -> 0 | BW93: =BW91-BW92 -> 0 | CI93: =CI91-CI92 -> 0 | CU93: =CU91-CU92 -> 0 | DG93: =DG91-DG92 -> 0
B94: Seniority 3 | C94: =IF(SUMIF($F$50:$O$50,"=3",$F$62:$O$62)<=C93,SUMIF($F$50:$O$50,"=3",$F$62:$O$62),C93) -> 0 | D94: 3 | N94: Seniority 3 | O94: =IF(SUMIF($F$50:$O$50,"=3",$F$62:$O$62)<=O93,SUMIF($F$50:$O$50,"=3",$F$62:$O$62),O93) -> 0 | P94: 3 | Z94: Seniority 3 | AA94: =IF(SUMIF($F$50:$O$50,"=3",$F$62:$O$62)<=AA93,SUMIF($F$50:$O$50,"=3",$F$62:$O$62),AA93) -> 0 | AB94: 3 | AL94: Seniority 3 | AM94: =IF(SUMIF($F$50:$O$50,"=3",$F$62:$O$62)<=AM93,SUMIF($F$50:$O$50,"=3",$F$62:$O$62),AM93) -> 0 | AN94: 3 | AX94: Seniority 3 | AY94: =IF(SUMIF($F$50:$O$50,"=3",$F$62:$O$62)<=AY93,SUMIF($F$50:$O$50,"=3",$F$62:$O$62),AY93) -> 0 | AZ94: 3 | BJ94: Seniority 3 | BK94: =IF(SUMIF($F$50:$O$50,"=3",$F$62:$O$62)<=BK93,SUMIF($F$50:$O$50,"=3",$F$62:$O$62),BK93) -> 0 | BL94: 3 | BV94: Seniority 3 | BW94: =IF(SUMIF($F$50:$O$50,"=3",$F$62:$O$62)<=BW93,SUMIF($F$50:$O$50,"=3",$F$62:$O$62),BW93) -> 0 | BX94: 3 | CH94: Seniority 3 | CI94: =IF(SUMIF($F$50:$O$50,"=3",$F$62:$O$62)<=CI93,SUMIF($F$50:$O$50,"=3",$F$62:$O$62),CI93) -> 0 | CJ94: 3 | CT94: Seniority 3 | CU94: =IF(SUMIF($F$50:$O$50,"=3",$F$62:$O$62)<=CU93,SUMIF($F$50:$O$50,"=3",$F$62:$O$62),CU93) -> 0 | CV94: 3 | DF94: Seniority 3 | DG94: =IF(SUMIF($F$50:$O$50,"=3",$F$62:$O$62)<=DG93,SUMIF($F$50:$O$50,"=3",$F$62:$O$62),DG93) -> 0 | DH94: 3
C95: =C93-C94 -> 0 | O95: =O93-O94 -> 0 | AA95: =AA93-AA94 -> 0 | AM95: =AM93-AM94 -> 0 | AY95: =AY93-AY94 -> 0 | BK95: =BK93-BK94 -> 0 | BW95: =BW93-BW94 -> 0 | CI95: =CI93-CI94 -> 0 | CU95: =CU93-CU94 -> 0 | DG95: =DG93-DG94 -> 0
B96: Seniority 3 - warrants | C96: =IF(SUMIF($F$50:$O$50,"=3",$F$63:$O$63)<=C95,SUMIF($F$50:$O$50,"=3",$F$63:$O$63),C95) -> 0 | E96: 3 | N96: Seniority 3 - warrants | O96: =IF(SUMIF($F$50:$O$50,"=3",$F$63:$O$63)<=O95,SUMIF($F$50:$O$50,"=3",$F$63:$O$63),O95) -> 0 | Q96: 3 | Z96: Seniority 3 - warrants | AA96: =IF(SUMIF($F$50:$O$50,"=3",$F$63:$O$63)<=AA95,SUMIF($F$50:$O$50,"=3",$F$63:$O$63),AA95) -> 0 | AC96: 3 | AL96: Seniority 3 - warrants | AM96: =IF(SUMIF($F$50:$O$50,"=3",$F$63:$O$63)<=AM95,SUMIF($F$50:$O$50,"=3",$F$63:$O$63),AM95) -> 0 | AO96: 3 | AX96: Seniority 3 - warrants | AY96: =IF(SUMIF($F$50:$O$50,"=3",$F$63:$O$63)<=AY95,SUMIF($F$50:$O$50,"=3",$F$63:$O$63),AY95) -> 0 | BA96: 3 | BJ96: Seniority 3 - warrants | BK96: =IF(SUMIF($F$50:$O$50,"=3",$F$63:$O$63)<=BK95,SUMIF($F$50:$O$50,"=3",$F$63:$O$63),BK95) -> 0 | BM96: 3 | BV96: Seniority 3 - warrants | BW96: =IF(SUMIF($F$50:$O$50,"=3",$F$63:$O$63)<=BW95,SUMIF($F$50:$O$50,"=3",$F$63:$O$63),BW95) -> 0 | BY96: 3 | CH96: Seniority 3 - warrants | CI96: =IF(SUMIF($F$50:$O$50,"=3",$F$63:$O$63)<=CI95,SUMIF($F$50:$O$50,"=3",$F$63:$O$63),CI95) -> 0 | CK96: 3 | CT96: Seniority 3 - warrants | CU96: =IF(SUMIF($F$50:$O$50,"=3",$F$63:$O$63)<=CU95,SUMIF($F$50:$O$50,"=3",$F$63:$O$63),CU95) -> 0 | CW96: 3 | DF96: Seniority 3 - warrants | DG96: =IF(SUMIF($F$50:$O$50,"=3",$F$63:$O$63)<=DG95,SUMIF($F$50:$O$50,"=3",$F$63:$O$63),DG95) -> 0 | DI96: 3
C97: =C95-C96 -> 0 | O97: =O95-O96 -> 0 | AA97: =AA95-AA96 -> 0 | AM97: =AM95-AM96 -> 0 | AY97: =AY95-AY96 -> 0 | BK97: =BK95-BK96 -> 0 | BW97: =BW95-BW96 -> 0 | CI97: =CI95-CI96 -> 0 | CU97: =CU95-CU96 -> 0 | DG97: =DG95-DG96 -> 0
B98: Seniority 4 | C98: =IF(SUMIF($F$50:$O$50,"=4",$F$62:$O$62)<=C97,SUMIF($F$50:$O$50,"=4",$F$62:$O$62),C97) -> 0 | D98: 4 | N98: Seniority 4 | O98: =IF(SUMIF($F$50:$O$50,"=4",$F$62:$O$62)<=O97,SUMIF($F$50:$O$50,"=4",$F$62:$O$62),O97) -> 0 | P98: 4 | Z98: Seniority 4 | AA98: =IF(SUMIF($F$50:$O$50,"=4",$F$62:$O$62)<=AA97,SUMIF($F$50:$O$50,"=4",$F$62:$O$62),AA97) -> 0 | AB98: 4 | AL98: Seniority 4 | AM98: =IF(SUMIF($F$50:$O$50,"=4",$F$62:$O$62)<=AM97,SUMIF($F$50:$O$50,"=4",$F$62:$O$62),AM97) -> 0 | AN98: 4 | AX98: Seniority 4 | AY98: =IF(SUMIF($F$50:$O$50,"=4",$F$62:$O$62)<=AY97,SUMIF($F$50:$O$50,"=4",$F$62:$O$62),AY97) -> 0 | AZ98: 4 | BJ98: Seniority 4 | BK98: =IF(SUMIF($F$50:$O$50,"=4",$F$62:$O$62)<=BK97,SUMIF($F$50:$O$50,"=4",$F$62:$O$62),BK97) -> 0 | BL98: 4 | BV98: Seniority 4 | BW98: =IF(SUMIF($F$50:$O$50,"=4",$F$62:$O$62)<=BW97,SUMIF($F$50:$O$50,"=4",$F$62:$O$62),BW97) -> 0 | BX98: 4 | CH98: Seniority 4 | CI98: =IF(SUMIF($F$50:$O$50,"=4",$F$62:$O$62)<=CI97,SUMIF($F$50:$O$50,"=4",$F$62:$O$62),CI97) -> 0 | CJ98: 4 | CT98: Seniority 4 | CU98: =IF(SUMIF($F$50:$O$50,"=4",$F$62:$O$62)<=CU97,SUMIF($F$50:$O$50,"=4",$F$62:$O$62),CU97) -> 0 | CV98: 4 | DF98: Seniority 4 | DG98: =IF(SUMIF($F$50:$O$50,"=4",$F$62:$O$62)<=DG97,SUMIF($F$50:$O$50,"=4",$F$62:$O$62),DG97) -> 0 | DH98: 4
C99: =C97-C98 -> 0 | O99: =O97-O98 -> 0 | AA99: =AA97-AA98 -> 0 | AM99: =AM97-AM98 -> 0 | AY99: =AY97-AY98 -> 0 | BK99: =BK97-BK98 -> 0 | BW99: =BW97-BW98 -> 0 | CI99: =CI97-CI98 -> 0 | CU99: =CU97-CU98 -> 0 | DG99: =DG97-DG98 -> 0
B100: Seniority 4 - warrants | C100: =IF(SUMIF($F$50:$O$50,"=4",$F$63:$O$63)<=C99,SUMIF($F$50:$O$50,"=4",$F$63:$O$63),C99) -> 0 | E100: 4 | N100: Seniority 4 - warrants | O100: =IF(SUMIF($F$50:$O$50,"=4",$F$63:$O$63)<=O99,SUMIF($F$50:$O$50,"=4",$F$63:$O$63),O99) -> 0 | Q100: 4 | Z100: Seniority 4 - warrants | AA100: =IF(SUMIF($F$50:$O$50,"=4",$F$63:$O$63)<=AA99,SUMIF($F$50:$O$50,"=4",$F$63:$O$63),AA99) -> 0 | AC100: 4 | AL100: Seniority 4 - warrants | AM100: =IF(SUMIF($F$50:$O$50,"=4",$F$63:$O$63)<=AM99,SUMIF($F$50:$O$50,"=4",$F$63:$O$63),AM99) -> 0 | AO100: 4 | AX100: Seniority 4 - warrants | AY100: =IF(SUMIF($F$50:$O$50,"=4",$F$63:$O$63)<=AY99,SUMIF($F$50:$O$50,"=4",$F$63:$O$63),AY99) -> 0 | BA100: 4 | BJ100: Seniority 4 - warrants | BK100: =IF(SUMIF($F$50:$O$50,"=4",$F$63:$O$63)<=BK99,SUMIF($F$50:$O$50,"=4",$F$63:$O$63),BK99) -> 0 | BM100: 4 | BV100: Seniority 4 - warrants | BW100: =IF(SUMIF($F$50:$O$50,"=4",$F$63:$O$63)<=BW99,SUMIF($F$50:$O$50,"=4",$F$63:$O$63),BW99) -> 0 | BY100: 4 | CH100: Seniority 4 - warrants | CI100: =IF(SUMIF($F$50:$O$50,"=4",$F$63:$O$63)<=CI99,SUMIF($F$50:$O$50,"=4",$F$63:$O$63),CI99) -> 0 | CK100: 4 | CT100: Seniority 4 - warrants | CU100: =IF(SUMIF($F$50:$O$50,"=4",$F$63:$O$63)<=CU99,SUMIF($F$50:$O$50,"=4",$F$63:$O$63),CU99) -> 0 | CW100: 4 | DF100: Seniority 4 - warrants | DG100: =IF(SUMIF($F$50:$O$50,"=4",$F$63:$O$63)<=DG99,SUMIF($F$50:$O$50,"=4",$F$63:$O$63),DG99) -> 0 | DI100: 4
C101: =C99-C100 -> 0 | O101: =O99-O100 -> 0 | AA101: =AA99-AA100 -> 0 | AM101: =AM99-AM100 -> 0 | AY101: =AY99-AY100 -> 0 | BK101: =BK99-BK100 -> 0 | BW101: =BW99-BW100 -> 0 | CI101: =CI99-CI100 -> 0 | CU101: =CU99-CU100 -> 0 | DG101: =DG99-DG100 -> 0
B102: Seniority 5 | C102: =IF(SUMIF($F$50:$O$50,"=5",$F$62:$O$62)<=C101,SUMIF($F$50:$O$50,"=5",$F$62:$O$62),C101) -> 0 | D102: 5 | N102: Seniority 5 | O102: =IF(SUMIF($F$50:$O$50,"=5",$F$62:$O$62)<=O101,SUMIF($F$50:$O$50,"=5",$F$62:$O$62),O101) -> 0 | P102: 5 | Z102: Seniority 5 | AA102: =IF(SUMIF($F$50:$O$50,"=5",$F$62:$O$62)<=AA101,SUMIF($F$50:$O$50,"=5",$F$62:$O$62),AA101) -> 0 | AB102: 5 | AL102: Seniority 5 | AM102: =IF(SUMIF($F$50:$O$50,"=5",$F$62:$O$62)<=AM101,SUMIF($F$50:$O$50,"=5",$F$62:$O$62),AM101) -> 0 | AN102: 5 | AX102: Seniority 5 | AY102: =IF(SUMIF($F$50:$O$50,"=5",$F$62:$O$62)<=AY101,SUMIF($F$50:$O$50,"=5",$F$62:$O$62),AY101) -> 0 | AZ102: 5 | BJ102: Seniority 5 | BK102: =IF(SUMIF($F$50:$O$50,"=5",$F$62:$O$62)<=BK101,SUMIF($F$50:$O$50,"=5",$F$62:$O$62),BK101) -> 0 | BL102: 5 | BV102: Seniority 5 | BW102: =IF(SUMIF($F$50:$O$50,"=5",$F$62:$O$62)<=BW101,SUMIF($F$50:$O$50,"=5",$F$62:$O$62),BW101) -> 0 | BX102: 5 | CH102: Seniority 5 | CI102: =IF(SUMIF($F$50:$O$50,"=5",$F$62:$O$62)<=CI101,SUMIF($F$50:$O$50,"=5",$F$62:$O$62),CI101) -> 0 | CJ102: 5 | CT102: Seniority 5 | CU102: =IF(SUMIF($F$50:$O$50,"=5",$F$62:$O$62)<=CU101,SUMIF($F$50:$O$50,"=5",$F$62:$O$62),CU101) -> 0 | CV102: 5 | DF102: Seniority 5 | DG102: =IF(SUMIF($F$50:$O$50,"=5",$F$62:$O$62)<=DG101,SUMIF($F$50:$O$50,"=5",$F$62:$O$62),DG101) -> 0 | DH102: 5
C103: =C101-C102 -> 0 | O103: =O101-O102 -> 0 | AA103: =AA101-AA102 -> 0 | AM103: =AM101-AM102 -> 0 | AY103: =AY101-AY102 -> 0 | BK103: =BK101-BK102 -> 0 | BW103: =BW101-BW102 -> 0 | CI103: =CI101-CI102 -> 0 | CU103: =CU101-CU102 -> 0 | DG103: =DG101-DG102 -> 0
B104: Seniority 5 - warrants | C104: =IF(SUMIF($F$50:$O$50,"=5",$F$63:$O$63)<=C103,SUMIF($F$50:$O$50,"=5",$F$63:$O$63),C103) -> 0 | E104: 5 | N104: Seniority 5 - warrants | O104: =IF(SUMIF($F$50:$O$50,"=5",$F$63:$O$63)<=O103,SUMIF($F$50:$O$50,"=5",$F$63:$O$63),O103) -> 0 | Q104: 5 | Z104: Seniority 5 - warrants | AA104: =IF(SUMIF($F$50:$O$50,"=5",$F$63:$O$63)<=AA103,SUMIF($F$50:$O$50,"=5",$F$63:$O$63),AA103) -> 0 | AC104: 5 | AL104: Seniority 5 - warrants | AM104: =IF(SUMIF($F$50:$O$50,"=5",$F$63:$O$63)<=AM103,SUMIF($F$50:$O$50,"=5",$F$63:$O$63),AM103) -> 0 | AO104: 5 | AX104: Seniority 5 - warrants | AY104: =IF(SUMIF($F$50:$O$50,"=5",$F$63:$O$63)<=AY103,SUMIF($F$50:$O$50,"=5",$F$63:$O$63),AY103) -> 0 | BA104: 5 | BJ104: Seniority 5 - warrants | BK104: =IF(SUMIF($F$50:$O$50,"=5",$F$63:$O$63)<=BK103,SUMIF($F$50:$O$50,"=5",$F$63:$O$63),BK103) -> 0 | BM104: 5 | BV104: Seniority 5 - warrants | BW104: =IF(SUMIF($F$50:$O$50,"=5",$F$63:$O$63)<=BW103,SUMIF($F$50:$O$50,"=5",$F$63:$O$63),BW103) -> 0 | BY104: 5 | CH104: Seniority 5 - warrants | CI104: =IF(SUMIF($F$50:$O$50,"=5",$F$63:$O$63)<=CI103,SUMIF($F$50:$O$50,"=5",$F$63:$O$63),CI103) -> 0 | CK104: 5 | CT104: Seniority 5 - warrants | CU104: =IF(SUMIF($F$50:$O$50,"=5",$F$63:$O$63)<=CU103,SUMIF($F$50:$O$50,"=5",$F$63:$O$63),CU103) -> 0 | CW104: 5 | DF104: Seniority 5 - warrants | DG104: =IF(SUMIF($F$50:$O$50,"=5",$F$63:$O$63)<=DG103,SUMIF($F$50:$O$50,"=5",$F$63:$O$63),DG103) -> 0 | DI104: 5
C105: =C103-C104 -> 0 | O105: =O103-O104 -> 0 | AA105: =AA103-AA104 -> 0 | AM105: =AM103-AM104 -> 0 | AY105: =AY103-AY104 -> 0 | BK105: =BK103-BK104 -> 0 | BW105: =BW103-BW104 -> 0 | CI105: =CI103-CI104 -> 0 | CU105: =CU103-CU104 -> 0 | DG105: =DG103-DG104 -> 0
B106: Seniority 6 | C106: =IF(SUMIF($F$50:$O$50,"=6",$F$62:$O$62)<=C105,SUMIF($F$50:$O$50,"=6",$F$62:$O$62),C105) -> 0 | D106: 6 | N106: Seniority 6 | O106: =IF(SUMIF($F$50:$O$50,"=6",$F$62:$O$62)<=O105,SUMIF($F$50:$O$50,"=6",$F$62:$O$62),O105) -> 0 | P106: 6 | Z106: Seniority 6 | AA106: =IF(SUMIF($F$50:$O$50,"=6",$F$62:$O$62)<=AA105,SUMIF($F$50:$O$50,"=6",$F$62:$O$62),AA105) -> 0 | AB106: 6 | AL106: Seniority 6 | AM106: =IF(SUMIF($F$50:$O$50,"=6",$F$62:$O$62)<=AM105,SUMIF($F$50:$O$50,"=6",$F$62:$O$62),AM105) -> 0 | AN106: 6 | AX106: Seniority 6 | AY106: =IF(SUMIF($F$50:$O$50,"=6",$F$62:$O$62)<=AY105,SUMIF($F$50:$O$50,"=6",$F$62:$O$62),AY105) -> 0 | AZ106: 6 | BJ106: Seniority 6 | BK106: =IF(SUMIF($F$50:$O$50,"=6",$F$62:$O$62)<=BK105,SUMIF($F$50:$O$50,"=6",$F$62:$O$62),BK105) -> 0 | BL106: 6 | BV106: Seniority 6 | BW106: =IF(SUMIF($F$50:$O$50,"=6",$F$62:$O$62)<=BW105,SUMIF($F$50:$O$50,"=6",$F$62:$O$62),BW105) -> 0 | BX106: 6 | CH106: Seniority 6 | CI106: =IF(SUMIF($F$50:$O$50,"=6",$F$62:$O$62)<=CI105,SUMIF($F$50:$O$50,"=6",$F$62:$O$62),CI105) -> 0 | CJ106: 6 | CT106: Seniority 6 | CU106: =IF(SUMIF($F$50:$O$50,"=6",$F$62:$O$62)<=CU105,SUMIF($F$50:$O$50,"=6",$F$62:$O$62),CU105) -> 0 | CV106: 6 | DF106: Seniority 6 | DG106: =IF(SUMIF($F$50:$O$50,"=6",$F$62:$O$62)<=DG105,SUMIF($F$50:$O$50,"=6",$F$62:$O$62),DG105) -> 0 | DH106: 6
C107: =C105-C106 -> 0 | O107: =O105-O106 -> 0 | AA107: =AA105-AA106 -> 0 | AM107: =AM105-AM106 -> 0 | AY107: =AY105-AY106 -> 0 | BK107: =BK105-BK106 -> 0 | BW107: =BW105-BW106 -> 0 | CI107: =CI105-CI106 -> 0 | CU107: =CU105-CU106 -> 0 | DG107: =DG105-DG106 -> 0
B108: Seniority 6 - warrants | C108: =IF(SUMIF($F$50:$O$50,"=6",$F$63:$O$63)<=C107,SUMIF($F$50:$O$50,"=6",$F$63:$O$63),C107) -> 0 | E108: 6 | N108: Seniority 6 - warrants | O108: =IF(SUMIF($F$50:$O$50,"=6",$F$63:$O$63)<=O107,SUMIF($F$50:$O$50,"=6",$F$63:$O$63),O107) -> 0 | Q108: 6 | Z108: Seniority 6 - warrants | AA108: =IF(SUMIF($F$50:$O$50,"=6",$F$63:$O$63)<=AA107,SUMIF($F$50:$O$50,"=6",$F$63:$O$63),AA107) -> 0 | AC108: 6 | AL108: Seniority 6 - warrants | AM108: =IF(SUMIF($F$50:$O$50,"=6",$F$63:$O$63)<=AM107,SUMIF($F$50:$O$50,"=6",$F$63:$O$63),AM107) -> 0 | AO108: 6 | AX108: Seniority 6 - warrants | AY108: =IF(SUMIF($F$50:$O$50,"=6",$F$63:$O$63)<=AY107,SUMIF($F$50:$O$50,"=6",$F$63:$O$63),AY107) -> 0 | BA108: 6 | BJ108: Seniority 6 - warrants | BK108: =IF(SUMIF($F$50:$O$50,"=6",$F$63:$O$63)<=BK107,SUMIF($F$50:$O$50,"=6",$F$63:$O$63),BK107) -> 0 | BM108: 6 | BV108: Seniority 6 - warrants | BW108: =IF(SUMIF($F$50:$O$50,"=6",$F$63:$O$63)<=BW107,SUMIF($F$50:$O$50,"=6",$F$63:$O$63),BW107) -> 0 | BY108: 6 | CH108: Seniority 6 - warrants | CI108: =IF(SUMIF($F$50:$O$50,"=6",$F$63:$O$63)<=CI107,SUMIF($F$50:$O$50,"=6",$F$63:$O$63),CI107) -> 0 | CK108: 6 | CT108: Seniority 6 - warrants | CU108: =IF(SUMIF($F$50:$O$50,"=6",$F$63:$O$63)<=CU107,SUMIF($F$50:$O$50,"=6",$F$63:$O$63),CU107) -> 0 | CW108: 6 | DF108: Seniority 6 - warrants | DG108: =IF(SUMIF($F$50:$O$50,"=6",$F$63:$O$63)<=DG107,SUMIF($F$50:$O$50,"=6",$F$63:$O$63),DG107) -> 0 | DI108: 6
C109: =C107-C108 -> 0 | O109: =O107-O108 -> 0 | AA109: =AA107-AA108 -> 0 | AM109: =AM107-AM108 -> 0 | AY109: =AY107-AY108 -> 0 | BK109: =BK107-BK108 -> 0 | BW109: =BW107-BW108 -> 0 | CI109: =CI107-CI108 -> 0 | CU109: =CU107-CU108 -> 0 | DG109: =DG107-DG108 -> 0
B110: Seniority 7 | C110: =IF(SUMIF($F$50:$O$50,"=7",$F$62:$O$62)<=C109,SUMIF($F$50:$O$50,"=7",$F$62:$O$62),C109) -> 0 | D110: 7 | N110: Seniority 7 | O110: =IF(SUMIF($F$50:$O$50,"=7",$F$62:$O$62)<=O109,SUMIF($F$50:$O$50,"=7",$F$62:$O$62),O109) -> 0 | P110: 7 | Z110: Seniority 7 | AA110: =IF(SUMIF($F$50:$O$50,"=7",$F$62:$O$62)<=AA109,SUMIF($F$50:$O$50,"=7",$F$62:$O$62),AA109) -> 0 | AB110: 7 | AL110: Seniority 7 | AM110: =IF(SUMIF($F$50:$O$50,"=7",$F$62:$O$62)<=AM109,SUMIF($F$50:$O$50,"=7",$F$62:$O$62),AM109) -> 0 | AN110: 7 | AX110: Seniority 7 | AY110: =IF(SUMIF($F$50:$O$50,"=7",$F$62:$O$62)<=AY109,SUMIF($F$50:$O$50,"=7",$F$62:$O$62),AY109) -> 0 | AZ110: 7 | BJ110: Seniority 7 | BK110: =IF(SUMIF($F$50:$O$50,"=7",$F$62:$O$62)<=BK109,SUMIF($F$50:$O$50,"=7",$F$62:$O$62),BK109) -> 0 | BL110: 7 | BV110: Seniority 7 | BW110: =IF(SUMIF($F$50:$O$50,"=7",$F$62:$O$62)<=BW109,SUMIF($F$50:$O$50,"=7",$F$62:$O$62),BW109) -> 0 | BX110: 7 | CH110: Seniority 7 | CI110: =IF(SUMIF($F$50:$O$50,"=7",$F$62:$O$62)<=CI109,SUMIF($F$50:$O$50,"=7",$F$62:$O$62),CI109) -> 0 | CJ110: 7 | CT110: Seniority 7 | CU110: =IF(SUMIF($F$50:$O$50,"=7",$F$62:$O$62)<=CU109,SUMIF($F$50:$O$50,"=7",$F$62:$O$62),CU109) -> 0 | CV110: 7 | DF110: Seniority 7 | DG110: =IF(SUMIF($F$50:$O$50,"=7",$F$62:$O$62)<=DG109,SUMIF($F$50:$O$50,"=7",$F$62:$O$62),DG109) -> 0 | DH110: 7
C111: =C109-C110 -> 0 | O111: =O109-O110 -> 0 | AA111: =AA109-AA110 -> 0 | AM111: =AM109-AM110 -> 0 | AY111: =AY109-AY110 -> 0 | BK111: =BK109-BK110 -> 0 | BW111: =BW109-BW110 -> 0 | CI111: =CI109-CI110 -> 0 | CU111: =CU109-CU110 -> 0 | DG111: =DG109-DG110 -> 0
B112: Seniority 7 - warrants | C112: =IF(SUMIF($F$50:$O$50,"=7",$F$63:$O$63)<=C111,SUMIF($F$50:$O$50,"=7",$F$63:$O$63),C111) -> 0 | E112: 7 | N112: Seniority 7 - warrants | O112: =IF(SUMIF($F$50:$O$50,"=7",$F$63:$O$63)<=O111,SUMIF($F$50:$O$50,"=7",$F$63:$O$63),O111) -> 0 | Q112: 7 | Z112: Seniority 7 - warrants | AA112: =IF(SUMIF($F$50:$O$50,"=7",$F$63:$O$63)<=AA111,SUMIF($F$50:$O$50,"=7",$F$63:$O$63),AA111) -> 0 | AC112: 7 | AL112: Seniority 7 - warrants | AM112: =IF(SUMIF($F$50:$O$50,"=7",$F$63:$O$63)<=AM111,SUMIF($F$50:$O$50,"=7",$F$63:$O$63),AM111) -> 0 | AO112: 7 | AX112: Seniority 7 - warrants | AY112: =IF(SUMIF($F$50:$O$50,"=7",$F$63:$O$63)<=AY111,SUMIF($F$50:$O$50,"=7",$F$63:$O$63),AY111) -> 0 | BA112: 7 | BJ112: Seniority 7 - warrants | BK112: =IF(SUMIF($F$50:$O$50,"=7",$F$63:$O$63)<=BK111,SUMIF($F$50:$O$50,"=7",$F$63:$O$63),BK111) -> 0 | BM112: 7 | BV112: Seniority 7 - warrants | BW112: =IF(SUMIF($F$50:$O$50,"=7",$F$63:$O$63)<=BW111,SUMIF($F$50:$O$50,"=7",$F$63:$O$63),BW111) -> 0 | BY112: 7 | CH112: Seniority 7 - warrants | CI112: =IF(SUMIF($F$50:$O$50,"=7",$F$63:$O$63)<=CI111,SUMIF($F$50:$O$50,"=7",$F$63:$O$63),CI111) -> 0 | CK112: 7 | CT112: Seniority 7 - warrants | CU112: =IF(SUMIF($F$50:$O$50,"=7",$F$63:$O$63)<=CU111,SUMIF($F$50:$O$50,"=7",$F$63:$O$63),CU111) -> 0 | CW112: 7 | DF112: Seniority 7 - warrants | DG112: =IF(SUMIF($F$50:$O$50,"=7",$F$63:$O$63)<=DG111,SUMIF($F$50:$O$50,"=7",$F$63:$O$63),DG111) -> 0 | DI112: 7
C113: =C111-C112 -> 0 | O113: =O111-O112 -> 0 | AA113: =AA111-AA112 -> 0 | AM113: =AM111-AM112 -> 0 | AY113: =AY111-AY112 -> 0 | BK113: =BK111-BK112 -> 0 | BW113: =BW111-BW112 -> 0 | CI113: =CI111-CI112 -> 0 | CU113: =CU111-CU112 -> 0 | DG113: =DG111-DG112 -> 0
B114: Seniority 8 | C114: =IF(SUMIF($F$50:$O$50,"=8",$F$62:$O$62)<=C113,SUMIF($F$50:$O$50,"=8",$F$62:$O$62),C113) -> 0 | D114: 8 | N114: Seniority 8 | O114: =IF(SUMIF($F$50:$O$50,"=8",$F$62:$O$62)<=O113,SUMIF($F$50:$O$50,"=8",$F$62:$O$62),O113) -> 0 | P114: 8 | Z114: Seniority 8 | AA114: =IF(SUMIF($F$50:$O$50,"=8",$F$62:$O$62)<=AA113,SUMIF($F$50:$O$50,"=8",$F$62:$O$62),AA113) -> 0 | AB114: 8 | AL114: Seniority 8 | AM114: =IF(SUMIF($F$50:$O$50,"=8",$F$62:$O$62)<=AM113,SUMIF($F$50:$O$50,"=8",$F$62:$O$62),AM113) -> 0 | AN114: 8 | AX114: Seniority 8 | AY114: =IF(SUMIF($F$50:$O$50,"=8",$F$62:$O$62)<=AY113,SUMIF($F$50:$O$50,"=8",$F$62:$O$62),AY113) -> 0 | AZ114: 8 | BJ114: Seniority 8 | BK114: =IF(SUMIF($F$50:$O$50,"=8",$F$62:$O$62)<=BK113,SUMIF($F$50:$O$50,"=8",$F$62:$O$62),BK113) -> 0 | BL114: 8 | BV114: Seniority 8 | BW114: =IF(SUMIF($F$50:$O$50,"=8",$F$62:$O$62)<=BW113,SUMIF($F$50:$O$50,"=8",$F$62:$O$62),BW113) -> 0 | BX114: 8 | CH114: Seniority 8 | CI114: =IF(SUMIF($F$50:$O$50,"=8",$F$62:$O$62)<=CI113,SUMIF($F$50:$O$50,"=8",$F$62:$O$62),CI113) -> 0 | CJ114: 8 | CT114: Seniority 8 | CU114: =IF(SUMIF($F$50:$O$50,"=8",$F$62:$O$62)<=CU113,SUMIF($F$50:$O$50,"=8",$F$62:$O$62),CU113) -> 0 | CV114: 8 | DF114: Seniority 8 | DG114: =IF(SUMIF($F$50:$O$50,"=8",$F$62:$O$62)<=DG113,SUMIF($F$50:$O$50,"=8",$F$62:$O$62),DG113) -> 0 | DH114: 8
C115: =C113-C114 -> 0 | O115: =O113-O114 -> 0 | AA115: =AA113-AA114 -> 0 | AM115: =AM113-AM114 -> 0 | AY115: =AY113-AY114 -> 0 | BK115: =BK113-BK114 -> 0 | BW115: =BW113-BW114 -> 0 | CI115: =CI113-CI114 -> 0 | CU115: =CU113-CU114 -> 0 | DG115: =DG113-DG114 -> 0
B116: Seniority 8 - warrants | C116: =IF(SUMIF($F$50:$O$50,"=8",$F$63:$O$63)<=C115,SUMIF($F$50:$O$50,"=8",$F$63:$O$63),C115) -> 0 | E116: 8 | N116: Seniority 8 - warrants | O116: =IF(SUMIF($F$50:$O$50,"=8",$F$63:$O$63)<=O115,SUMIF($F$50:$O$50,"=8",$F$63:$O$63),O115) -> 0 | Q116: 8 | Z116: Seniority 8 - warrants | AA116: =IF(SUMIF($F$50:$O$50,"=8",$F$63:$O$63)<=AA115,SUMIF($F$50:$O$50,"=8",$F$63:$O$63),AA115) -> 0 | AC116: 8 | AL116: Seniority 8 - warrants | AM116: =IF(SUMIF($F$50:$O$50,"=8",$F$63:$O$63)<=AM115,SUMIF($F$50:$O$50,"=8",$F$63:$O$63),AM115) -> 0 | AO116: 8 | AX116: Seniority 8 - warrants | AY116: =IF(SUMIF($F$50:$O$50,"=8",$F$63:$O$63)<=AY115,SUMIF($F$50:$O$50,"=8",$F$63:$O$63),AY115) -> 0 | BA116: 8 | BJ116: Seniority 8 - warrants | BK116: =IF(SUMIF($F$50:$O$50,"=8",$F$63:$O$63)<=BK115,SUMIF($F$50:$O$50,"=8",$F$63:$O$63),BK115) -> 0 | BM116: 8 | BV116: Seniority 8 - warrants | BW116: =IF(SUMIF($F$50:$O$50,"=8",$F$63:$O$63)<=BW115,SUMIF($F$50:$O$50,"=8",$F$63:$O$63),BW115) -> 0 | BY116: 8 | CH116: Seniority 8 - warrants | CI116: =IF(SUMIF($F$50:$O$50,"=8",$F$63:$O$63)<=CI115,SUMIF($F$50:$O$50,"=8",$F$63:$O$63),CI115) -> 0 | CK116: 8 | CT116: Seniority 8 - warrants | CU116: =IF(SUMIF($F$50:$O$50,"=8",$F$63:$O$63)<=CU115,SUMIF($F$50:$O$50,"=8",$F$63:$O$63),CU115) -> 0 | CW116: 8 | DF116: Seniority 8 - warrants | DG116: =IF(SUMIF($F$50:$O$50,"=8",$F$63:$O$63)<=DG115,SUMIF($F$50:$O$50,"=8",$F$63:$O$63),DG115) -> 0 | DI116: 8
C117: =C115-C116 -> 0 | O117: =O115-O116 -> 0 | AA117: =AA115-AA116 -> 0 | AM117: =AM115-AM116 -> 0 | AY117: =AY115-AY116 -> 0 | BK117: =BK115-BK116 -> 0 | BW117: =BW115-BW116 -> 0 | CI117: =CI115-CI116 -> 0 | CU117: =CU115-CU116 -> 0 | DG117: =DG115-DG116 -> 0
B118: Seniority 9 | C118: =IF(SUMIF($F$50:$O$50,"=9",$F$62:$O$62)<=C117,SUMIF($F$50:$O$50,"=9",$F$62:$O$62),C117) -> 0 | D118: 9 | N118: Seniority 9 | O118: =IF(SUMIF($F$50:$O$50,"=9",$F$62:$O$62)<=O117,SUMIF($F$50:$O$50,"=9",$F$62:$O$62),O117) -> 0 | P118: 9 | Z118: Seniority 9 | AA118: =IF(SUMIF($F$50:$O$50,"=9",$F$62:$O$62)<=AA117,SUMIF($F$50:$O$50,"=9",$F$62:$O$62),AA117) -> 0 | AB118: 9 | AL118: Seniority 9 | AM118: =IF(SUMIF($F$50:$O$50,"=9",$F$62:$O$62)<=AM117,SUMIF($F$50:$O$50,"=9",$F$62:$O$62),AM117) -> 0 | AN118: 9 | AX118: Seniority 9 | AY118: =IF(SUMIF($F$50:$O$50,"=9",$F$62:$O$62)<=AY117,SUMIF($F$50:$O$50,"=9",$F$62:$O$62),AY117) -> 0 | AZ118: 9 | BJ118: Seniority 9 | BK118: =IF(SUMIF($F$50:$O$50,"=9",$F$62:$O$62)<=BK117,SUMIF($F$50:$O$50,"=9",$F$62:$O$62),BK117) -> 0 | BL118: 9 | BV118: Seniority 9 | BW118: =IF(SUMIF($F$50:$O$50,"=9",$F$62:$O$62)<=BW117,SUMIF($F$50:$O$50,"=9",$F$62:$O$62),BW117) -> 0 | BX118: 9 | CH118: Seniority 9 | CI118: =IF(SUMIF($F$50:$O$50,"=9",$F$62:$O$62)<=CI117,SUMIF($F$50:$O$50,"=9",$F$62:$O$62),CI117) -> 0 | CJ118: 9 | CT118: Seniority 9 | CU118: =IF(SUMIF($F$50:$O$50,"=9",$F$62:$O$62)<=CU117,SUMIF($F$50:$O$50,"=9",$F$62:$O$62),CU117) -> 0 | CV118: 9 | DF118: Seniority 9 | DG118: =IF(SUMIF($F$50:$O$50,"=9",$F$62:$O$62)<=DG117,SUMIF($F$50:$O$50,"=9",$F$62:$O$62),DG117) -> 0 | DH118: 9
C119: =C117-C118 -> 0 | O119: =O117-O118 -> 0 | AA119: =AA117-AA118 -> 0 | AM119: =AM117-AM118 -> 0 | AY119: =AY117-AY118 -> 0 | BK119: =BK117-BK118 -> 0 | BW119: =BW117-BW118 -> 0 | CI119: =CI117-CI118 -> 0 | CU119: =CU117-CU118 -> 0 | DG119: =DG117-DG118 -> 0
B120: Seniority 9 - warrants | C120: =IF(SUMIF($F$50:$O$50,"=9",$F$63:$O$63)<=C119,SUMIF($F$50:$O$50,"=9",$F$63:$O$63),C119) -> 0 | E120: 9 | N120: Seniority 9 - warrants | O120: =IF(SUMIF($F$50:$O$50,"=9",$F$63:$O$63)<=O119,SUMIF($F$50:$O$50,"=9",$F$63:$O$63),O119) -> 0 | Q120: 9 | Z120: Seniority 9 - warrants | AA120: =IF(SUMIF($F$50:$O$50,"=9",$F$63:$O$63)<=AA119,SUMIF($F$50:$O$50,"=9",$F$63:$O$63),AA119) -> 0 | AC120: 9 | AL120: Seniority 9 - warrants | AM120: =IF(SUMIF($F$50:$O$50,"=9",$F$63:$O$63)<=AM119,SUMIF($F$50:$O$50,"=9",$F$63:$O$63),AM119) -> 0 | AO120: 9 | AX120: Seniority 9 - warrants | AY120: =IF(SUMIF($F$50:$O$50,"=9",$F$63:$O$63)<=AY119,SUMIF($F$50:$O$50,"=9",$F$63:$O$63),AY119) -> 0 | BA120: 9 | BJ120: Seniority 9 - warrants | BK120: =IF(SUMIF($F$50:$O$50,"=9",$F$63:$O$63)<=BK119,SUMIF($F$50:$O$50,"=9",$F$63:$O$63),BK119) -> 0 | BM120: 9 | BV120: Seniority 9 - warrants | BW120: =IF(SUMIF($F$50:$O$50,"=9",$F$63:$O$63)<=BW119,SUMIF($F$50:$O$50,"=9",$F$63:$O$63),BW119) -> 0 | BY120: 9 | CH120: Seniority 9 - warrants | CI120: =IF(SUMIF($F$50:$O$50,"=9",$F$63:$O$63)<=CI119,SUMIF($F$50:$O$50,"=9",$F$63:$O$63),CI119) -> 0 | CK120: 9 | CT120: Seniority 9 - warrants | CU120: =IF(SUMIF($F$50:$O$50,"=9",$F$63:$O$63)<=CU119,SUMIF($F$50:$O$50,"=9",$F$63:$O$63),CU119) -> 0 | CW120: 9 | DF120: Seniority 9 - warrants | DG120: =IF(SUMIF($F$50:$O$50,"=9",$F$63:$O$63)<=DG119,SUMIF($F$50:$O$50,"=9",$F$63:$O$63),DG119) -> 0 | DI120: 9
C121: =C119-C120 -> 0 | O121: =O119-O120 -> 0 | AA121: =AA119-AA120 -> 0 | AM121: =AM119-AM120 -> 0 | AY121: =AY119-AY120 -> 0 | BK121: =BK119-BK120 -> 0 | BW121: =BW119-BW120 -> 0 | CI121: =CI119-CI120 -> 0 | CU121: =CU119-CU120 -> 0 | DG121: =DG119-DG120 -> 0
B122: Seniority 10 | C122: =IF(SUMIF($F$50:$O$50,"=10",$F$62:$O$62)<=C121,SUMIF($F$50:$O$50,"=10",$F$62:$O$62),C121) -> 0 | D122: 10 | N122: Seniority 10 | O122: =IF(SUMIF($F$50:$O$50,"=10",$F$62:$O$62)<=O121,SUMIF($F$50:$O$50,"=10",$F$62:$O$62),O121) -> 0 | P122: 10 | Z122: Seniority 10 | AA122: =IF(SUMIF($F$50:$O$50,"=10",$F$62:$O$62)<=AA121,SUMIF($F$50:$O$50,"=10",$F$62:$O$62),AA121) -> 0 | AB122: 10 | AL122: Seniority 10 | AM122: =IF(SUMIF($F$50:$O$50,"=10",$F$62:$O$62)<=AM121,SUMIF($F$50:$O$50,"=10",$F$62:$O$62),AM121) -> 0 | AN122: 10 | AX122: Seniority 10 | AY122: =IF(SUMIF($F$50:$O$50,"=10",$F$62:$O$62)<=AY121,SUMIF($F$50:$O$50,"=10",$F$62:$O$62),AY121) -> 0 | AZ122: 10 | BJ122: Seniority 10 | BK122: =IF(SUMIF($F$50:$O$50,"=10",$F$62:$O$62)<=BK121,SUMIF($F$50:$O$50,"=10",$F$62:$O$62),BK121) -> 0 | BL122: 10 | BV122: Seniority 10 | BW122: =IF(SUMIF($F$50:$O$50,"=10",$F$62:$O$62)<=BW121,SUMIF($F$50:$O$50,"=10",$F$62:$O$62),BW121) -> 0 | BX122: 10 | CH122: Seniority 10 | CI122: =IF(SUMIF($F$50:$O$50,"=10",$F$62:$O$62)<=CI121,SUMIF($F$50:$O$50,"=10",$F$62:$O$62),CI121) -> 0 | CJ122: 10 | CT122: Seniority 10 | CU122: =IF(SUMIF($F$50:$O$50,"=10",$F$62:$O$62)<=CU121,SUMIF($F$50:$O$50,"=10",$F$62:$O$62),CU121) -> 0 | CV122: 10 | DF122: Seniority 10 | DG122: =IF(SUMIF($F$50:$O$50,"=10",$F$62:$O$62)<=DG121,SUMIF($F$50:$O$50,"=10",$F$62:$O$62),DG121) -> 0 | DH122: 10
C123: =C121-C122 -> 0 | O123: =O121-O122 -> 0 | AA123: =AA121-AA122 -> 0 | AM123: =AM121-AM122 -> 0 | AY123: =AY121-AY122 -> 0 | BK123: =BK121-BK122 -> 0 | BW123: =BW121-BW122 -> 0 | CI123: =CI121-CI122 -> 0 | CU123: =CU121-CU122 -> 0 | DG123: =DG121-DG122 -> 0
B124: Seniority 10 - warrants | C124: =IF(SUMIF($F$50:$O$50,"=10",$F$63:$O$63)<=C123,SUMIF($F$50:$O$50,"=10",$F$63:$O$63),C123) -> 0 | E124: 10 | N124: Seniority 10 - warrants | O124: =IF(SUMIF($F$50:$O$50,"=10",$F$63:$O$63)<=O123,SUMIF($F$50:$O$50,"=10",$F$63:$O$63),O123) -> 0 | Q124: 10 | Z124: Seniority 10 - warrants | AA124: =IF(SUMIF($F$50:$O$50,"=10",$F$63:$O$63)<=AA123,SUMIF($F$50:$O$50,"=10",$F$63:$O$63),AA123) -> 0 | AC124: 10 | AL124: Seniority 10 - warrants | AM124: =IF(SUMIF($F$50:$O$50,"=10",$F$63:$O$63)<=AM123,SUMIF($F$50:$O$50,"=10",$F$63:$O$63),AM123) -> 0 | AO124: 10 | AX124: Seniority 10 - warrants | AY124: =IF(SUMIF($F$50:$O$50,"=10",$F$63:$O$63)<=AY123,SUMIF($F$50:$O$50,"=10",$F$63:$O$63),AY123) -> 0 | BA124: 10 | BJ124: Seniority 10 - warrants | BK124: =IF(SUMIF($F$50:$O$50,"=10",$F$63:$O$63)<=BK123,SUMIF($F$50:$O$50,"=10",$F$63:$O$63),BK123) -> 0 | BM124: 10 | BV124: Seniority 10 - warrants | BW124: =IF(SUMIF($F$50:$O$50,"=10",$F$63:$O$63)<=BW123,SUMIF($F$50:$O$50,"=10",$F$63:$O$63),BW123) -> 0 | BY124: 10 | CH124: Seniority 10 - warrants | CI124: =IF(SUMIF($F$50:$O$50,"=10",$F$63:$O$63)<=CI123,SUMIF($F$50:$O$50,"=10",$F$63:$O$63),CI123) -> 0 | CK124: 10 | CT124: Seniority 10 - warrants | CU124: =IF(SUMIF($F$50:$O$50,"=10",$F$63:$O$63)<=CU123,SUMIF($F$50:$O$50,"=10",$F$63:$O$63),CU123) -> 0 | CW124: 10 | DF124: Seniority 10 - warrants | DG124: =IF(SUMIF($F$50:$O$50,"=10",$F$63:$O$63)<=DG123,SUMIF($F$50:$O$50,"=10",$F$63:$O$63),DG123) -> 0 | DI124: 10
B125: Remaining proceed for part. shareholder | C125: =C123-C124 -> 0 | N125: Remaining proceed for part. shareholder | O125: =O123-O124 -> 0 | Z125: Remaining proceed for part. shareholder | AA125: =AA123-AA124 -> 0 | AL125: Remaining proceed for part. shareholder | AM125: =AM123-AM124 -> 0 | AX125: Remaining proceed for part. shareholder | AY125: =AY123-AY124 -> 0 | BJ125: Remaining proceed for part. shareholder | BK125: =BK123-BK124 -> 0 | BV125: Remaining proceed for part. shareholder | BW125: =BW123-BW124 -> 0 | CH125: Remaining proceed for part. shareholder | CI125: =CI123-CI124 -> 0 | CT125: Remaining proceed for part. shareholder | CU125: =CU123-CU124 -> 0 | DF125: Remaining proceed for part. shareholder | DG125: =DG123-DG124 -> 0
B128: Equity | N128: Equity | Z128: Equity | AL128: Equity | AX128: Equity | BJ128: Equity | BV128: Equity | CH128: Equity | CT128: Equity | DF128: Equity
B129: =F$6 -> Series A | C129: =IF(AND(C125<>0,F152=0),0,IF(SUMIF($F$50:$O$50,$F$50,$F$62:$O$62)=0,0,SUMIF(D86:D124,$F$50,C86:C124)*$F$62/(SUMIF($F$50:$O$50,$F$50,$F$62:$O$62)))) -> 0 | N129: =B129 -> Series A | O129: =IF(AND(O125<>0,R152=0),0,IF(SUMIF($F$50:$O$50,$F$50,$F$62:$O$62)=0,0,SUMIF(P86:P124,$F$50,O86:O124)*$F$62/(SUMIF($F$50:$O$50,$F$50,$F$62:$O$62)))) -> 0 | Z129: =N129 -> Series A | AA129: =IF(AND(AA125<>0,AD152=0),0,IF(SUMIF($F$50:$O$50,$F$50,$F$62:$O$62)=0,0,SUMIF(AB86:AB124,$F$50,AA86:AA124)*$F$62/(SUMIF($F$50:$O$50,$F$50,$F$62:$O$62)))) -> 0 | AL129: =Z129 -> Series A | AM129: =IF(AND(AM125<>0,AP152=0),0,IF(SUMIF($F$50:$O$50,$F$50,$F$62:$O$62)=0,0,SUMIF(AN86:AN124,$F$50,AM86:AM124)*$F$62/(SUMIF($F$50:$O$50,$F$50,$F$62:$O$62)))) -> 0 | AX129: =AL129 -> Series A | AY129: =IF(AND(AY125<>0,BB152=0),0,IF(SUMIF($F$50:$O$50,$F$50,$F$62:$O$62)=0,0,SUMIF(AZ86:AZ124,$F$50,AY86:AY124)*$F$62/(SUMIF($F$50:$O$50,$F$50,$F$62:$O$62)))) -> 0 | BJ129: =AX129 -> Series A | BK129: =IF(AND(BK125<>0,BN152=0),0,IF(SUMIF($F$50:$O$50,$F$50,$F$62:$O$62)=0,0,SUMIF(BL86:BL124,$F$50,BK86:BK124)*$F$62/(SUMIF($F$50:$O$50,$F$50,$F$62:$O$62)))) -> 0 | BV129: =BJ129 -> Series A | BW129: =IF(AND(BW125<>0,BZ152=0),0,IF(SUMIF($F$50:$O$50,$F$50,$F$62:$O$62)=0,0,SUMIF(BX86:BX124,$F$50,BW86:BW124)*$F$62/(SUMIF($F$50:$O$50,$F$50,$F$62:$O$62)))) -> 0 | CH129: =BV129 -> Series A | CI129: =IF(AND(CI125<>0,CL152=0),0,IF(SUMIF($F$50:$O$50,$F$50,$F$62:$O$62)=0,0,SUMIF(CJ86:CJ124,$F$50,CI86:CI124)*$F$62/(SUMIF($F$50:$O$50,$F$50,$F$62:$O$62)))) -> 0 | CT129: =CH129 -> Series A | CU129: =IF(AND(CU125<>0,CX152=0),0,IF(SUMIF($F$50:$O$50,$F$50,$F$62:$O$62)=0,0,SUMIF(CV86:CV124,$F$50,CU86:CU124)*$F$62/(SUMIF($F$50:$O$50,$F$50,$F$62:$O$62)))) -> 0 | DF129: =CT129 -> Series A | DG129: =IF(AND(DG125<>0,DJ152=0),0,IF(SUMIF($F$50:$O$50,$F$50,$F$62:$O$62)=0,0,SUMIF(DH86:DH124,$F$50,DG86:DG124)*$F$62/(SUMIF($F$50:$O$50,$F$50,$F$62:$O$62)))) -> 0
B130: =G$6 -> Series B | C130: =IF(AND(C125<>0,F153=0),0,IF(SUMIF($F$50:$O$50,$G$50,$F$62:$O$62)=0,0,SUMIF(D86:D124,$G$50,C86:C124)*$G$62/(SUMIF($F$50:$O$50,$G$50,$F$62:$O$62)))) -> 0 | N130: =B130 -> Series B | O130: =IF(AND(O125<>0,R153=0),0,IF(SUMIF($F$50:$O$50,$G$50,$F$62:$O$62)=0,0,SUMIF(P86:P124,$G$50,O86:O124)*$G$62/(SUMIF($F$50:$O$50,$G$50,$F$62:$O$62)))) -> 0 | Z130: =N130 -> Series B | AA130: =IF(AND(AA125<>0,AD153=0),0,IF(SUMIF($F$50:$O$50,$G$50,$F$62:$O$62)=0,0,SUMIF(AB86:AB124,$G$50,AA86:AA124)*$G$62/(SUMIF($F$50:$O$50,$G$50,$F$62:$O$62)))) -> 0 | AL130: =Z130 -> Series B | AM130: =IF(AND(AM125<>0,AP153=0),0,IF(SUMIF($F$50:$O$50,$G$50,$F$62:$O$62)=0,0,SUMIF(AN86:AN124,$G$50,AM86:AM124)*$G$62/(SUMIF($F$50:$O$50,$G$50,$F$62:$O$62)))) -> 0 | AX130: =AL130 -> Series B | AY130: =IF(AND(AY125<>0,BB153=0),0,IF(SUMIF($F$50:$O$50,$G$50,$F$62:$O$62)=0,0,SUMIF(AZ86:AZ124,$G$50,AY86:AY124)*$G$62/(SUMIF($F$50:$O$50,$G$50,$F$62:$O$62)))) -> 0 | BJ130: =AX130 -> Series B | BK130: =IF(AND(BK125<>0,BN153=0),0,IF(SUMIF($F$50:$O$50,$G$50,$F$62:$O$62)=0,0,SUMIF(BL86:BL124,$G$50,BK86:BK124)*$G$62/(SUMIF($F$50:$O$50,$G$50,$F$62:$O$62)))) -> 0 | BV130: =BJ130 -> Series B | BW130: =IF(AND(BW125<>0,BZ153=0),0,IF(SUMIF($F$50:$O$50,$G$50,$F$62:$O$62)=0,0,SUMIF(BX86:BX124,$G$50,BW86:BW124)*$G$62/(SUMIF($F$50:$O$50,$G$50,$F$62:$O$62)))) -> 0 | CH130: =BV130 -> Series B | CI130: =IF(AND(CI125<>0,CL153=0),0,IF(SUMIF($F$50:$O$50,$G$50,$F$62:$O$62)=0,0,SUMIF(CJ86:CJ124,$G$50,CI86:CI124)*$G$62/(SUMIF($F$50:$O$50,$G$50,$F$62:$O$62)))) -> 0 | CT130: =CH130 -> Series B | CU130: =IF(AND(CU125<>0,CX153=0),0,IF(SUMIF($F$50:$O$50,$G$50,$F$62:$O$62)=0,0,SUMIF(CV86:CV124,$G$50,CU86:CU124)*$G$62/(SUMIF($F$50:$O$50,$G$50,$F$62:$O$62)))) -> 0 | DF130: =CT130 -> Series B | DG130: =IF(AND(DG125<>0,DJ153=0),0,IF(SUMIF($F$50:$O$50,$G$50,$F$62:$O$62)=0,0,SUMIF(DH86:DH124,$G$50,DG86:DG124)*$G$62/(SUMIF($F$50:$O$50,$G$50,$F$62:$O$62)))) -> 0
B131: =H$6 -> Series C | C131: =IF(AND(C125<>0,F154=0),0,IF(SUMIF($F$50:$O$50,$H$50,$F$62:$O$62)=0,0,SUMIF(D86:D124,$H$50,C86:C124)*$H$62/(SUMIF($F$50:$O$50,$H$50,$F$62:$O$62)))) -> 0 | N131: =B131 -> Series C | O131: =IF(AND(O125<>0,R154=0),0,IF(SUMIF($F$50:$O$50,$H$50,$F$62:$O$62)=0,0,SUMIF(P86:P124,$H$50,O86:O124)*$H$62/(SUMIF($F$50:$O$50,$H$50,$F$62:$O$62)))) -> 0 | Z131: =N131 -> Series C | AA131: =IF(AND(AA125<>0,AD154=0),0,IF(SUMIF($F$50:$O$50,$H$50,$F$62:$O$62)=0,0,SUMIF(AB86:AB124,$H$50,AA86:AA124)*$H$62/(SUMIF($F$50:$O$50,$H$50,$F$62:$O$62)))) -> 0 | AL131: =Z131 -> Series C | AM131: =IF(AND(AM125<>0,AP154=0),0,IF(SUMIF($F$50:$O$50,$H$50,$F$62:$O$62)=0,0,SUMIF(AN86:AN124,$H$50,AM86:AM124)*$H$62/(SUMIF($F$50:$O$50,$H$50,$F$62:$O$62)))) -> 0 | AX131: =AL131 -> Series C | AY131: =IF(AND(AY125<>0,BB154=0),0,IF(SUMIF($F$50:$O$50,$H$50,$F$62:$O$62)=0,0,SUMIF(AZ86:AZ124,$H$50,AY86:AY124)*$H$62/(SUMIF($F$50:$O$50,$H$50,$F$62:$O$62)))) -> 0 | BJ131: =AX131 -> Series C | BK131: =IF(AND(BK125<>0,BN154=0),0,IF(SUMIF($F$50:$O$50,$H$50,$F$62:$O$62)=0,0,SUMIF(BL86:BL124,$H$50,BK86:BK124)*$H$62/(SUMIF($F$50:$O$50,$H$50,$F$62:$O$62)))) -> 0 | BV131: =BJ131 -> Series C | BW131: =IF(AND(BW125<>0,BZ154=0),0,IF(SUMIF($F$50:$O$50,$H$50,$F$62:$O$62)=0,0,SUMIF(BX86:BX124,$H$50,BW86:BW124)*$H$62/(SUMIF($F$50:$O$50,$H$50,$F$62:$O$62)))) -> 0 | CH131: =BV131 -> Series C | CI131: =IF(AND(CI125<>0,CL154=0),0,IF(SUMIF($F$50:$O$50,$H$50,$F$62:$O$62)=0,0,SUMIF(CJ86:CJ124,$H$50,CI86:CI124)*$H$62/(SUMIF($F$50:$O$50,$H$50,$F$62:$O$62)))) -> 0 | CT131: =CH131 -> Series C | CU131: =IF(AND(CU125<>0,CX154=0),0,IF(SUMIF($F$50:$O$50,$H$50,$F$62:$O$62)=0,0,SUMIF(CV86:CV124,$H$50,CU86:CU124)*$H$62/(SUMIF($F$50:$O$50,$H$50,$F$62:$O$62)))) -> 0 | DF131: =CT131 -> Series C | DG131: =IF(AND(DG125<>0,DJ154=0),0,IF(SUMIF($F$50:$O$50,$H$50,$F$62:$O$62)=0,0,SUMIF(DH86:DH124,$H$50,DG86:DG124)*$H$62/(SUMIF($F$50:$O$50,$H$50,$F$62:$O$62)))) -> 0
B132: =I$6 -> Series D | C132: =IF(AND(C125<>0,F155=0),0,IF(SUMIF($F$50:$O$50,$I$50,$F$62:$O$62)=0,0,SUMIF(D86:D124,$I$50,C86:C124)*$I$62/(SUMIF($F$50:$O$50,$I$50,$F$62:$O$62)))) -> 0 | N132: =B132 -> Series D | O132: =IF(AND(O125<>0,R155=0),0,IF(SUMIF($F$50:$O$50,$I$50,$F$62:$O$62)=0,0,SUMIF(P86:P124,$I$50,O86:O124)*$I$62/(SUMIF($F$50:$O$50,$I$50,$F$62:$O$62)))) -> 0 | Z132: =N132 -> Series D | AA132: =IF(AND(AA125<>0,AD155=0),0,IF(SUMIF($F$50:$O$50,$I$50,$F$62:$O$62)=0,0,SUMIF(AB86:AB124,$I$50,AA86:AA124)*$I$62/(SUMIF($F$50:$O$50,$I$50,$F$62:$O$62)))) -> 0 | AL132: =Z132 -> Series D | AM132: =IF(AND(AM125<>0,AP155=0),0,IF(SUMIF($F$50:$O$50,$I$50,$F$62:$O$62)=0,0,SUMIF(AN86:AN124,$I$50,AM86:AM124)*$I$62/(SUMIF($F$50:$O$50,$I$50,$F$62:$O$62)))) -> 0 | AX132: =AL132 -> Series D | AY132: =IF(AND(AY125<>0,BB155=0),0,IF(SUMIF($F$50:$O$50,$I$50,$F$62:$O$62)=0,0,SUMIF(AZ86:AZ124,$I$50,AY86:AY124)*$I$62/(SUMIF($F$50:$O$50,$I$50,$F$62:$O$62)))) -> 0 | BJ132: =AX132 -> Series D | BK132: =IF(AND(BK125<>0,BN155=0),0,IF(SUMIF($F$50:$O$50,$I$50,$F$62:$O$62)=0,0,SUMIF(BL86:BL124,$I$50,BK86:BK124)*$I$62/(SUMIF($F$50:$O$50,$I$50,$F$62:$O$62)))) -> 0 | BV132: =BJ132 -> Series D | BW132: =IF(AND(BW125<>0,BZ155=0),0,IF(SUMIF($F$50:$O$50,$I$50,$F$62:$O$62)=0,0,SUMIF(BX86:BX124,$I$50,BW86:BW124)*$I$62/(SUMIF($F$50:$O$50,$I$50,$F$62:$O$62)))) -> 0 | CH132: =BV132 -> Series D | CI132: =IF(AND(CI125<>0,CL155=0),0,IF(SUMIF($F$50:$O$50,$I$50,$F$62:$O$62)=0,0,SUMIF(CJ86:CJ124,$I$50,CI86:CI124)*$I$62/(SUMIF($F$50:$O$50,$I$50,$F$62:$O$62)))) -> 0 | CT132: =CH132 -> Series D | CU132: =IF(AND(CU125<>0,CX155=0),0,IF(SUMIF($F$50:$O$50,$I$50,$F$62:$O$62)=0,0,SUMIF(CV86:CV124,$I$50,CU86:CU124)*$I$62/(SUMIF($F$50:$O$50,$I$50,$F$62:$O$62)))) -> 0 | DF132: =CT132 -> Series D | DG132: =IF(AND(DG125<>0,DJ155=0),0,IF(SUMIF($F$50:$O$50,$I$50,$F$62:$O$62)=0,0,SUMIF(DH86:DH124,$I$50,DG86:DG124)*$I$62/(SUMIF($F$50:$O$50,$I$50,$F$62:$O$62)))) -> 0
B133: =J$6 -> - | C133: =IF(AND(F156=0,C125<>0),0,IF(SUMIF($F$50:$O$50,$J$50,$F$62:$O$62)=0,0,SUMIF(D86:D124,$J$50,C86:C124)*$J$62/(SUMIF($F$50:$O$50,$J$50,$F$62:$O$62)))) -> 0 | N133: =B133 -> - | O133: =IF(AND(R156=0,O125<>0),0,IF(SUMIF($F$50:$O$50,$J$50,$F$62:$O$62)=0,0,SUMIF(P86:P124,$J$50,O86:O124)*$J$62/(SUMIF($F$50:$O$50,$J$50,$F$62:$O$62)))) -> 0 | Z133: =N133 -> - | AA133: =IF(AND(AD156=0,AA125<>0),0,IF(SUMIF($F$50:$O$50,$J$50,$F$62:$O$62)=0,0,SUMIF(AB86:AB124,$J$50,AA86:AA124)*$J$62/(SUMIF($F$50:$O$50,$J$50,$F$62:$O$62)))) -> 0 | AL133: =Z133 -> - | AM133: =IF(AND(AP156=0,AM125<>0),0,IF(SUMIF($F$50:$O$50,$J$50,$F$62:$O$62)=0,0,SUMIF(AN86:AN124,$J$50,AM86:AM124)*$J$62/(SUMIF($F$50:$O$50,$J$50,$F$62:$O$62)))) -> 0 | AX133: =AL133 -> - | AY133: =IF(AND(BB156=0,AY125<>0),0,IF(SUMIF($F$50:$O$50,$J$50,$F$62:$O$62)=0,0,SUMIF(AZ86:AZ124,$J$50,AY86:AY124)*$J$62/(SUMIF($F$50:$O$50,$J$50,$F$62:$O$62)))) -> 0 | BJ133: =AX133 -> - | BK133: =IF(AND(BN156=0,BK125<>0),0,IF(SUMIF($F$50:$O$50,$J$50,$F$62:$O$62)=0,0,SUMIF(BL86:BL124,$J$50,BK86:BK124)*$J$62/(SUMIF($F$50:$O$50,$J$50,$F$62:$O$62)))) -> 0 | BV133: =BJ133 -> - | BW133: =IF(AND(BZ156=0,BW125<>0),0,IF(SUMIF($F$50:$O$50,$J$50,$F$62:$O$62)=0,0,SUMIF(BX86:BX124,$J$50,BW86:BW124)*$J$62/(SUMIF($F$50:$O$50,$J$50,$F$62:$O$62)))) -> 0 | CH133: =BV133 -> - | CI133: =IF(AND(CL156=0,CI125<>0),0,IF(SUMIF($F$50:$O$50,$J$50,$F$62:$O$62)=0,0,SUMIF(CJ86:CJ124,$J$50,CI86:CI124)*$J$62/(SUMIF($F$50:$O$50,$J$50,$F$62:$O$62)))) -> 0 | CT133: =CH133 -> - | CU133: =IF(AND(CX156=0,CU125<>0),0,IF(SUMIF($F$50:$O$50,$J$50,$F$62:$O$62)=0,0,SUMIF(CV86:CV124,$J$50,CU86:CU124)*$J$62/(SUMIF($F$50:$O$50,$J$50,$F$62:$O$62)))) -> 0 | DF133: =CT133 -> - | DG133: =IF(AND(DJ156=0,DG125<>0),0,IF(SUMIF($F$50:$O$50,$J$50,$F$62:$O$62)=0,0,SUMIF(DH86:DH124,$J$50,DG86:DG124)*$J$62/(SUMIF($F$50:$O$50,$J$50,$F$62:$O$62)))) -> 0
B134: =K$6 -> - | C134: =IF(AND(C125<>0,F157=0),0,IF(SUMIF($F$50:$O$50,$K$50,$F$62:$O$62)=0,0,SUMIF(D86:D124,$K$50,C86:C124)*$K$62/(SUMIF($F$50:$O$50,$K$50,$F$62:$O$62)))) -> 0 | N134: =B134 -> - | O134: =IF(AND(O125<>0,R157=0),0,IF(SUMIF($F$50:$O$50,$K$50,$F$62:$O$62)=0,0,SUMIF(P86:P124,$K$50,O86:O124)*$K$62/(SUMIF($F$50:$O$50,$K$50,$F$62:$O$62)))) -> 0 | Z134: =N134 -> - | AA134: =IF(AND(AA125<>0,AD157=0),0,IF(SUMIF($F$50:$O$50,$K$50,$F$62:$O$62)=0,0,SUMIF(AB86:AB124,$K$50,AA86:AA124)*$K$62/(SUMIF($F$50:$O$50,$K$50,$F$62:$O$62)))) -> 0 | AL134: =Z134 -> - | AM134: =IF(AND(AM125<>0,AP157=0),0,IF(SUMIF($F$50:$O$50,$K$50,$F$62:$O$62)=0,0,SUMIF(AN86:AN124,$K$50,AM86:AM124)*$K$62/(SUMIF($F$50:$O$50,$K$50,$F$62:$O$62)))) -> 0 | AX134: =AL134 -> - | AY134: =IF(AND(AY125<>0,BB157=0),0,IF(SUMIF($F$50:$O$50,$K$50,$F$62:$O$62)=0,0,SUMIF(AZ86:AZ124,$K$50,AY86:AY124)*$K$62/(SUMIF($F$50:$O$50,$K$50,$F$62:$O$62)))) -> 0 | BJ134: =AX134 -> - | BK134: =IF(AND(BK125<>0,BN157=0),0,IF(SUMIF($F$50:$O$50,$K$50,$F$62:$O$62)=0,0,SUMIF(BL86:BL124,$K$50,BK86:BK124)*$K$62/(SUMIF($F$50:$O$50,$K$50,$F$62:$O$62)))) -> 0 | BV134: =BJ134 -> - | BW134: =IF(AND(BW125<>0,BZ157=0),0,IF(SUMIF($F$50:$O$50,$K$50,$F$62:$O$62)=0,0,SUMIF(BX86:BX124,$K$50,BW86:BW124)*$K$62/(SUMIF($F$50:$O$50,$K$50,$F$62:$O$62)))) -> 0 | CH134: =BV134 -> - | CI134: =IF(AND(CI125<>0,CL157=0),0,IF(SUMIF($F$50:$O$50,$K$50,$F$62:$O$62)=0,0,SUMIF(CJ86:CJ124,$K$50,CI86:CI124)*$K$62/(SUMIF($F$50:$O$50,$K$50,$F$62:$O$62)))) -> 0 | CT134: =CH134 -> - | CU134: =IF(AND(CU125<>0,CX157=0),0,IF(SUMIF($F$50:$O$50,$K$50,$F$62:$O$62)=0,0,SUMIF(CV86:CV124,$K$50,CU86:CU124)*$K$62/(SUMIF($F$50:$O$50,$K$50,$F$62:$O$62)))) -> 0 | DF134: =CT134 -> - | DG134: =IF(AND(DG125<>0,DJ157=0),0,IF(SUMIF($F$50:$O$50,$K$50,$F$62:$O$62)=0,0,SUMIF(DH86:DH124,$K$50,DG86:DG124)*$K$62/(SUMIF($F$50:$O$50,$K$50,$F$62:$O$62)))) -> 0
...

Sheet Summary
B1: =Inputs!I6 -> Company Name
B2: Pro Forma Capitalization Table
B3: =Inputs!I7 -> 39813
F5: {=IF(TRANSPOSE(Inputs!E$10:E$19)=0,"",TRANSPOSE(Inputs!E$10:E$19))} -> 39113 | G5: 39478 | H5: 39843 | I5: 39843 | J5: 39843 | K5: 39843 | L5: 39843 | M5: 39843 | N5: 39843 | O5: 39843
C6: Common | D6: Stock | E6: Total | F6: {=IF(TRANSPOSE(Inputs!D$10:D$19)=0,"",TRANSPOSE(Inputs!D$10:D$19))} -> Series A | G6: Series B | H6: Series C | I6: Series D | J6: - | K6: - | L6: - | M6: - | N6: - | O6: - | P6: Total | Q6: Total # | R6: Ful. Dil. as Conv. | W6: Total | X6: Total # | Y6: Total
B7: Investor (Partner) | C7: =Inputs!K22 -> 1e-08 | D7: =Inputs!K23 -> 1e-07 | E7: Common | F7: {=IF(TRANSPOSE(Inputs!K$10:K$19)=0,0,TRANSPOSE(Inputs!K$10:K$19))} -> 1 | G7: 2 | H7: 2.5 | I7: 2 | J7: 0 | K7: 0 | L7: 0 | M7: 0 | N7: 0 | O7: 0 | P7: Dollars ($) | Q7: Of All | R7: Ownership | W7: Preferred | X7: Of All | Y7: Ownership
C8: Shares | D8: Options | E8: & Options | F8: =IF(F7=0,"","Preferred") -> Preferred | G8: =IF(G7=0,"","Preferred") -> Preferred | H8: =IF(H7=0,"","Preferred") -> Preferred | I8: =IF(I7=0,"","Preferred") -> Preferred | J8: =IF(J7=0,"","Preferred") | K8: =IF(K7=0,"","Preferred") | L8: =IF(L7=0,"","Preferred") | M8: =IF(M7=0,"","Preferred") | ... O8: =IF(O7=0,"","Preferred") | P8: Invested | Q8: Shares Held | R8: Percent (%) | W8: Shares | X8: Shares Held | Y8: Percent (%)
B9: =IF(Inputs!E31=0,Inputs!D31,CONCATENATE(Inputs!D31," (",Inputs!E31,")")) -> HTGC | C9: ='Pro Forma Cap Table'!C29 -> 0 | D9: ='Pro Forma Cap Table'!D29 -> 0 | E9: =SUM(C9:D9) -> 0 | F9: ='Pro Forma Cap Table'!F29 -> 1000000 | G9: ='Pro Forma Cap Table'!G29 -> 2000000 | H9: ='Pro Forma Cap Table'!H29 -> 0 | I9: ='Pro Forma Cap Table'!I29 -> 0 | J9: ='Pro Forma Cap Table'!J29 -> 0 | K9: ='Pro Forma Cap Table'!K29 -> 0 | L9: ='Pro Forma Cap Table'!L29 -> 0 | M9: ='Pro Forma Cap Table'!M29 -> 0 | ... O9: ='Pro Forma Cap Table'!O29 -> 0 | P9: ='Pro Forma Cap Table'!T10 -> 3000000 | Q9: ='Pro Forma Cap Table'!Q10 -> 2000000 | R9: ='Pro Forma Cap Table'!S10 -> 0.064020487 | W9: =SUM(AN9:AW9) -> 2000000 | X9: =W9+AM9 -> 2000000 | Y9: =X9/X$27 -> 0.064020487 | AJ9: =IF(Inputs!E31=0,Inputs!D31,CONCATENATE(Inputs!D31," (",Inputs!E31,")")) -> HTGC | AK9: 0 | AL9: 0 | AM9: =SUM(AK9:AL9) -> 0 | AN9: =IF(F$7="",0,Inputs!F31) -> 1000000 | AO9: =IF(G$7="",0,Inputs!G31) -> 1000000 | AP9: =IF(H$7="",0,Inputs!H31) -> 0 | AQ9: =IF(I$7="",0,Inputs!I31) -> 0 | AR9: =IF(J$7="",0,Inputs!J31) -> 0 | AS9: =IF(K$7="",0,Inputs!K31) -> 0 | AT9: =IF(L$7="",0,Inputs!L31) -> 0 | AU9: =IF(M$7="",0,Inputs!M31) -> 0 | ... AW9: =IF(O$7="",0,Inputs!O31) -> 0 | AX9: =$F$7*AN9+$G$7*AO9+$H$7*AP9+$I$7*AQ9+$J$7*AR9+$K$7*AS9+$L$7*AT9+$M$7*AU9+$N$7*AV9+$O$7*AW9 -> 3000000 | AY9: =(AN9*$AA$61+AO9*$AB$61+AP9*$AC$61+AQ9*$AD$61+AR9*$AE$61+AS9*$AF$61+AT9*$AG$61+AU9*$AH$61+AV9*$AI$61+AW9*$AJ$61+AM9)/($R$31+$X$21) -> 0.064020487
B10: =IF(Inputs!E32=0,Inputs!D32,CONCATENATE(Inputs!D32," (",Inputs!E32,")")) -> Inv B | C10: ='Pro Forma Cap Table'!C30 -> 0 | D10: ='Pro Forma Cap Table'!D30 -> 0 | E10: =SUM(C10:D10) -> 0 | F10: ='Pro Forma Cap Table'!F30 -> 1000000 | G10: ='Pro Forma Cap Table'!G30 -> 2000000 | H10: ='Pro Forma Cap Table'!H30 -> 0 | I10: ='Pro Forma Cap Table'!I30 -> 0 | J10: ='Pro Forma Cap Table'!J30 -> 0 | K10: ='Pro Forma Cap Table'!K30 -> 0 | L10: ='Pro Forma Cap Table'!L30 -> 0 | M10: ='Pro Forma Cap Table'!M30 -> 0 | ... O10: ='Pro Forma Cap Table'!O30 -> 0 | P10: ='Pro Forma Cap Table'!T11 -> 3000000 | Q10: ='Pro Forma Cap Table'!Q11 -> 2000000 | R10: ='Pro Forma Cap Table'!S11 -> 0.064020487 | W10: =SUM(AN10:AW10) -> 2000000 | X10: =W10+AM10 -> 2000000 | Y10: =X10/X$27 -> 0.064020487 | AJ10: =IF(Inputs!E32=0,Inputs!D32,CONCATENATE(Inputs!D32," (",Inputs!E32,")")) -> Inv B | AK10: 0 | AL10: 0 | AM10: =SUM(AK10:AL10) -> 0 | AN10: =IF(F$7="",0,Inputs!F32) -> 1000000 | AO10: =IF(G$7="",0,Inputs!G32) -> 1000000 | AP10: =IF(H$7="",0,Inputs!H32) -> 0 | AQ10: =IF(I$7="",0,Inputs!I32) -> 0 | AR10: =IF(J$7="",0,Inputs!J32) -> 0 | AS10: =IF(K$7="",0,Inputs!K32) -> 0 | AT10: =IF(L$7="",0,Inputs!L32) -> 0 | AU10: =IF(M$7="",0,Inputs!M32) -> 0 | ... AW10: =IF(O$7="",0,Inputs!O32) -> 0 | AX10: =$F$7*AN10+$G$7*AO10+$H$7*AP10+$I$7*AQ10+$J$7*AR10+$K$7*AS10+$L$7*AT10+$M$7*AU10+$N$7*AV10+$O$7*AW10 -> 3000000 | AY10: =(AN10*$AA$61+AO10*$AB$61+AP10*$AC$61+AQ10*$AD$61+AR10*$AE$61+AS10*$AF$61+AT10*$AG$61+AU10*$AH$61+AV10*$AI$61+AW10*$AJ$61+AM10)/($R$31+$X$21) -> 0.064020487
B11: =IF(Inputs!E33=0,Inputs!D33,CONCATENATE(Inputs!D33," (",Inputs!E33,")")) -> Inv C | C11: ='Pro Forma Cap Table'!C31 -> 0 | D11: ='Pro Forma Cap Table'!D31 -> 0 | E11: =SUM(C11:D11) -> 0 | F11: ='Pro Forma Cap Table'!F31 -> 1000000 | G11: ='Pro Forma Cap Table'!G31 -> 2000000 | H11: ='Pro Forma Cap Table'!H31 -> 2500000 | I11: ='Pro Forma Cap Table'!I31 -> 0 | J11: ='Pro Forma Cap Table'!J31 -> 0 | K11: ='Pro Forma Cap Table'!K31 -> 0 | L11: ='Pro Forma Cap Table'!L31 -> 0 | M11: ='Pro Forma Cap Table'!M31 -> 0 | ... O11: ='Pro Forma Cap Table'!O31 -> 0 | P11: ='Pro Forma Cap Table'!T12 -> 5500000 | Q11: ='Pro Forma Cap Table'!Q12 -> 3000000 | R11: ='Pro Forma Cap Table'!S12 -> 0.09603073 | W11: =SUM(AN11:AW11) -> 3000000 | X11: =W11+AM11 -> 3000000 | Y11: =X11/X$27 -> 0.09603073 | AJ11: =IF(Inputs!E33=0,Inputs!D33,CONCATENATE(Inputs!D33," (",Inputs!E33,")")) -> Inv C | AK11: 0 | AL11: 0 | AM11: =SUM(AK11:AL11) -> 0 | AN11: =IF(F$7="",0,Inputs!F33) -> 1000000 | AO11: =IF(G$7="",0,Inputs!G33) -> 1000000 | AP11: =IF(H$7="",0,Inputs!H33) -> 1000000 | AQ11: =IF(I$7="",0,Inputs!I33) -> 0 | AR11: =IF(J$7="",0,Inputs!J33) -> 0 | AS11: =IF(K$7="",0,Inputs!K33) -> 0 | AT11: =IF(L$7="",0,Inputs!L33) -> 0 | AU11: =IF(M$7="",0,Inputs!M33) -> 0 | ... AW11: =IF(O$7="",0,Inputs!O33) -> 0 | AX11: =$F$7*AN11+$G$7*AO11+$H$7*AP11+$I$7*AQ11+$J$7*AR11+$K$7*AS11+$L$7*AT11+$M$7*AU11+$N$7*AV11+$O$7*AW11 -> 5500000 | AY11: =(AN11*$AA$61+AO11*$AB$61+AP11*$AC$61+AQ11*$AD$61+AR11*$AE$61+AS11*$AF$61+AT11*$AG$61+AU11*$AH$61+AV11*$AI$61+AW11*$AJ$61+AM11)/($R$31+$X$21) -> 0.09603073
B12: =IF(Inputs!E34=0,Inputs!D34,CONCATENATE(Inputs!D34," (",Inputs!E34,")")) -> Inv D | C12: ='Pro Forma Cap Table'!C32 -> 0 | D12: ='Pro Forma Cap Table'!D32 -> 0 | E12: =SUM(C12:D12) -> 0 | F12: ='Pro Forma Cap Table'!F32 -> 1000000 | G12: ='Pro Forma Cap Table'!G32 -> 2000000 | H12: ='Pro Forma Cap Table'!H32 -> 2500000 | I12: ='Pro Forma Cap Table'!I32 -> 0 | J12: ='Pro Forma Cap Table'!J32 -> 0 | K12: ='Pro Forma Cap Table'!K32 -> 0 | L12: ='Pro Forma Cap Table'!L32 -> 0 | M12: ='Pro Forma Cap Table'!M32 -> 0 | ... O12: ='Pro Forma Cap Table'!O32 -> 0 | P12: ='Pro Forma Cap Table'!T13 -> 5500000 | Q12: ='Pro Forma Cap Table'!Q13 -> 3000000 | R12: ='Pro Forma Cap Table'!S13 -> 0.09603073 | W12: =SUM(AN12:AW12) -> 3000000 | X12: =W12+AM12 -> 3000000 | Y12: =X12/X$27 -> 0.09603073 | AJ12: =IF(Inputs!E34=0,Inputs!D34,CONCATENATE(Inputs!D34," (",Inputs!E34,")")) -> Inv D | AK12: 0 | AL12: 0 | AM12: =SUM(AK12:AL12) -> 0 | AN12: =IF(F$7="",0,Inputs!F34) -> 1000000 | AO12: =IF(G$7="",0,Inputs!G34) -> 1000000 | AP12: =IF(H$7="",0,Inputs!H34) -> 1000000 | AQ12: =IF(I$7="",0,Inputs!I34) -> 0 | AR12: =IF(J$7="",0,Inputs!J34) -> 0 | AS12: =IF(K$7="",0,Inputs!K34) -> 0 | AT12: =IF(L$7="",0,Inputs!L34) -> 0 | AU12: =IF(M$7="",0,Inputs!M34) -> 0 | ... AW12: =IF(O$7="",0,Inputs!O34) -> 0 | AX12: =$F$7*AN12+$G$7*AO12+$H$7*AP12+$I$7*AQ12+$J$7*AR12+$K$7*AS12+$L$7*AT12+$M$7*AU12+$N$7*AV12+$O$7*AW12 -> 5500000 | AY12: =(AN12*$AA$61+AO12*$AB$61+AP12*$AC$61+AQ12*$AD$61+AR12*$AE$61+AS12*$AF$61+AT12*$AG$61+AU12*$AH$61+AV12*$AI$61+AW12*$AJ$61+AM12)/($R$31+$X$21) -> 0.09603073
B13: =IF(Inputs!E35=0,Inputs!D35,CONCATENATE(Inputs!D35," (",Inputs!E35,")")) -> Inv E | C13: ='Pro Forma Cap Table'!C33 -> 0 | D13: ='Pro Forma Cap Table'!D33 -> 0 | E13: =SUM(C13:D13) -> 0 | F13: ='Pro Forma Cap Table'!F33 -> 1000000 | G13: ='Pro Forma Cap Table'!G33 -> 2000000 | H13: ='Pro Forma Cap Table'!H33 -> 2500000 | I13: ='Pro Forma Cap Table'!I33 -> 0 | J13: ='Pro Forma Cap Table'!J33 -> 0 | K13: ='Pro Forma Cap Table'!K33 -> 0 | L13: ='Pro Forma Cap Table'!L33 -> 0 | M13: ='Pro Forma Cap Table'!M33 -> 0 | ... O13: ='Pro Forma Cap Table'!O33 -> 0 | P13: ='Pro Forma Cap Table'!T14 -> 5500000 | Q13: ='Pro Forma Cap Table'!Q14 -> 3000000 | R13: ='Pro Forma Cap Table'!S14 -> 0.09603073 | W13: =SUM(AN13:AW13) -> 3000000 | X13: =W13+AM13 -> 3000000 | Y13: =X13/X$27 -> 0.09603073 | AJ13: =IF(Inputs!E35=0,Inputs!D35,CONCATENATE(Inputs!D35," (",Inputs!E35,")")) -> Inv E | AK13: 0 | AL13: 0 | AM13: =SUM(AK13:AL13) -> 0 | AN13: =IF(F$7="",0,Inputs!F35) -> 1000000 | AO13: =IF(G$7="",0,Inputs!G35) -> 1000000 | AP13: =IF(H$7="",0,Inputs!H35) -> 1000000 | AQ13: =IF(I$7="",0,Inputs!I35) -> 0 | AR13: =IF(J$7="",0,Inputs!J35) -> 0 | AS13: =IF(K$7="",0,Inputs!K35) -> 0 | AT13: =IF(L$7="",0,Inputs!L35) -> 0 | AU13: =IF(M$7="",0,Inputs!M35) -> 0 | ... AW13: =IF(O$7="",0,Inputs!O35) -> 0 | AX13: =$F$7*AN13+$G$7*AO13+$H$7*AP13+$I$7*AQ13+$J$7*AR13+$K$7*AS13+$L$7*AT13+$M$7*AU13+$N$7*AV13+$O$7*AW13 -> 5500000 | AY13: =(AN13*$AA$61+AO13*$AB$61+AP13*$AC$61+AQ13*$AD$61+AR13*$AE$61+AS13*$AF$61+AT13*$AG$61+AU13*$AH$61+AV13*$AI$61+AW13*$AJ$61+AM13)/($R$31+$X$21) -> 0.09603073
B14: =IF(Inputs!E36=0,Inputs!D36,CONCATENATE(Inputs!D36," (",Inputs!E36,")")) -> Inv F | C14: ='Pro Forma Cap Table'!C34 -> 0 | D14: ='Pro Forma Cap Table'!D34 -> 0 | E14: =SUM(C14:D14) -> 0 | F14: ='Pro Forma Cap Table'!F34 -> 0 | G14: ='Pro Forma Cap Table'!G34 -> 0 | H14: ='Pro Forma Cap Table'!H34 -> 2500000 | I14: ='Pro Forma Cap Table'!I34 -> 6666666.7 | J14: ='Pro Forma Cap Table'!J34 -> 0 | K14: ='Pro Forma Cap Table'!K34 -> 0 | L14: ='Pro Forma Cap Table'!L34 -> 0 | M14: ='Pro Forma Cap Table'!M34 -> 0 | ... O14: ='Pro Forma Cap Table'!O34 -> 0 | P14: ='Pro Forma Cap Table'!T15 -> 9166666.7 | Q14: ='Pro Forma Cap Table'!Q15 -> 4333333.3 | R14: ='Pro Forma Cap Table'!S15 -> 0.13871105 | W14: =SUM(AN14:AW14) -> 4333333.3 | X14: =W14+AM14 -> 4333333.3 | Y14: =X14/X$27 -> 0.13871105 | AJ14: =IF(Inputs!E36=0,Inputs!D36,CONCATENATE(Inputs!D36," (",Inputs!E36,")")) -> Inv F | AK14: 0 | AL14: 0 | AM14: =SUM(AK14:AL14) -> 0 | AN14: =IF(F$7="",0,Inputs!F36) -> 0 | AO14: =IF(G$7="",0,Inputs!G36) -> 0 | AP14: =IF(H$7="",0,Inputs!H36) -> 1000000 | AQ14: =IF(I$7="",0,Inputs!I36) -> 3333333.3 | AR14: =IF(J$7="",0,Inputs!J36) -> 0 | AS14: =IF(K$7="",0,Inputs!K36) -> 0 | AT14: =IF(L$7="",0,Inputs!L36) -> 0 | AU14: =IF(M$7="",0,Inputs!M36) -> 0 | ... AW14: =IF(O$7="",0,Inputs!O36) -> 0 | AX14: =$F$7*AN14+$G$7*AO14+$H$7*AP14+$I$7*AQ14+$J$7*AR14+$K$7*AS14+$L$7*AT14+$M$7*AU14+$N$7*AV14+$O$7*AW14 -> 9166666.7 | AY14: =(AN14*$AA$61+AO14*$AB$61+AP14*$AC$61+AQ14*$AD$61+AR14*$AE$61+AS14*$AF$61+AT14*$AG$61+AU14*$AH$61+AV14*$AI$61+AW14*$AJ$61+AM14)/($R$31+$X$21) -> 0.13871105
B15: =IF(Inputs!E37=0,Inputs!D37,CONCATENATE(Inputs!D37," (",Inputs!E37,")")) -> Inv G | C15: ='Pro Forma Cap Table'!C35 -> 0 | D15: ='Pro Forma Cap Table'!D35 -> 0 | E15: =SUM(C15:D15) -> 0 | F15: ='Pro Forma Cap Table'!F35 -> 0 | G15: ='Pro Forma Cap Table'!G35 -> 0 | H15: ='Pro Forma Cap Table'!H35 -> 2500000 | I15: ='Pro Forma Cap Table'!I35 -> 6666666.7 | J15: ='Pro Forma Cap Table'!J35 -> 0 | K15: ='Pro Forma Cap Table'!K35 -> 0 | L15: ='Pro Forma Cap Table'!L35 -> 0 | M15: ='Pro Forma Cap Table'!M35 -> 0 | ... O15: ='Pro Forma Cap Table'!O35 -> 0 | P15: ='Pro Forma Cap Table'!T16 -> 9166666.7 | Q15: ='Pro Forma Cap Table'!Q16 -> 4333333.3 | R15: ='Pro Forma Cap Table'!S16 -> 0.13871105 | W15: =SUM(AN15:AW15) -> 4333333.3 | X15: =W15+AM15 -> 4333333.3 | Y15: =X15/X$27 -> 0.13871105 | AJ15: =IF(Inputs!E37=0,Inputs!D37,CONCATENATE(Inputs!D37," (",Inputs!E37,")")) -> Inv G | AK15: 0 | AL15: 0 | AM15: =SUM(AK15:AL15) -> 0 | AN15: =IF(F$7="",0,Inputs!F37) -> 0 | AO15: =IF(G$7="",0,Inputs!G37) -> 0 | AP15: =IF(H$7="",0,Inputs!H37) -> 1000000 | AQ15: =IF(I$7="",0,Inputs!I37) -> 3333333.3 | AR15: =IF(J$7="",0,Inputs!J37) -> 0 | AS15: =IF(K$7="",0,Inputs!K37) -> 0 | AT15: =IF(L$7="",0,Inputs!L37) -> 0 | AU15: =IF(M$7="",0,Inputs!M37) -> 0 | ... AW15: =IF(O$7="",0,Inputs!O37) -> 0 | AX15: =$F$7*AN15+$G$7*AO15+$H$7*AP15+$I$7*AQ15+$J$7*AR15+$K$7*AS15+$L$7*AT15+$M$7*AU15+$N$7*AV15+$O$7*AW15 -> 9166666.7 | AY15: =(AN15*$AA$61+AO15*$AB$61+AP15*$AC$61+AQ15*$AD$61+AR15*$AE$61+AS15*$AF$61+AT15*$AG$61+AU15*$AH$61+AV15*$AI$61+AW15*$AJ$61+AM15)/($R$31+$X$21) -> 0.13871105
B16: =IF(Inputs!E38=0,Inputs!D38,CONCATENATE(Inputs!D38," (",Inputs!E38,")")) -> Inv H | C16: ='Pro Forma Cap Table'!C36 -> 0 | D16: ='Pro Forma Cap Table'!D36 -> 0 | E16: =SUM(C16:D16) -> 0 | F16: ='Pro Forma Cap Table'!F36 -> 0 | G16: ='Pro Forma Cap Table'!G36 -> 0 | H16: ='Pro Forma Cap Table'!H36 -> 2500000 | I16: ='Pro Forma Cap Table'!I36 -> 6666666.7 | J16: ='Pro Forma Cap Table'!J36 -> 0 | K16: ='Pro Forma Cap Table'!K36 -> 0 | L16: ='Pro Forma Cap Table'!L36 -> 0 | M16: ='Pro Forma Cap Table'!M36 -> 0 | ... O16: ='Pro Forma Cap Table'!O36 -> 0 | P16: ='Pro Forma Cap Table'!T17 -> 9166666.7 | Q16: ='Pro Forma Cap Table'!Q17 -> 4333333.3 | R16: ='Pro Forma Cap Table'!S17 -> 0.13871105 | W16: =SUM(AN16:AW16) -> 4333333.3 | X16: =W16+AM16 -> 4333333.3 | Y16: =X16/X$27 -> 0.13871105 | AJ16: =IF(Inputs!E38=0,Inputs!D38,CONCATENATE(Inputs!D38," (",Inputs!E38,")")) -> Inv H | AK16: 0 | AL16: 0 | AM16: =SUM(AK16:AL16) -> 0 | AN16: =IF(F$7="",0,Inputs!F38) -> 0 | AO16: =IF(G$7="",0,Inputs!G38) -> 0 | AP16: =IF(H$7="",0,Inputs!H38) -> 1000000 | AQ16: =IF(I$7="",0,Inputs!I38) -> 3333333.3 | AR16: =IF(J$7="",0,Inputs!J38) -> 0 | AS16: =IF(K$7="",0,Inputs!K38) -> 0 | AT16: =IF(L$7="",0,Inputs!L38) -> 0 | AU16: =IF(M$7="",0,Inputs!M38) -> 0 | ... AW16: =IF(O$7="",0,Inputs!O38) -> 0 | AX16: =$F$7*AN16+$G$7*AO16+$H$7*AP16+$I$7*AQ16+$J$7*AR16+$K$7*AS16+$L$7*AT16+$M$7*AU16+$N$7*AV16+$O$7*AW16 -> 9166666.7 | AY16: =(AN16*$AA$61+AO16*$AB$61+AP16*$AC$61+AQ16*$AD$61+AR16*$AE$61+AS16*$AF$61+AT16*$AG$61+AU16*$AH$61+AV16*$AI$61+AW16*$AJ$61+AM16)/($R$31+$X$21) -> 0.13871105
B17: =Inputs!D39 -> Other Investors | C17: ='Pro Forma Cap Table'!C37 -> 0 | D17: ='Pro Forma Cap Table'!D37 -> 0 | E17: =SUM(C17:D17) -> 0 | F17: ='Pro Forma Cap Table'!F37 -> 0 | G17: ='Pro Forma Cap Table'!G37 -> 0 | H17: ='Pro Forma Cap Table'!H37 -> 0 | I17: ='Pro Forma Cap Table'!I37 -> 0 | J17: ='Pro Forma Cap Table'!J37 -> 0 | K17: ='Pro Forma Cap Table'!K37 -> 0 | L17: ='Pro Forma Cap Table'!L37 -> 0 | M17: ='Pro Forma Cap Table'!M37 -> 0 | ... O17: ='Pro Forma Cap Table'!O37 -> 0 | P17: ='Pro Forma Cap Table'!T18 -> 0 | Q17: ='Pro Forma Cap Table'!Q18 -> 0 | R17: ='Pro Forma Cap Table'!S18 -> 0 | W17: =SUM(AN17:AW17) -> 0 | X17: =W17+AM17 -> 0 | Y17: =X17/X$27 -> 0 | AJ17: =Inputs!D39 -> Other Investors | AK17: 0 | AL17: 0 | AM17: =SUM(AK17:AL17) -> 0 | AN17: =IF(F$7="",0,Inputs!F39) -> 0 | AO17: =IF(G$7="",0,Inputs!G39) -> 0 | AP17: =IF(H$7="",0,Inputs!H39) -> 0 | AQ17: =IF(I$7="",0,Inputs!I39) -> 0 | AR17: =IF(J$7="",0,Inputs!J39) -> 0 | AS17: =IF(K$7="",0,Inputs!K39) -> 0 | AT17: =IF(L$7="",0,Inputs!L39) -> 0 | AU17: =IF(M$7="",0,Inputs!M39) -> 0 | ... AW17: =IF(O$7="",0,Inputs!O39) -> 0 | AX17: =$F$7*AN17+$G$7*AO17+$H$7*AP17+$I$7*AQ17+$J$7*AR17+$K$7*AS17+$L$7*AT17+$M$7*AU17+$N$7*AV17+$O$7*AW17 -> 0 | AY17: =(AN17*$AA$61+AO17*$AB$61+AP17*$AC$61+AQ17*$AD$61+AR17*$AE$61+AS17*$AF$61+AT17*$AG$61+AU17*$AH$61+AV17*$AI$61+AW17*$AJ$61+AM17)/($R$31+$X$21) -> 0
B18: Warrants By Series | C18: ='Pro Forma Cap Table'!C38 -> 0 | D18: ='Pro Forma Cap Table'!D38 -> 0 | E18: =SUM(C18:D18) -> 0 | F18: ='Pro Forma Cap Table'!F38 -> 10000 | G18: ='Pro Forma Cap Table'!G38 -> 10000 | H18: ='Pro Forma Cap Table'!H38 -> 10000 | I18: ='Pro Forma Cap Table'!I38 -> 10000 | J18: ='Pro Forma Cap Table'!J38 -> 0 | K18: ='Pro Forma Cap Table'!K38 -> 0 | L18: ='Pro Forma Cap Table'!L38 -> 0 | M18: ='Pro Forma Cap Table'!M38 -> 0 | ... O18: ='Pro Forma Cap Table'!O38 -> 0 | P18: ='Pro Forma Cap Table'!T19 -> 40000 | Q18: ='Pro Forma Cap Table'!Q19 -> 40000 | R18: ='Pro Forma Cap Table'!S19 -> 0.0012804097 | W18: =SUM(AN18:AW18) -> 40000 | X18: =W18+AM18 -> 40000 | Y18: =X18/X$27 -> 0.0012804097 | AJ18: Warrants By Series | AN18: {=IF(TRANSPOSE(Inputs!N$10:N$19)=0,0,TRANSPOSE(Inputs!N$10:N$19))} -> 10000 | AO18: 10000 | AP18: 10000 | AQ18: 10000 | AR18: 0 | AS18: 0 | AT18: 0 | AU18: 0 | AV18: 0 | AW18: 0 | AY18: =(AN18*$AA$61+AO18*$AB$61+AP18*$AC$61+AQ18*$AD$61+AR18*$AE$61+AS18*$AF$61+AT18*$AG$61+AU18*$AH$61+AV18*$AI$61+AW18*$AJ$61+AM18)/($R$31+$X$21) -> 0.0012804097
B19: Subtotal Investors | C19: =SUM(C9:C17) -> 0 | D19: =SUM(D9:D17) -> 0 | E19: =SUM(E9:E17) -> 0 | F19: =SUM(F9:F18) -> 5010000 | G19: =SUM(G9:G18) -> 10010000 | H19: =SUM(H9:H18) -> 15010000 | I19: =SUM(I9:I18) -> 20010000 | J19: =SUM(J9:J18) -> 0 | K19: =SUM(K9:K18) -> 0 | L19: =SUM(L9:L18) -> 0 | M19: =SUM(M9:M18) -> 0 | ... P19: =SUM(P9:P18) -> 50040000 | Q19: ='Pro Forma Cap Table'!Q20 -> 26040000 | R19: =SUM(R9:R18) -> 0.83354673 | W19: =SUM(W9:W18) -> 26040000 | X19: =SUM(X9:X18) -> 26040000 | Y19: =SUM(Y9:Y18) -> 0.83354673 | AJ19: Subtotal Investors | AK19: =SUM(AK9:AK17) -> 0 | AL19: =SUM(AL9:AL17) -> 0 | AM19: =SUM(AM9:AM17) -> 0 | AN19: =SUM(AN9:AN18) -> 5010000 | AO19: =SUM(AO9:AO18) -> 5010000 | AP19: =SUM(AP9:AP18) -> 6010000 | AQ19: =SUM(AQ9:AQ18) -> 10010000 | AR19: =SUM(AR9:AR18) -> 0 | AS19: =SUM(AS9:AS18) -> 0 | AT19: =SUM(AT9:AT18) -> 0 | AU19: =SUM(AU9:AU18) -> 0 | ... AY19: =SUM(AY9:AY18) -> 0.83354673
B20: Subtotal Managers | C20: =IF(C$7=0,0,Inputs!M22*C7) -> 0.052 | D20: =IF(D$7=0,0,Inputs!M23*D7) -> 0 | E20: =SUM(C20:D20) -> 0.052 | F20: ='Pro Forma Cap Table'!F43 -> 0 | G20: ='Pro Forma Cap Table'!G43 -> 0 | H20: ='Pro Forma Cap Table'!H43 -> 0 | I20: ='Pro Forma Cap Table'!I43 -> 0 | J20: ='Pro Forma Cap Table'!J43 -> 0 | K20: ='Pro Forma Cap Table'!K43 -> 0 | L20: ='Pro Forma Cap Table'!L43 -> 0 | M20: ='Pro Forma Cap Table'!M43 -> 0 | ... O20: ='Pro Forma Cap Table'!O43 -> 0 | P20: ='Pro Forma Cap Table'!T22 -> 0 | Q20: ='Pro Forma Cap Table'!Q22 -> 5200000 | R20: ='Pro Forma Cap Table'!S24 -> 0.16645327
W21: =SUM(AN21:AW21) -> 0 | X21: =W21+AM21 -> 5200000 | Y21: =X21/X$27 -> 0.16645327 | AJ21: =Inputs!D40 -> Management | AK21: =IF(C$7=0,0,Inputs!M22) -> 5200000 | AL21: =IF(D$7=0,0,Inputs!M23) -> 0 | AM21: =SUM(AK21:AL21) -> 5200000 | AN21: =IF(F$7=0,0,Inputs!F40/F$7) -> 0 | AO21: =IF(G$7=0,0,Inputs!G40/G$7) -> 0 | AP21: =IF(H$7=0,0,Inputs!H40/H$7) -> 0 | AQ21: =IF(I$7=0,0,Inputs!I40/I$7) -> 0 | AR21: =IF(J$7=0,0,Inputs!J40/J$7) -> 0 | AS21: =IF(K$7=0,0,Inputs!K40/K$7) -> 0 | AT21: =IF(L$7=0,0,Inputs!L40/L$7) -> 0 | AU21: =IF(M$7=0,0,Inputs!M40/M$7) -> 0 | ... AW21: =IF(O$7=0,0,Inputs!O40/O$7) -> 0 | AX21: =$F$7*AN21+$G$7*AO21+$H$7*AP21+$I$7*AQ21+$J$7*AR21+$K$7*AS21+$L$7*AT21+$M$7*AU21+$N$7*AV21+$O$7*AW21 -> 0 | AY21: =X21/($R$31+$X$21) -> 0.16645327
B22: Total | C22: =C19+C20 -> 0.052 | D22: =D19+D20 -> 0 | E22: =E19+E20 -> 0.052 | F22: =IF(F$7=0,0,'Pro Forma Cap Table'!F45) -> 5000000 | G22: =IF(G$7=0,0,'Pro Forma Cap Table'!G45) -> 10000000 | H22: =IF(H$7=0,0,'Pro Forma Cap Table'!H45) -> 15000000 | I22: =IF(I$7=0,0,'Pro Forma Cap Table'!I45) -> 20000000 | J22: =IF(J$7=0,0,'Pro Forma Cap Table'!J45) -> 0 | K22: =IF(K$7=0,0,'Pro Forma Cap Table'!K45) -> 0 | L22: =IF(L$7=0,0,'Pro Forma Cap Table'!L45) -> 0 | M22: =IF(M$7=0,0,'Pro Forma Cap Table'!M45) -> 0 | ... O22: =IF(O$7=0,0,'Pro Forma Cap Table'!O45) -> 0 | P22: ='Pro Forma Cap Table'!T45 -> 50040000 | Q22: =Q19+Q20 -> 31240000 | R22: =R19+R20 -> 1
W24: =SUM(W21:W23) -> 0 | X24: =SUM(X21:X23) -> 5200000 | Y24: =SUM(Y21:Y23) -> 0.16645327 | AJ24: Subtotal Managers | AK24: =SUM(AK21:AK23) -> 5200000 | AL24: =SUM(AL21:AL23) -> 0 | AM24: =SUM(AM21:AM23) -> 5200000 | AN24: =SUM(AN21:AN23) -> 0 | AO24: =SUM(AO21:AO23) -> 0 | AP24: =SUM(AP21:AP23) -> 0 | AQ24: =SUM(AQ21:AQ23) -> 0 | AR24: =SUM(AR21:AR23) -> 0 | ... AY24: =SUM(AY21:AY23) -> 0.16645327
W27: =W19+W24 -> 26040000 | X27: =X19+X24 -> 31240000 | Y27: =Y19+Y24 -> 1 | AJ27: Total Shares | AK27: =AK19+AK24 -> 5200000 | AL27: =AL19+AL24 -> 0 | AM27: =AM19+AM24 -> 5200000 | AN27: =AN19+AN24 -> 5010000 | AO27: =AO19+AO24 -> 5010000 | AP27: =AP19+AP24 -> 6010000 | AQ27: =AQ19+AQ24 -> 10010000 | AR27: =AR19+AR24 -> 0 | ... AW27: =AW19+AW24 -> 0 | AY27: =AY19+AY24 -> 1
W28: =SUM(AN28:AW28) -> 50000000 | AJ28: Total Dollars | AK28: =AK27*C7 -> 0.052 | AL28: =AL27*D7 -> 0 | AM28: =SUM(AK28:AL28) -> 0.052 | AN28: =(AN27-AN18)*F7 -> 5000000 | AO28: =(AO27-AO18)*G7 -> 10000000 | AP28: =(AP27-AP18)*H7 -> 15000000 | AQ28: =(AQ27-AQ18)*I7 -> 20000000 | AR28: =(AR27-AR18)*J7 -> 0 | AS28: =(AS27-AS18)*K7 -> 0 | AT28: =(AT27-AT18)*L7 -> 0 | AU28: =(AU27-AU18)*M7 -> 0 | ... AW28: =(AW27-AW18)*O7 -> 0 | AX28: =W28+AM28 -> 50000000
R31: =SUM(AA62:AJ62) -> 26040000 | W31: =SUM(F9:O9) -> 3000000 | X31: ='Pro Forma Cap Table'!Q10 -> 2000000 | Y31: =X31/X$47 -> 0.076804915
E32: Total Liquidation Preference | H32: ='Pro Forma Cap Table'!T46 -> 50000000 | W32: =SUM(F10:O10) -> 3000000 | X32: ='Pro Forma Cap Table'!Q11 -> 2000000 | Y32: =X32/X$47 -> 0.076804915
E33: ='Pro Forma Cap Table'!Q47 -> Series D | F33: ful. dil. post-money valuation of | H33: ='Pro Forma Cap Table'!T47 -> 62480000 | W33: =SUM(F11:O11) -> 5500000 | X33: ='Pro Forma Cap Table'!Q12 -> 3000000 | Y33: =X33/X$47 -> 0.11520737
E34: Based on | F34: ='Pro Forma Cap Table'!R48 -> 2 | G34: per share price. | W34: =SUM(F12:O12) -> 5500000 | X34: ='Pro Forma Cap Table'!Q13 -> 3000000 | Y34: =X34/X$47 -> 0.11520737
E35: Footnotes | W35: =SUM(F13:O13) -> 5500000 | X35: ='Pro Forma Cap Table'!Q14 -> 3000000 | Y35: =X35/X$47 -> 0.11520737
E36: =IF(Inputs!E45="Text Here","HIDE ROW", CONCATENATE(Inputs!D45, Inputs!E45)) -> * | W36: =SUM(F14:O14) -> 9166666.7 | X36: ='Pro Forma Cap Table'!Q15 -> 4333333.3 | Y36: =X36/X$47 -> 0.16641065
E37: =IF(Inputs!E46="Text Here","HIDE ROW", CONCATENATE(Inputs!D46, Inputs!E46)) -> ** | W37: =SUM(F15:O15) -> 9166666.7 | X37: ='Pro Forma Cap Table'!Q16 -> 4333333.3 | Y37: =X37/X$47 -> 0.16641065
E38: =IF(Inputs!E47="Text Here","HIDE ROW", CONCATENATE(Inputs!D47," ",Inputs!E47)) -> *** | W38: =SUM(F16:O16) -> 9166666.7 | X38: ='Pro Forma Cap Table'!Q17 -> 4333333.3 | Y38: =X38/X$47 -> 0.16641065
E39: =IF(Inputs!E48="Text Here","HIDE ROW", CONCATENATE(Inputs!D48," ",Inputs!E48)) -> **** | W39: =SUM(F17:O17) -> 0 | X39: ='Pro Forma Cap Table'!Q18 -> 0 | Y39: =X39/X$47 -> 0
W40: =SUM(F18:O18) -> 40000 | X40: ='Pro Forma Cap Table'!Q19 -> 40000 | Y40: =X40/X$47 -> 0.0015360983
W41: =SUM(W31:W40) -> 50040000 | X41: =SUM(X31:X40) -> 26040000 | Y41: =SUM(Y31:Y40) -> 1
W43: =SUM(F20:O20) -> 0 | X43: =W43+E20 -> 0.052 | Y43: =X43/X$27 -> 1.6645327e-09
W45: =SUM(W43:W44) -> 0 | X45: =SUM(X43:X44) -> 0.052 | Y45: =SUM(Y43:Y44) -> 1.6645327e-09
W47: =W27 -> 26040000 | X47: =X41+X45 -> 26040000 | Y47: =Y41+Y45 -> 1
W55: Total Dollars | X55: =C22*C7 -> 5.2e-10 | Y55: =D22*D7 -> 0 | Z55: =SUM(X55:Y55) -> 5.2e-10 | AA55: =IF(F7=0,"n/a",F$22*F$7) -> 5000000 | AB55: =IF(G7=0,"n/a",G$22*G$7) -> 20000000 | AC55: =IF(H7=0,"n/a",H$22*H$7) -> 37500000 | AD55: =IF(I7=0,"n/a",I$22*I$7) -> 40000000 | AE55: =IF(J7=0,"n/a",J$22*J$7) -> n/a | AF55: =IF(K7=0,"n/a",K$22*K$7) -> n/a | AG55: =IF(L7=0,"n/a",L$22*L$7) -> n/a | AH55: =IF(M7=0,"n/a",M$22*M$7) -> n/a | ... AJ55: =IF(O7=0,"n/a",O$22*O$7) -> n/a | AK55: =P19+#REF! -> #REF!
Y56: Post-Money | AA56: {=IF(TRANSPOSE(Inputs!F$10:F$19)=0,"N/A",TRANSPOSE(Inputs!F$10:F$19))} -> N/A | AB56: N/A | AC56: N/A | AD56: N/A | AE56: N/A | AF56: N/A | AG56: N/A | AH56: N/A | AI56: N/A | AJ56: N/A
Y57: Preference Multiple | AA57: {=IF(TRANSPOSE(Inputs!G$10:G$19)=0,0,TRANSPOSE(Inputs!G$10:G$19))} -> 1 | AB57: 1 | AC57: 1 | AD57: 1 | AE57: 1 | AF57: 1 | AG57: 1 | AH57: 1 | AI57: 1 | AJ57: 1
Y58: Cap | AA58: {=IF(TRANSPOSE(Inputs!H$10:H$19)=0,0,TRANSPOSE(Inputs!H$10:H$19))} -> 2 | AB58: 2 | AC58: 2 | AD58: 2 | AE58: 2 | AF58: 2 | AG58: 2 | AH58: 2 | AI58: 2 | AJ58: 2
Y59: Participating Preferred | AA59: =IF(AA57="","",IF(AA58<=AA57,"No","Yes")) -> Yes | AB59: =IF(AB57="","",IF(AB58<=AB57,"No","Yes")) -> Yes | AC59: =IF(AC57="","",IF(AC58<=AC57,"No","Yes")) -> Yes | AD59: =IF(AD57="","",IF(AD58<=AD57,"No","Yes")) -> Yes | AE59: =IF(AE57="","",IF(AE58<=AE57,"No","Yes")) -> Yes | AF59: =IF(AF57="","",IF(AF58<=AF57,"No","Yes")) -> Yes | AG59: =IF(AG57="","",IF(AG58<=AG57,"No","Yes")) -> Yes | AH59: =IF(AH57="","",IF(AH58<=AH57,"No","Yes")) -> Yes | ... AJ59: =IF(AJ57="","",IF(AJ58<=AJ57,"No","Yes")) -> Yes
Y60: Seniority Rank | AA60: {=IF(TRANSPOSE(Inputs!I$10:I$19)=0,"",TRANSPOSE(Inputs!I$10:I$19))} -> 10 | AB60: 10 | AC60: 2 | AD60: 1 | AE60: 10 | AF60: 10 | AG60: 10 | AH60: 10 | AI60: 10 | AJ60: 10
Y61: Conversion Ratio | AA61: {=IF(TRANSPOSE(Inputs!J$10:J$19)=0,0,TRANSPOSE(Inputs!J$10:J$19))} -> 1 | AB61: 1 | AC61: 1 | AD61: 1 | AE61: 1 | AF61: 1 | AG61: 1 | AH61: 1 | AI61: 1 | AJ61: 1
Y62: Round CSE | AA62: =IFERROR(AA61*AN27,"") -> 5010000 | AB62: =IFERROR(AB61*AO27,"") -> 5010000 | AC62: =IFERROR(AC61*AP27,"") -> 6010000 | AD62: =IFERROR(AD61*AQ27,"") -> 10010000 | AE62: =IFERROR(AE61*AR27,"") -> 0 | AF62: =IFERROR(AF61*AS27,"") -> 0 | AG62: =IFERROR(AG61*AT27,"") -> 0 | AH62: =IFERROR(AH61*AU27,"") -> 0 | ... AJ62: =IFERROR(AJ61*AW27,"") -> 0
